Workbook

Sheet Demanda Bruta
A1: processo | B1: modalidade | C1: nivel | D1: inicio | E1: termino | F1: cpf_proponente | G1: proponente | H1: link_cvlattes_proponente | I1: beneficiario | J1: orientador_proponente | K1: membros_equipe | L1: proposta | M1: titulo_projeto | N1: programa | O1: ca | P1: grande_area_conhecimento | Q1: area_conhecimento | R1: instituicao_origem | S1: instituicao_origem_sigla | T1: instituicao_origem_uf | U1: instituicao_origem_regiao | V1: instituicao_origem_pais | W1: instituicao_destino | X1: instituicao_destino_sigla | Y1: instituicao_destino_uf | Z1: instituicao_destino_regiao | AA1: instituicao_destino_pais | AB1: diretoria | AC1: unidade | AD1: data_envio | AE1: hora_envio | AF1: data_carga | AG1: hora_carga | AH1: quantidade_bolsa | AI1: valor_bolsa | AJ1: valor_custeio | AK1: valor_capital | AL1: valor_total | AM1: instituicao_vinculo | AN1: sigla_inst_vinculo | AO1: uf_inst_vinculo | AP1: regiao_inst_vinculo | AQ1: pais_inst_vinculo | AR1: id_lattes | AS1: data_importacao | AT1: sigla_chamada | AU1: nome_chamada | AV1: nome_chamada_arquivo | AW1: numero_chamada | AX1: linha_chamada | AY1: inicio_submissao | AZ1: termino_submissao | BA1: email | BB1: Número do Processo | BC1: Nome do Pesquisador | BD1: Instituição de Execução do Processo | BE1: Sigla da Instituição | BF1: Pré-Selecionado? | BG1: Instituição Permitida (MCTI)? | BH1: Ano do Primeiro Doutorado | BI1: Enviou Carta de Anuência? | BJ1: Faixa/Linha da Proposta | BK1: Faixa Majoritária da Instituição | BL1: Faixa Majoritária (=Faixa=ESQUERDA(Majoritária;7)) | BM1: Vínculo com Inst. Executora? | BN1: Vínculo Executora é Celetista/Estatutário? | BO1: Vínculos Ativos (Lattes) | BP1: Sendo Avaliada?
A2: 402356/2026-8 | B2: APQ | D2: 46204 | E2: 47664 | F2: 46624198087 | G2: Alexandre Bragio Bonaldo | H2: http://lattes.cnpq.br/8721994758453503 | I2: Alexandre Bragio Bonaldo | K2: Alexandre Bragio Bonaldo, Antonio Domingos Brescovit, Facundo Martín Labarque, Leonardo Sousa Carvalho, Ivan Luiz Fiorini de Magalhães, Martin Ramirez, Paulo Roberto Pantoja Gomes, Marcos Quintino Drago Bisneto, Cláudio | L2: 5116854 | M2: Sistemática e taxonomia integrativa de aranhas-soldado e aranhas-raio (Araneae: Corinnidae Karsh, 1880; Theridiosomatidae Simon, 1881) | N2: PROGRAMA BASICO DE ZOOLOGIA E RECURSOS PESQUEIROS DE AGUAS INTERIORES | O2: ZO | P2: Ciências Biológicas | Q2: Taxonomia dos Grupos Recentes | R2: Museu Paraense Emílio Goeldi | S2: MPEG | T2: PA | U2: NO | V2: Brasil | W2: Museu Paraense Emílio Goeldi | X2: MPEG | Y2: PA | Z2: NO | AA2: Brasil | AB2: DCTI | AC2: COEBI | AD2: 27/06/2026 | AE2: 15:54:01 | AF2: 27/06/2026 | AG2: 15:54:21 | AH2: 4 | AI2: 443040 | AJ2: 44000 | AK2: 0 | AL2: 487040 | AM2: Museu Paraense Emílio Goeldi | AN2: MPEG | AO2: PA | AP2: NO | AQ2: Brasil | AR2: 8721994758453503 | AS2: 46202.465 | AT2: PCI2026 | AU2: Chamada CNPq/MCTI/FNDCT Nº 12/2026 - Programa PCI | AV2: Chamada: Chamada CNPq/MCTI/FNDCT Nº 12/2026 - Faixa 3: Projetos de Pesquisa vinculados a | AW2: 12/2026 | AX2: Chamada CNPq/MCTI/FNDCT Nº 12/2026 - Faixa 3: Projetos de Pesquisa vinculados a UPs Grandes (acima de 200 servidores) | AY2: 27/04/2026 | AZ2: 27/06/2026 | BA2: bonaldo@museu-goeldi.br | BB2: 402356/2026-8 | BC2: Alexandre Bragio Bonaldo | BD2: Museu Paraense Emílio Goeldi | BE2: MPEG | BF2: =IF(AND(BG2,BI2,BL2,BM2),TRUE,FALSE) -> TRUE | BG2: TRUE | BH2: 1999 | BI2: TRUE | BJ2: Faixa 3 | BK2: Faixa 3 (24 propostas) | BL2: TRUE | BM2: TRUE | BN2: TRUE | BO2: - Museu Paraense Emílio Goeldi: (Pesquisador Titular) - Museu Paraense Emílio Goeldi: (Servidor público - Curador das coleções de Arachnida e Myriapoda) - Instituto Butantan: (COLABORADOR - Colaborador) - Universidade Federal do Pará: (COLABORADOR - Professor Pós-Graduação em Zoologia) - Universidade Federal do Pará: (COLABORADOR - Vice-Coordenador Pós-Graduação Zoologia) - Universidade Federal do Pará: (COLABORADOR - Coordenador - Programa de PG em Zoologia) - Museo Argentino de Ciencias Naturales Bernardino Rivadavia: (em branco) | BP2: =IF(IFERROR(VLOOKUP(A2,[1]Planilha1!$A:$A,1,0),FALSE)=FALSE,FALSE,TRUE) -> TRUE
A3: 400950/2026-0 | B3: APQ | D3: 46204 | E3: 47664 | F3: 80777376504 | G3: Alfeu Joãozinho Sguarezi Filho | H3: http://lattes.cnpq.br/6603067354811112 | I3: Alfeu Joãozinho Sguarezi Filho | K3: Alfeu Joãozinho Sguarezi Filho, Luis Felipe Normandia Lourenço, Darlan Alexandria Fernandes, Alain Segundo Potts, Jefferson Souza Costa, Yuri de Oliveira Cota, Vitor da Silva Jorge, Angelo dos Santos Lunardi, Marco Estaban Rivera | L3: 5105890 | M3: Desenvolvimento de técnicas de controle para um conversor de potência aplicado na integração de fontes de energia renováveis a rede elétrica. | N3: PROGRAMA BASICO DE ENGENHARIA ELETRICA | O3: EE | P3: Engenharias | Q3: Eletrônica de Potência | R3: Universidade Federal do ABC | S3: UFABC | T3: SP | U3: SE | V3: Brasil | W3: Universidade Federal do ABC | X3: UFABC | Y3: SP | Z3: SE | AA3: Brasil | AB3: DCTI | AC3: COENG | AD3: 08/05/2026 | AE3: 10:09:48 | AF3: 08/05/2026 | AG3: 10:09:55 | AH3: 9 | AI3: 1304800 | AJ3: 130000 | AK3: 0 | AL3: 1434800 | AM3: Universidade Federal do ABC | AN3: UFABC | AO3: SP | AP3: SE | AQ3: Brasil | AR3: 6603067354811112 | AS3: 46202.465 | AT3: PCI2026 | AU3: Chamada CNPq/MCTI/FNDCT Nº 12/2026 - Programa PCI | AV3: Chamada: Chamada CNPq/MCTI/FNDCT Nº 12/2026 - Faixa 3: Projetos de Pesquisa vinculados a | AW3: 12/2026 | AX3: Chamada CNPq/MCTI/FNDCT Nº 12/2026 - Faixa 3: Projetos de Pesquisa vinculados a UPs Grandes (acima de 200 servidores) | AY3: 27/04/2026 | AZ3: 27/06/2026 | BA3: alfeu_sguarezi@yahoo.com.br | BB3: 400950/2026-0 | BC3: Alfeu Joãozinho Sguarezi Filho | BD3: Universidade Federal do ABC | BE3: UFABC | BF3: =IF(AND(BG3,BI3,BL3,BM3),TRUE,FALSE) -> FALSE | BG3: FALSE | BH3: 2010 | BI3: FALSE | BJ3: Faixa 3 | BK3: Faixa 3 (1 propostas) | BL3: TRUE | BM3: TRUE | BN3: TRUE | BO3: - Universidade Federal do ABC: (Servidor público - Professor Associado IV) - Sociedade Brasileira de Automática: (Membro comitê - Vice-coordenador Sistemas de Potência) - Universidade de São Paulo: (Docente PGEE - Docente PPGEE) - International Federation of Automatic Control: (Membro - Não há.) | BP3: =IF(IFERROR(VLOOKUP(A3,[1]Planilha1!$A:$A,1,0),FALSE)=FALSE,FALSE,TRUE) -> FALSE
A4: 401867/2026-9 | B4: APQ | D4: 46204 | E4: 47664 | F4: 02837590703 | G4: Aline Theodoro Toci | H4: http://lattes.cnpq.br/2923907838228544 | I4: Aline Theodoro Toci | K4: Aline Theodoro Toci, Rodrigo Sequinel, Fernando Augusto de Freitas, Rafaella Costa Bonugli Santos, Mayara Ali Dahrouj, Luana Estefani Knaul, Aldo Sindulfo Barboza Valdez | L4: 5116300 | M4: Perfil químico e biológico de canetas emagrecedoras a base de tirzepatida e retatrutida apreendidas na Triplice Fronteira (PY-BR-AR) | N4: PROGRAMA BASICO DE QUIMICA | O4: QU | P4: Ciências Exatas e da Terra | Q4: Química Analítica | R4: Universidade Federal da Integração Latino-Americana | S4: UNILA | T4: PR | U4: SU | V4: Brasil | W4: Universidade Federal da Integração Latino-Americana | X4: UNILA | Y4: PR | Z4: SU | AA4: Brasil | AB4: DCTI | AC4: COCQG | AD4: 23/06/2026 | AE4: 12:36:12 | AF4: 23/06/2026 | AG4: 13:49:10 | AH4: 5 | AI4: 461760 | AJ4: 60000 | AK4: 0 | AL4: 521760 | AM4: Universidade Federal da Integração Latino-Americana | AN4: UNILA | AO4: PR | AP4: SU | AQ4: Brasil | AR4: 2923907838228544 | AS4: 46202.465 | AT4: PCI2026 | AU4: Chamada CNPq/MCTI/FNDCT Nº 12/2026 - Programa PCI | AV4: Chamada: Chamada CNPq/MCTI/FNDCT Nº 12/2026 - Faixa 3: Projetos de Pesquisa vinculados a | AW4: 12/2026 | AX4: Chamada CNPq/MCTI/FNDCT Nº 12/2026 - Faixa 3: Projetos de Pesquisa vinculados a UPs Grandes (acima de 200 servidores) | AY4: 27/04/2026 | AZ4: 27/06/2026 | BA4: attoci@yahoo.com.br | BB4: 401867/2026-9 | BC4: Aline Theodoro Toci | BD4: Universidade Federal da Integração Latino-Americana | BE4: UNILA | BF4: =IF(AND(BG4,BI4,BL4,BM4),TRUE,FALSE) -> FALSE | BG4: FALSE | BH4: 2010 | BI4: FALSE | BJ4: Faixa 3 | BK4: Faixa 3 (4 propostas) | BL4: TRUE | BM4: TRUE | BN4: TRUE | BO4: - Universidade Federal da Integração Latino-Americana: (Servidor público - Adjunto A) - Fundação Araucária de Apoio ao Desenvolvimento Científico e Tecnológico: (Membro de comitê assessor) | BP4: =IF(IFERROR(VLOOKUP(A4,[1]Planilha1!$A:$A,1,0),FALSE)=FALSE,FALSE,TRUE) -> FALSE
A5: 402099/2026-5 | B5: APQ | D5: 46204 | E5: 47664 | F5: 72842792653 | G5: Ana Lúcia da Costa Prudente | H5: http://lattes.cnpq.br/1008924786363328 | I5: Ana Lúcia da Costa Prudente | K5: Ana Lúcia da Costa Prudente, Roberta Graboski Mendes, Luciano Nicolás Naka, Kaelle Vaccari Silva Caldeira, Patricia Rodrigues da Silva, João Fabricio de Melo Sarmento, Bruna Mirely da Silva Costa, Giovanna Olivarez Couto | L5: 5116591 | M5: Origem e Diversificação de Vertebrados Terrestres na Amazônia: Uma Abordagem Integrativa | N5: PROGRAMA BASICO DE ZOOLOGIA E RECURSOS PESQUEIROS DE AGUAS INTERIORES | O5: ZO | P5: Ciências Biológicas | Q5: Taxonomia dos Grupos Recentes | R5: Museu Paraense Emílio Goeldi | S5: MPEG | T5: PA | U5: NO | V5: Brasil | W5: Museu Paraense Emílio Goeldi | X5: MPEG | Y5: PA | Z5: NO | AA5: Brasil | AB5: DCTI | AC5: COEBI | AD5: 26/06/2026 | AE5: 15:56:04 | AF5: 27/06/2026 | AG5: 09:52:34 | AH5: 11 | AI5: 1054820 | AJ5: 149658.89 | AK5: 0 | AL5: 1204478.9 | AM5: Museu Paraense Emílio Goeldi | AN5: MPEG | AO5: PA | AP5: NO | AQ5: Brasil | AR5: 1008924786363328 | AS5: 46202.465 | AT5: PCI2026 | AU5: Chamada CNPq/MCTI/FNDCT Nº 12/2026 - Programa PCI | AV5: Chamada: Chamada CNPq/MCTI/FNDCT Nº 12/2026 - Faixa 3: Projetos de Pesquisa vinculados a | AW5: 12/2026 | AX5: Chamada CNPq/MCTI/FNDCT Nº 12/2026 - Faixa 3: Projetos de Pesquisa vinculados a UPs Grandes (acima de 200 servidores) | AY5: 27/04/2026 | AZ5: 27/06/2026 | BA5: prudente@museu-goeldi.br | BB5: 402099/2026-5 | BC5: Ana Lúcia da Costa Prudente | BD5: Museu Paraense Emílio Goeldi | BE5: MPEG | BF5: =IF(AND(BG5,BI5,BL5,BM5),TRUE,FALSE) -> TRUE | BG5: TRUE | BH5: 1998 | BI5: TRUE | BJ5: Faixa 3 | BK5: Faixa 3 (24 propostas) | BL5: TRUE | BM5: TRUE | BN5: TRUE | BO5: - Museu Paraense Emílio Goeldi: (Servidor público - Pesquisador Titular) | BP5: =IF(IFERROR(VLOOKUP(A5,[1]Planilha1!$A:$A,1,0),FALSE)=FALSE,FALSE,TRUE) -> TRUE
A6: 401036/2026-0 | B6: APQ | D6: 46204 | E6: 47664 | F6: 56038496220 | G6: Ana Lucia M Wanzeller | H6: http://lattes.cnpq.br/8983339131944366 | I6: Ana Lucia M Wanzeller | K6: Ana Lucia M Wanzeller, Anderson Bentes de Lima, Ana Cecília Ribeiro Cruz, Ana Claudia da Silva Ribeiro, Joaquim Pinto Nunes Neto, Paula Renata Lima Machado Farias, Lívia Caricio Martins, Livia Medeiros Neves Casseb, Valéria | L6: 5111149 | M6: Nanotecnologia farmacêutica aplicada ao desenvolvimento de antivirais contra arbovírus: avaliação in vitro e in vivo de nanoemulsões contendo óleos essenciais da biodiversidade amazônica. | N6: PROGRAMA BASICO DE MICROBIOLOGIA | O6: MP | P6: Ciências Biológicas | Q6: Virologia | R6: Instituto Evandro Chagas | S6: IEC | T6: PA | U6: NO | V6: Brasil | W6: Instituto Evandro Chagas | X6: IEC | Y6: PA | Z6: NO | AA6: Brasil | AB6: DCTI | AC6: COBIO | AD6: 23/05/2026 | AE6: 09:22:51 | AF6: 23/05/2026 | AG6: 09:23:00 | AH6: 8 | AI6: 1394640 | AJ6: 104200 | AK6: 0 | AL6: 1498840 | AM6: Instituto Evandro Chagas | AN6: IEC | AO6: PA | AP6: NO | AQ6: Brasil | AR6: 8983339131944366 | AS6: 46202.465 | AT6: PCI2026 | AU6: Chamada CNPq/MCTI/FNDCT Nº 12/2026 - Programa PCI | AV6: Chamada: Chamada CNPq/MCTI/FNDCT Nº 12/2026 - Faixa 3: Projetos de Pesquisa vinculados a | AW6: 12/2026 | AX6: Chamada CNPq/MCTI/FNDCT Nº 12/2026 - Faixa 3: Projetos de Pesquisa vinculados a UPs Grandes (acima de 200 servidores) | AY6: 27/04/2026 | AZ6: 27/06/2026 | BA6: anawanzeller@iec.gov.br | BB6: 401036/2026-0 | BC6: Ana Lucia M Wanzeller | BD6: Instituto Evandro Chagas | BE6: IEC | BF6: =IF(AND(BG6,BI6,BL6,BM6),TRUE,FALSE) -> FALSE | BG6: FALSE | BH6: 2017 | BI6: FALSE | BJ6: Faixa 3 | BK6: Faixa 3 (1 propostas) | BL6: TRUE | BM6: TRUE | BN6: TRUE | BO6: - Instituto Evandro Chagas: (Servidor público - Pesquisadora em Saúde Pública) - Instituto Evandro Chagas: (Servidor público - Pesquisadora em Saúde Pública) - Instituto Evandro Chagas: (VICE COORDENAÇÃO PPGV - VICE-COORDENADORA DO PPGV) - Instituto Evandro Chagas: (em branco) | BP6: =IF(IFERROR(VLOOKUP(A6,[1]Planilha1!$A:$A,1,0),FALSE)=FALSE,FALSE,TRUE) -> FALSE
A7: 401028/2026-7 | B7: APQ | D7: 46204 | E7: 47664 | F7: 11464843805 | G7: Anderson Zanardi de Freitas | H7: http://lattes.cnpq.br/7935699829401769 | I7: Anderson Zanardi de Freitas | K7: Anderson Zanardi de Freitas, Anselmo Sigari Moriscot, Niklaus Ursus Wetter, Patrick Jack Spencer, Daniel Perez Vieira, André Mourão Batista, Martha Simões Ribeiro | L7: 5110772 | M7: Capacitação Científica e Tecnológica em Espectroscopia Raman em Nanoescala Aplicada a Sistemas Biológicos | N7: PROGRAMA BASICO DE FISICA | O7: FA | P7: Ciências Exatas e da Terra | Q7: Prop. Óticas e Espectrosc. da Mat. Condens; Outras Inter. da | R7: COMISSAO NACIONAL DE ENERGIA NUCLEAR | S7: CNEN | T7: RJ | U7: SE | V7: Brasil | W7: COMISSAO NACIONAL DE ENERGIA NUCLEAR | X7: CNEN | Y7: RJ | Z7: SE | AA7: Brasil | AB7: DCTI | AC7: COCEC | AD7: 22/05/2026 | AE7: 13:03:36 | AF7: 22/05/2026 | AG7: 14:04:55 | AH7: 6 | AI7: 1272960 | AJ7: 119000 | AK7: 0 | AL7: 1391960 | AR7: 7935699829401769 | AS7: 46202.465 | AT7: PCI2026 | AU7: Chamada CNPq/MCTI/FNDCT Nº 12/2026 - Programa PCI | AV7: Chamada: Chamada CNPq/MCTI/FNDCT Nº 12/2026 - Faixa 3: Projetos de Pesquisa vinculados a | AW7: 12/2026 | AX7: Chamada CNPq/MCTI/FNDCT Nº 12/2026 - Faixa 3: Projetos de Pesquisa vinculados a UPs Grandes (acima de 200 servidores) | AY7: 27/04/2026 | AZ7: 27/06/2026 | BA7: freitas.az@gmail.com | BB7: 401028/2026-7 | BC7: Anderson Zanardi de Freitas | BD7: COMISSAO NACIONAL DE ENERGIA NUCLEAR | BE7: CNEN | BF7: =IF(AND(BG7,BI7,BL7,BM7),TRUE,FALSE) -> TRUE | BG7: TRUE | BH7: 2007 | BI7: TRUE | BJ7: Faixa 3 | BK7: Faixa 3 (32 propostas) | BL7: TRUE | BM7: TRUE | BN7: TRUE | BO7: - Instituto de Pesquisas Enegéticas e Nucleares: (Servidor público - Tecnologista) | BP7: =IF(IFERROR(VLOOKUP(A7,[1]Planilha1!$A:$A,1,0),FALSE)=FALSE,FALSE,TRUE) -> TRUE
A8: 402246/2026-8 | B8: APQ | D8: 46204 | E8: 47664 | F8: 05462482680 | G8: Andre Augusto Campagnole dos Santos | H8: http://lattes.cnpq.br/4652863024621768 | I8: Andre Augusto Campagnole dos Santos | K8: Andre Augusto Campagnole dos Santos, Graiciany de Paula Barros, Vitor Vasconcelos Araújo Silva, Wesley Cecilio silva, Higor Fabiano Pereira de Castro, Edson Ribeiro, Eduardo Tadeu Stehling Saraiva, Claudio Cunha Lopes, | L8: 5116744 | M8: Investigação Numérico-Experimental de Protótipos Fabricados por Manufatura Aditiva para Desenvolvimento e Nacionalização de Componentes de Reatores SMR | N8: PROGRAMA BASICO DE ENGENHARIA NUCLEAR | O8: EN | P8: Engenharias | Q8: Transferência de Calor em Reatores | R8: COMISSAO NACIONAL DE ENERGIA NUCLEAR | S8: CNEN | T8: RJ | U8: SE | V8: Brasil | W8: COMISSAO NACIONAL DE ENERGIA NUCLEAR | X8: CNEN | Y8: RJ | Z8: SE | AA8: Brasil | AB8: DCTI | AC8: COBEN | AD8: 26/06/2026 | AE8: 17:25:01 | AF8: 27/06/2026 | AG8: 10:01:36 | AH8: 3 | AI8: 542880 | AJ8: 78416 | AK8: 0 | AL8: 621296 | AM8: COMISSAO NACIONAL DE ENERGIA NUCLEAR | AN8: CNEN | AO8: RJ | AP8: SE | AQ8: Brasil | AR8: 4652863024621768 | AS8: 46202.465 | AT8: PCI2026 | AU8: Chamada CNPq/MCTI/FNDCT Nº 12/2026 - Programa PCI | AV8: Chamada: Chamada CNPq/MCTI/FNDCT Nº 12/2026 - Faixa 3: Projetos de Pesquisa vinculados a | AW8: 12/2026 | AX8: Chamada CNPq/MCTI/FNDCT Nº 12/2026 - Faixa 3: Projetos de Pesquisa vinculados a UPs Grandes (acima de 200 servidores) | AY8: 27/04/2026 | AZ8: 27/06/2026 | BA8: acampagnole@yahoo.com.br | BB8: 402246/2026-8 | BC8: Andre Augusto Campagnole dos Santos | BD8: COMISSAO NACIONAL DE ENERGIA NUCLEAR | BE8: CNEN | BF8: =IF(AND(BG8,BI8,BL8,BM8),TRUE,FALSE) -> TRUE | BG8: TRUE | BH8: 2012 | BI8: TRUE | BJ8: Faixa 3 | BK8: Faixa 3 (32 propostas) | BL8: TRUE | BM8: TRUE | BN8: TRUE | BO8: - COMISSAO NACIONAL DE ENERGIA NUCLEAR: (Pesquisador) - COMISSAO NACIONAL DE ENERGIA NUCLEAR: (Professor - Professor permanente) - COMISSAO NACIONAL DE ENERGIA NUCLEAR: (Coordenador da pós-graduação - Coordenador da pós-graduação CDTN) - COMISSAO NACIONAL DE ENERGIA NUCLEAR: (Servidor público - Chefe substituto DIFES - Divisão de Formação) - Comissão Nacional de Energia Nuclear: (Membro de comitê assessor) | BP8: =IF(IFERROR(VLOOKUP(A8,[1]Planilha1!$A:$A,1,0),FALSE)=FALSE,FALSE,TRUE) -> TRUE
A9: 402067/2026-6 | B9: APQ | D9: 46204 | E9: 47664 | F9: 07730923742 | G9: André dos Santos Bragança Gil | H9: http://lattes.cnpq.br/4874787664520093 | I9: André dos Santos Bragança Gil | K9: André dos Santos Bragança Gil, Julia Meirelles, Josiane Santana Monteiro, Adriene Mayra da Silva Soares, Jadson José Souza de Oliveira, Bárbara Dunck Oliveira, Flavia Machado Durgante, Caroline da Cruz Vasconcelos | L9: 5116558 | M9: Flora e Funga da Floresta Nacional de Caxiuanã: Taxonomia, Fortalecimento de Acervos e Inovação Tecnológica para a Conservação da Biodiversidade Amazônica | N9: PROGRAMA BASICO DE BOTANICA | O9: BO | P9: Ciências Biológicas | Q9: Taxonomia Vegetal | R9: Museu Paraense Emílio Goeldi | S9: MPEG | T9: PA | U9: NO | V9: Brasil | W9: Museu Paraense Emílio Goeldi | X9: MPEG | Y9: PA | Z9: NO | AA9: Brasil | AB9: DCTI | AC9: COEBI | AD9: 26/06/2026 | AE9: 13:06:04 | AF9: 27/06/2026 | AG9: 09:50:41 | AH9: 14 | AI9: 1041040 | AJ9: 146561.05 | AK9: 0 | AL9: 1187601.1 | AM9: Museu Paraense Emílio Goeldi | AN9: MPEG | AO9: PA | AP9: NO | AQ9: Brasil | AR9: 4874787664520093 | AS9: 46202.465 | AT9: PCI2026 | AU9: Chamada CNPq/MCTI/FNDCT Nº 12/2026 - Programa PCI | AV9: Chamada: Chamada CNPq/MCTI/FNDCT Nº 12/2026 - Faixa 3: Projetos de Pesquisa vinculados a | AW9: 12/2026 | AX9: Chamada CNPq/MCTI/FNDCT Nº 12/2026 - Faixa 3: Projetos de Pesquisa vinculados a UPs Grandes (acima de 200 servidores) | AY9: 27/04/2026 | AZ9: 27/06/2026 | BA9: asbgil@yahoo.com.br | BB9: 402067/2026-6 | BC9: André dos Santos Bragança Gil | BD9: Museu Paraense Emílio Goeldi | BE9: MPEG | BF9: =IF(AND(BG9,BI9,BL9,BM9),TRUE,FALSE) -> TRUE | BG9: TRUE | BH9: 2012 | BI9: TRUE | BJ9: Faixa 3 | BK9: Faixa 3 (24 propostas) | BL9: TRUE | BM9: TRUE | BN9: TRUE | BO9: - Museu Paraense Emílio Goeldi: (Servidor público - Pesquisador Titular III) - Universidade Federal Rural da Amazônia/Museu Paraense Emílio Goeldi: (Docente permanente - Professor orientador) - Instituto Nacional de Pesquisas da Amazônia: (COLABORADOR - Colaborador no projeto HerbSpectra-Amazônia) | BP9: =IF(IFERROR(VLOOKUP(A9,[1]Planilha1!$A:$A,1,0),FALSE)=FALSE,FALSE,TRUE) -> TRUE
A10: 401115/2026-7 | B10: APQ | D10: 46204 | E10: 47664 | F10: 02786029678 | G10: André Luís Silva | H10: http://lattes.cnpq.br/3393832875052048 | I10: André Luís Silva | K10: André Luís Silva, Pamella Thaís Magalhães Ferreira, Daniel Magalhães Bicalho, André Fonseca Amâncio, Abelard Ramos Fernandes, Saulo Hallah | L10: 5114814 | M10: SISTEMA DE DIAGNÓSTICO DE MATURIDADE E SOBREVIVÊNCIA : DESENVOLVIMENTO, DEMONSTRAÇÃO E TRANSFERÊNCIA DE TECNOLOGIA DE GESTÃO PARA INCUBADORAS DE EMPRESAS BRASILEIRAS | N10: PROGRAMA BASICO DE ADMINISTRACAO | O10: AE | P10: Ciências Sociais Aplicadas | Q10: Administração de Setores Específicos | R10: Universidade Federal de Ouro Preto | S10: UFOP | T10: MG | U10: SE | V10: Brasil | W10: Universidade Federal de Ouro Preto | X10: UFOP | Y10: MG | Z10: SE | AA10: Brasil | AB10: DCTI | AC10: COSAE | AD10: 26/05/2026 | AE10: 15:11:21 | AF10: 27/05/2026 | AG10: 16:56:19 | AH10: 5 | AI10: 1110720 | AJ10: 61000 | AK10: 0 | AL10: 1171720 | AM10: Universidade Federal de Ouro Preto | AN10: UFOP | AO10: MG | AP10: SE | AQ10: Brasil | AR10: 3393832875052048 | AS10: 46202.465 | AT10: PCI2026 | AU10: Chamada CNPq/MCTI/FNDCT Nº 12/2026 - Programa PCI | AV10: Chamada: Chamada CNPq/MCTI/FNDCT Nº 12/2026 - Faixa 3: Projetos de Pesquisa vinculados a | AW10: 12/2026 | AX10: Chamada CNPq/MCTI/FNDCT Nº 12/2026 - Faixa 3: Projetos de Pesquisa vinculados a UPs Grandes (acima de 200 servidores) | AY10: 27/04/2026 | AZ10: 27/06/2026 | BA10: andre.silva@ufop.edu.br | BB10: 401115/2026-7 | BC10: André Luís Silva | BD10: Universidade Federal de Ouro Preto | BE10: UFOP | BF10: =IF(AND(BG10,BI10,BL10,BM10),TRUE,FALSE) -> FALSE | BG10: FALSE | BH10: 2016 | BI10: FALSE | BJ10: Faixa 3 | BK10: Faixa 3 (1 propostas) | BL10: TRUE | BM10: TRUE | BN10: TRUE | BO10: - Universidade Federal de Ouro Preto: (Servidor público - Professor Associado) - Parque Tecnológico de Belo Horizonte: (COLABORADOR - Pesquisador) | BP10: =IF(IFERROR(VLOOKUP(A10,[1]Planilha1!$A:$A,1,0),FALSE)=FALSE,FALSE,TRUE) -> FALSE
A11: 401992/2026-8 | B11: APQ | D11: 46204 | E11: 47664 | F11: 42437784268 | G11: Anna Luiza Ilkiu Borges Benkendorff | H11: http://lattes.cnpq.br/4847808223159236 | I11: Anna Luiza Ilkiu Borges Benkendorff | K11: Anna Luiza Ilkiu Borges Benkendorff, Ana Carla Feio dos Santos, Paula Godinho Ribeiro, Fúvio Rubens Oliveira da Silva, Sâmia Batista e Silva, Manolo Cleiton Costa de Freitas, Patricia Magalhães Pereira Silva, Flavia Machado | L11: 5116475 | M11: Consolidação da Pesquisa e Inovação do Museu Goeldi na Amazônia: Capacitação Tecnológica para o Manejo e Conservação da FLONA de Caxiuanã | N11: Programa Especial de Biotecnologia e Recursos Genéticos - COBRG | O11: BI | P11: Ciências Biológicas | Q11: Biotecnologia Ambiental e Recursos Naturais | R11: Museu Paraense Emílio Goeldi | S11: MPEG | T11: PA | U11: NO | V11: Brasil | W11: Museu Paraense Emílio Goeldi | X11: MPEG | Y11: PA | Z11: NO | AA11: Brasil | AB11: DCTI | AC11: COBEN | AD11: 25/06/2026 | AE11: 16:33:38 | AF11: 25/06/2026 | AG11: 16:50:30 | AH11: 10 | AI11: 1299300 | AJ11: 130000 | AK11: 0 | AL11: 1429300 | AM11: Museu Paraense Emílio Goeldi | AN11: MPEG | AO11: PA | AP11: NO | AQ11: Brasil | AR11: 4847808223159236 | AS11: 46202.465 | AT11: PCI2026 | AU11: Chamada CNPq/MCTI/FNDCT Nº 12/2026 - Programa PCI | AV11: Chamada: Chamada CNPq/MCTI/FNDCT Nº 12/2026 - Faixa 3: Projetos de Pesquisa vinculados a | AW11: 12/2026 | AX11: Chamada CNPq/MCTI/FNDCT Nº 12/2026 - Faixa 3: Projetos de Pesquisa vinculados a UPs Grandes (acima de 200 servidores) | AY11: 27/04/2026 | AZ11: 27/06/2026 | BA11: ilkiu-borges@museu-goeldi.br | BB11: 401992/2026-8 | BC11: Anna Luiza Ilkiu Borges Benkendorff | BD11: Museu Paraense Emílio Goeldi | BE11: MPEG | BF11: =IF(AND(BG11,BI11,BL11,BM11),TRUE,FALSE) -> TRUE | BG11: TRUE | BH11: 2005 | BI11: TRUE | BJ11: Faixa 3 | BK11: Faixa 3 (24 propostas) | BL11: TRUE | BM11: TRUE | BN11: TRUE | BO11: - Museu Paraense Emílio Goeldi: (Servidor público - Editora Associada de Botânica) - Museu Paraense Emílio Goeldi: (Servidor público - Pesquisador Titular III) - Universidade Federal Rural da Amazônia: (Professor da Pós-Graduação) - Universidade Federal Rural da Amazônia: (COLABORADOR - Coordenadora de Pós-graduação) | BP11: =IF(IFERROR(VLOOKUP(A11,[1]Planilha1!$A:$A,1,0),FALSE)=FALSE,FALSE,TRUE) -> TRUE
A12: 401313/2026-3 | B12: APQ | D12: 46204 | E12: 47664 | F12: 87302128715 | G12: Antônio Carlos de Abreu Mól | H12: http://lattes.cnpq.br/1168989222280325 | I12: Antônio Carlos de Abreu Mól | K12: Antônio Carlos de Abreu Mól, Cláudio Márcio do Nascimento Abreu Pereira, Cláudio Henrique dos Santos Grecco, Paulo Victor Rodrigues de Carvalho, Eugenio Rangel Marins, Ana Paula Legey de Siqueira, Sheila da Silva Ferreira | L12: 5115674 | M12: CIDADE VIRTUAL DA CIÊNCIA: METODOLOGIAS EDUCATIVAS PARA POPULARIZAÇÃO DA CIÊNCIA NUCLEAR E FORMAÇÃO DE EDUCADORES | N12: PROGRAMA BASICO DE ENGENHARIA NUCLEAR | O12: EN | P12: Engenharias | Q12: Tecnologia dos Reatores | R12: Instituto de Engenharia Nuclear | S12: IEN/CNEN | T12: RJ | U12: SE | V12: Brasil | W12: Instituto de Engenharia Nuclear | X12: IEN/CNEN | Y12: RJ | Z12: SE | AA12: Brasil | AB12: DCTI | AC12: COBEN | AD12: 16/06/2026 | AE12: 17:34:33 | AF12: 16/06/2026 | AG12: 17:34:40 | AH12: 6 | AI12: 1048320 | AJ12: 120000 | AK12: 0 | AL12: 1168320 | AM12: COMISSAO NACIONAL DE ENERGIA NUCLEAR | AN12: CNEN | AO12: RJ | AP12: SE | AQ12: Brasil | AR12: 1168989222280325 | AS12: 46202.465 | AT12: PCI2026 | AU12: Chamada CNPq/MCTI/FNDCT Nº 12/2026 - Programa PCI | AV12: Chamada: Chamada CNPq/MCTI/FNDCT Nº 12/2026 - Faixa 3: Projetos de Pesquisa vinculados a | AW12: 12/2026 | AX12: Chamada CNPq/MCTI/FNDCT Nº 12/2026 - Faixa 3: Projetos de Pesquisa vinculados a UPs Grandes (acima de 200 servidores) | AY12: 27/04/2026 | AZ12: 27/06/2026 | BA12: antonio.mol@ien.gov.br | BB12: 401313/2026-3 | BC12: Antônio Carlos de Abreu Mól | BD12: Instituto de Engenharia Nuclear | BE12: IEN/CNEN | BF12: =IF(AND(BG12,BI12,BL12,BM12),TRUE,FALSE) -> TRUE | BG12: TRUE | BH12: 2002 | BI12: TRUE | BJ12: Faixa 3 | BK12: Faixa 3 (2 propostas) | BL12: TRUE | BM12: TRUE | BN12: TRUE | BO12: - COMISSAO NACIONAL DE ENERGIA NUCLEAR: (Servidor público - Tecnologista Sênior,) - COMISSAO NACIONAL DE ENERGIA NUCLEAR: (Servidor público - Pro-Reitor de Ensino) - COMISSAO NACIONAL DE ENERGIA NUCLEAR: (Servidor público - Chefe de Divisão de Ensino) - Fundação Carlos Chagas Filho de Amparo à Pesquisa do Estado do RJ: (COLABORADOR - consultor ad hoc (Ciência da Computação)) - Fundação Carlos Chagas Filho de Amparo à Pesquisa do Estado do RJ: (Pesquisador - Jovem Cientista do Estado do RJ) - Fundação Carlos Chagas Filho de Amparo à Pesquisa do Estado do RJ: (Pesquisador - Coordenador Projeto Pesquisa) - (CNPq) Conselho Nacional de Desenvolvimento Científico e Tecnológico: (Pesquisador - Coordenador Projeto Pesquisa) - (CNPq) Conselho Nacional de Desenvolvimento Científico e Tecnológico: (Pesquisador - Acessor Ad-hoc) - (FAPERJ) Fundação Carlos Chagas Filho de Amparo à Pesq. do Estado do Rio de: (Membro de comitê assessor) - (UGF) universdade gama filho: (Membro de comitê assessor) - (UGF) universdade gama filho: (Membro de comitê assessor) - (CNPq) Conselho Nacional de Desenvolvimento Científico e Tecnológico: (Membro de comitê assessor) - Centro Universitário Carioca: (CELETISTA - PROFESSOR_TITULAR) - Universidade Federal do Rio de Janeiro: (COLABORADOR - colaborador) - Instituto de Ciencia e Tecnologia de Reatores Modulares e Inovadores: (vice-coordenador - Pesquisador) | BP12: =IF(IFERROR(VLOOKUP(A12,[1]Planilha1!$A:$A,1,0),FALSE)=FALSE,FALSE,TRUE) -> TRUE
A13: 402370/2026-0 | B13: APQ | D13: 46204 | E13: 47664 | F13: 80900402849 | G13: Artur Wilson Carbonari | H13: http://lattes.cnpq.br/0983858173807551 | I13: Artur Wilson Carbonari | K13: Artur Wilson Carbonari, Rajendra Narain Saxena, Frederico Antonio Genezini, Gabriel Adolfo Cabrera Pasca, Ronaldo Domingues Mansano, Levy Scalise Maciel, Wanderson Lobato Ferreira, Luciano Fabrício Dias Pereira, | L13: 5116868 | M13: Capacitação Institucional em Tecnologias Nucleares Aplicadas a Semicondutores: Produção de Silício Tipo-N Dopado por Transmutação Neutrônica (NTD) para Dispositivos Fotovoltaicos e Detectores de Radiação de Alta Eficiência | N13: PROGRAMA BASICO DE ENGENHARIA NUCLEAR | O13: EN | P13: Engenharias | Q13: Aplicações Industriais de Radioisótopos | R13: Instituto de Pesquisas Energéticas e Nucleares | S13: IPEN/CNEN | T13: SP | U13: SE | V13: Brasil | W13: Instituto de Pesquisas Energéticas e Nucleares | X13: IPEN/CNEN | Y13: SP | Z13: SE | AA13: Brasil | AB13: DCTI | AC13: COBEN | AD13: 27/06/2026 | AE13: 17:56:32 | AF13: 27/06/2026 | AG13: 17:56:38 | AH13: 5 | AI13: 982800 | AJ13: 130670 | AK13: 0 | AL13: 1113470 | AR13: 0983858173807551 | AS13: 46202.465 | AT13: PCI2026 | AU13: Chamada CNPq/MCTI/FNDCT Nº 12/2026 - Programa PCI | AV13: Chamada: Chamada CNPq/MCTI/FNDCT Nº 12/2026 - Faixa 3: Projetos de Pesquisa vinculados a | AW13: 12/2026 | AX13: Chamada CNPq/MCTI/FNDCT Nº 12/2026 - Faixa 3: Projetos de Pesquisa vinculados a UPs Grandes (acima de 200 servidores) | AY13: 27/04/2026 | AZ13: 27/06/2026 | BA13: artur.wilson.carbonari@cern.ch | BB13: 402370/2026-0 | BC13: Artur Wilson Carbonari | BD13: Instituto de Pesquisas Energéticas e Nucleares | BE13: IPEN/CNEN | BF13: =IF(AND(BG13,BI13,BL13,BM13),TRUE,FALSE) -> FALSE | BG13: TRUE | BH13: 1992 | BI13: FALSE | BJ13: Faixa 3 | BK13: Faixa 3 (6 propostas) | BL13: TRUE | BM13: TRUE | BN13: TRUE | BO13: - Instituto de Pesquisas Energéticas e Nucleares: (Servidor público - PROFESSOR_TITULAR) - Instituto de Pesquisas Energéticas e Nucleares: (Servidor público - Pesquisador titular U III) - Conselho Nacional de Desenvolvimento Científico e Tecnológico: (OUTRO - pesquisador 1C) - Agencia Nacional de Promocion Cientifica y Tecnologica: (OUTRO - Outro (especifique) consultor ad hoc) - Universidade de São Paulo: (OUTRO - PROFESSOR_TITULAR) - European Organization for Nuclear Research: (COLABORADOR - Team leader) - COMISSAO NACIONAL DE ENERGIA NUCLEAR: (em branco) | BP13: =IF(IFERROR(VLOOKUP(A13,[1]Planilha1!$A:$A,1,0),FALSE)=FALSE,FALSE,TRUE) -> FALSE
A14: 402102/2026-6 | B14: APQ | D14: 46204 | E14: 47664 | F14: 38692799823 | G14: Augusto Nobre Gonçalves | H14: http://lattes.cnpq.br/1557063709034165 | I14: Augusto Nobre Gonçalves | K14: Augusto Nobre Gonçalves, Victor Leal Fernandes de Mello Pereira, Haline Dugolin Ceccato, Felipe Andre Mayer Silva, Cecília Vianna Pinheiro, Caroline Modica Custódio, Usama Ahmad, Ana Clara de Araujo Sousa, Fabio Ramos | L14: 5116594 | M14: Dos poliedros de coordenação aos quasicristais: Desenvolvimento de plataforma computacional para análise da complexidade estrutural de sólidos para inovação em caracterização de minerais estratégicos | N14: Programa Basico de Geociência | O14: GC | P14: Ciências Exatas e da Terra | Q14: Mineralogia | R14: Universidade de Brasília | S14: UnB | T14: DF | U14: CO | V14: Brasil | W14: Universidade de Brasília | X14: UnB | Y14: DF | Z14: CO | AA14: Brasil | AB14: DCTI | AC14: COCQG | AD14: 27/06/2026 | AE14: 01:43:58 | AF14: 27/06/2026 | AG14: 09:52:48 | AH14: 8 | AI14: 506640 | AJ14: 73181.33 | AK14: 0 | AL14: 579821.33 | AM14: Universidade de Brasília | AN14: UnB | AO14: DF | AP14: CO | AQ14: Brasil | AR14: 1557063709034165 | AS14: 46202.465 | AT14: PCI2026 | AU14: Chamada CNPq/MCTI/FNDCT Nº 12/2026 - Programa PCI | AV14: Chamada: Chamada CNPq/MCTI/FNDCT Nº 12/2026 - Faixa 3: Projetos de Pesquisa vinculados a | AW14: 12/2026 | AX14: Chamada CNPq/MCTI/FNDCT Nº 12/2026 - Faixa 3: Projetos de Pesquisa vinculados a UPs Grandes (acima de 200 servidores) | AY14: 27/04/2026 | AZ14: 27/06/2026 | BA14: nobre.augusto@gmail.com | BB14: 402102/2026-6 | BC14: Augusto Nobre Gonçalves | BD14: Universidade de Brasília | BE14: UnB | BF14: =IF(AND(BG14,BI14,BL14,BM14),TRUE,FALSE) -> FALSE | BG14: FALSE | BH14: 2020 | BI14: FALSE | BJ14: Faixa 3 | BK14: Faixa 3 (1 propostas) | BL14: TRUE | BM14: TRUE | BN14: TRUE | BO14: - Universidade de Brasília: (Servidor público - Professor Assistente A) | BP14: =IF(IFERROR(VLOOKUP(A14,[1]Planilha1!$A:$A,1,0),FALSE)=FALSE,FALSE,TRUE) -> FALSE
A15: 401010/2026-0 | B15: APQ | D15: 46204 | E15: 47664 | F15: 02755828684 | G15: Bruno Melo Mendes | H15: http://lattes.cnpq.br/7016638154017973 | I15: Bruno Melo Mendes | K15: Bruno Melo Mendes, Tarcisio Passos Ribeiro de Campos, Marco Aurélio de Sousa Lacerda, Bernardo Nunes Borges de Lima, Alberto Mizrahy Campos | L15: 5110015 | M15: Investigação da Técnica de Seleção Espectral Ressonante para Produção Radioisotópica e Redução de Radiotoxicidade de Radionuclideos | N15: PROGRAMA BASICO DE ENGENHARIA NUCLEAR | O15: EN | P15: Engenharias | Q15: Produção de Radioisótopos | R15: Centro de Desenvolvimento da Tecnologia Nuclear | S15: CDTN/CNEN | T15: MG | U15: SE | V15: Brasil | W15: Centro de Desenvolvimento da Tecnologia Nuclear | X15: CDTN/CNEN | Y15: MG | Z15: SE | AA15: Brasil | AB15: DCTI | AC15: COBEN | AD15: 20/05/2026 | AE15: 07:22:04 | AF15: 20/05/2026 | AG15: 12:01:59 | AH15: 3 | AI15: 583700 | AJ15: 59800 | AK15: 0 | AL15: 643500 | AR15: 7016638154017973 | AS15: 46202.465 | AT15: PCI2026 | AU15: Chamada CNPq/MCTI/FNDCT Nº 12/2026 - Programa PCI | AV15: Chamada: Chamada CNPq/MCTI/FNDCT Nº 12/2026 - Faixa 3: Projetos de Pesquisa vinculados a | AW15: 12/2026 | AX15: Chamada CNPq/MCTI/FNDCT Nº 12/2026 - Faixa 3: Projetos de Pesquisa vinculados a UPs Grandes (acima de 200 servidores) | AY15: 27/04/2026 | AZ15: 27/06/2026 | BA15: bmelom@hotmail.com | BB15: 401010/2026-0 | BC15: Bruno Melo Mendes | BD15: Centro de Desenvolvimento da Tecnologia Nuclear | BE15: CDTN/CNEN | BF15: =IF(AND(BG15,BI15,BL15,BM15),TRUE,FALSE) -> FALSE | BG15: TRUE | BH15: 2017 | BI15: FALSE | BJ15: Faixa 3 | BK15: Faixa 3 (2 propostas) | BL15: TRUE | BM15: TRUE | BN15: TRUE | BO15: - Centro de Desenvolvimento da Tecnologia Nuclear da CNEN: (Servidor público - Pesquisador) | BP15: =IF(IFERROR(VLOOKUP(A15,[1]Planilha1!$A:$A,1,0),FALSE)=FALSE,FALSE,TRUE) -> FALSE
A16: 402015/2026-6 | B16: APQ | D16: 46204 | E16: 47664 | F16: 16515740816 | G16: Caio Augusto dos Santos Coelho | H16: http://lattes.cnpq.br/4978912302419377 | I16: Caio Augusto dos Santos Coelho | K16: Caio Augusto dos Santos Coelho, Danielson Jorge Delgado Neves, Fabio Pinto da Rocha, Diogo Alessandro Arsego, Jose Alberto da Silva Ferreira, Luciana dos Santos Machado Carvalho, Eduardo Batista de Moraes Barbosa, Andre | L16: 5116505 | M16: Fortalecendo o sistema brasileiro de monitoramento e previsão climática para o enfrentamento de adversidades causadas por eventos meteorológicos extremos | N16: Programa Basico de Ciências Ambientais | O16: CA | P16: Ciências Exatas e da Terra | Q16: Climatologia | R16: Instituto Nacional de Pesquisas Espaciais | S16: INPE | T16: SP | U16: SE | V16: Brasil | W16: Instituto Nacional de Pesquisas Espaciais | X16: INPE | Y16: SP | Z16: SE | AA16: Brasil | AB16: DCTI | AC16: COCAM | AD16: 26/06/2026 | AE16: 02:16:18 | AF16: 26/06/2026 | AG16: 02:16:36 | AH16: 7 | AI16: 1048320 | AJ16: 137184 | AK16: 0 | AL16: 1185504 | AM16: Instituto Nacional de Pesquisas Espaciais | AN16: INPE | AO16: SP | AP16: SE | AQ16: Brasil | AR16: 4978912302419377 | AS16: 46202.465 | AT16: PCI2026 | AU16: Chamada CNPq/MCTI/FNDCT Nº 12/2026 - Programa PCI | AV16: Chamada: Chamada CNPq/MCTI/FNDCT Nº 12/2026 - Faixa 3: Projetos de Pesquisa vinculados a | AW16: 12/2026 | AX16: Chamada CNPq/MCTI/FNDCT Nº 12/2026 - Faixa 3: Projetos de Pesquisa vinculados a UPs Grandes (acima de 200 servidores) | AY16: 27/04/2026 | AZ16: 27/06/2026 | BA16: caio.coelho@inpe.br | BB16: 402015/2026-6 | BC16: Caio Augusto dos Santos Coelho | BD16: Instituto Nacional de Pesquisas Espaciais | BE16: INPE | BF16: =IF(AND(BG16,BI16,BL16,BM16),TRUE,FALSE) -> TRUE | BG16: TRUE | BH16: 2005 | BI16: TRUE | BJ16: Faixa 3 | BK16: Faixa 3 (20 propostas) | BL16: TRUE | BM16: TRUE | BN16: TRUE | BO16: - Instituto Nacional de Pesquisas Espaciais - PA: (Servidor público - Pesquisador) - Instituto Nacional de Pesquisas Espaciais: (em branco) | BP16: =IF(IFERROR(VLOOKUP(A16,[1]Planilha1!$A:$A,1,0),FALSE)=FALSE,FALSE,TRUE) -> TRUE
A17: 402012/2026-7 | B17: APQ | D17: 46204 | E17: 47664 | F17: 05019430641 | G17: Caleb Guedes Miranda dos Santos | H17: http://lattes.cnpq.br/1597761083606654 | I17: Caleb Guedes Miranda dos Santos | K17: Caleb Guedes Miranda dos Santos | L17: 5116502 | M17: Perfil imunofenotípico e multiômico de biomarcadores livres e derivados de vesículas extracelulares induzidos pelo exercício para monitoramento fisiológico em atletas de elite e militares | N17: Programa Especial de Biotecnologia e Recursos Genéticos - COBRG | O17: BI | P17: Ciências Biológicas | Q17: Biotecnologia em Saúde Humana e Animal | R17: Instituto de Biologia do Exécito | S17: IBEX | T17: RJ | U17: SE | V17: Brasil | W17: Instituto de Biologia do Exécito | X17: IBEX | Y17: RJ | Z17: SE | AA17: Brasil | AB17: DCTI | AC17: COBEN | AD17: 26/06/2026 | AE17: 00:50:44 | AF17: 26/06/2026 | AG17: 00:50:52 | AH17: 3 | AI17: 761280 | AJ17: 80000 | AK17: 0 | AL17: 841280 | AM17: Instituto de Biologia do Exécito | AN17: IBEX | AO17: RJ | AP17: SE | AQ17: Brasil | AR17: 1597761083606654 | AS17: 46202.465 | AT17: PCI2026 | AU17: Chamada CNPq/MCTI/FNDCT Nº 12/2026 - Programa PCI | AV17: Chamada: Chamada CNPq/MCTI/FNDCT Nº 12/2026 - Faixa 3: Projetos de Pesquisa vinculados a | AW17: 12/2026 | AX17: Chamada CNPq/MCTI/FNDCT Nº 12/2026 - Faixa 3: Projetos de Pesquisa vinculados a UPs Grandes (acima de 200 servidores) | AY17: 27/04/2026 | AZ17: 27/06/2026 | BA17: calebguedes@gmail.com | BB17: 402012/2026-7 | BC17: Caleb Guedes Miranda dos Santos | BD17: Instituto de Biologia do Exécito | BE17: IBEX | BF17: =IF(AND(BG17,BI17,BL17,BM17),TRUE,FALSE) -> FALSE | BG17: FALSE | BH17: 2016 | BI17: FALSE | BJ17: Faixa 3 | BK17: Faixa 3 (1 propostas) | BL17: TRUE | BM17: TRUE | BN17: TRUE | BO17: - Instituto de Biologia do Exécito: (Servidor público - Major Farmaceutico - Pesquisador) | BP17: =IF(IFERROR(VLOOKUP(A17,[1]Planilha1!$A:$A,1,0),FALSE)=FALSE,FALSE,TRUE) -> FALSE
A18: 402095/2026-0 | B18: APQ | D18: 46204 | E18: 47664 | F18: 03585876706 | G18: Camila Cherem Ribas | H18: http://lattes.cnpq.br/4928616387172275 | I18: Camila Cherem Ribas | K18: Camila Cherem Ribas, Andrea Correa Flores Albuquerque, Moysés Mendes de Lima, Roberto Oliveira dos Santos, Inácio de Oliveira Lima Neto, Clausewykson Ribeiro da Cunha | L18: 5116587 | M18: Observatório de Repositórios, Integração, Organização e Navegação de Dados Científicos (ORION) | N18: PROGRAMA BASICO DE CIENCIA DA COMPUTACAO | O18: CC | P18: Ciências Exatas e da Terra | Q18: Banco de Dados | R18: Instituto Nacional de Pesquisas da Amazônia | S18: INPA | T18: AM | U18: NO | V18: Brasil | W18: Instituto Nacional de Pesquisas da Amazônia | X18: INPA | Y18: AM | Z18: NO | AA18: Brasil | AB18: DCTI | AC18: COCEC | AD18: 27/06/2026 | AE18: 06:50:40 | AF18: 27/06/2026 | AG18: 09:52:18 | AH18: 9 | AI18: 1363020 | AJ18: 136796 | AK18: 0 | AL18: 1499816 | AM18: Instituto Nacional de Pesquisas da Amazônia | AN18: INPA | AO18: AM | AP18: NO | AQ18: Brasil | AR18: 4928616387172275 | AS18: 46202.465 | AT18: PCI2026 | AU18: Chamada CNPq/MCTI/FNDCT Nº 12/2026 - Programa PCI | AV18: Chamada: Chamada CNPq/MCTI/FNDCT Nº 12/2026 - Faixa 3: Projetos de Pesquisa vinculados a | AW18: 12/2026 | AX18: Chamada CNPq/MCTI/FNDCT Nº 12/2026 - Faixa 3: Projetos de Pesquisa vinculados a UPs Grandes (acima de 200 servidores) | AY18: 27/04/2026 | AZ18: 27/06/2026 | BA18: camilaribas@gmail.com | BB18: 402095/2026-0 | BC18: Camila Cherem Ribas | BD18: Instituto Nacional de Pesquisas da Amazônia | BE18: INPA | BF18: =IF(AND(BG18,BI18,BL18,BM18),TRUE,FALSE) -> TRUE | BG18: TRUE | BH18: 2005 | BI18: TRUE | BJ18: Faixa 3 | BK18: Faixa 3 (15 propostas) | BL18: TRUE | BM18: TRUE | BN18: TRUE | BO18: - American Museum of Natural History: (Research Associate - Research Associate) - Instituto Nacional de Pesquisas da Amazônia: (Servidor público - Tecnologista H-III) - Karlsruher Institut für Technologie: (Pesquisador visitante - Pesquisador visitante - PDE/CNPq) | BP18: =IF(IFERROR(VLOOKUP(A18,[1]Planilha1!$A:$A,1,0),FALSE)=FALSE,FALSE,TRUE) -> TRUE
A19: 402179/2026-9 | B19: APQ | D19: 46204 | E19: 47664 | F19: 05137625825 | G19: Carlos Roberto Jorge Soares | H19: http://lattes.cnpq.br/3805602544840562 | I19: Carlos Roberto Jorge Soares | K19: Carlos Roberto Jorge Soares, Alvaro Antonio Alencar Queiroz, Cibele Nunes Peroni, Emerson Soares Bernardes, Luís Alberto Pereira Dias, Margareth Mie Nakamura Matsuda, Andrea Glezer, Joao Ezequiel de Oliveira, Daniel Perez | L19: 5116673 | M19: Desenvolvimento e Avaliação Teranóstica de Antagonistas do Receptor de Prolactina em Cânceres Prolactino Dependentes | N19: Programa Especial de Biotecnologia e Recursos Genéticos - COBRG | O19: BI | P19: Ciências Biológicas | Q19: Novas Drogas Terapêuticas | R19: COMISSAO NACIONAL DE ENERGIA NUCLEAR | S19: CNEN | T19: RJ | U19: SE | V19: Brasil | W19: COMISSAO NACIONAL DE ENERGIA NUCLEAR | X19: CNEN | Y19: RJ | Z19: SE | AA19: Brasil | AB19: DCTI | AC19: COBEN | AD19: 26/06/2026 | AE19: 16:30:51 | AF19: 27/06/2026 | AG19: 09:57:29 | AH19: 4 | AI19: 829920 | AJ19: 40000 | AK19: 0 | AL19: 869920 | AM19: COMISSAO NACIONAL DE ENERGIA NUCLEAR | AN19: CNEN | AO19: RJ | AP19: SE | AQ19: Brasil | AR19: 3805602544840562 | AS19: 46202.465 | AT19: PCI2026 | AU19: Chamada CNPq/MCTI/FNDCT Nº 12/2026 - Programa PCI | AV19: Chamada: Chamada CNPq/MCTI/FNDCT Nº 12/2026 - Faixa 3: Projetos de Pesquisa vinculados a | AW19: 12/2026 | AX19: Chamada CNPq/MCTI/FNDCT Nº 12/2026 - Faixa 3: Projetos de Pesquisa vinculados a UPs Grandes (acima de 200 servidores) | AY19: 27/04/2026 | AZ19: 27/06/2026 | BA19: crsoares@ipen.br | BB19: 402179/2026-9 | BC19: Carlos Roberto Jorge Soares | BD19: COMISSAO NACIONAL DE ENERGIA NUCLEAR | BE19: CNEN | BF19: =IF(AND(BG19,BI19,BL19,BM19),TRUE,FALSE) -> TRUE | BG19: TRUE | BH19: 2000 | BI19: TRUE | BJ19: Faixa 3 | BK19: Faixa 3 (32 propostas) | BL19: TRUE | BM19: TRUE | BN19: TRUE | BO19: - COMISSAO NACIONAL DE ENERGIA NUCLEAR: (Servidor público - Pesquisador) - Universidade de São Paulo: (Professor - Responsável por curso de pós-graduação) - Fundação de Amparo à Pesquisa do Estado da Bahia: (Membro de comitê assessor) - Coordenação de Aperfeiçoamento de Pessoal de Nível Superior: (Membro de comitê assessor) - Conselho Nacional de Desenvolvimento Científico e Tecnológico: (Membro de comitê assessor) - Instituto de Pesquisas Energéticas e Nucleares: (em branco) - Universidade Estadual de Campinas: (em branco) | BP19: =IF(IFERROR(VLOOKUP(A19,[1]Planilha1!$A:$A,1,0),FALSE)=FALSE,FALSE,TRUE) -> TRUE
A20: 402215/2026-5 | B20: APQ | D20: 46204 | E20: 47664 | F20: 16756902865 | G20: Cecília Chaves Guedes e Silva | H20: http://lattes.cnpq.br/3598507725109908 | I20: Cecília Chaves Guedes e Silva | K20: Cecília Chaves Guedes e Silva, Dolores Ribeiro Ricci Lazar, Flavio Machado de Souza Carvalho, Thiago dos Santos Ferreira, Anelyse Arata | L20: 5116710 | M20: Novas Estratégias no Desenvolvimento de Cerâmicas para a Odontologia: Integração entre Processamento e Desempenho | N20: PROGRAMA BASICO DE ENGENHARIA DE MATERIAIS E METALURGIA | O20: MM | P20: Engenharias | Q20: Cerâmicos | R20: Instituto de Pesquisas Energéticas e Nucleares | S20: IPEN/CNEN | T20: SP | U20: SE | V20: Brasil | W20: Instituto de Pesquisas Energéticas e Nucleares | X20: IPEN/CNEN | Y20: SP | Z20: SE | AA20: Brasil | AB20: DCTI | AC20: COBEN | AD20: 26/06/2026 | AE20: 11:10:44 | AF20: 27/06/2026 | AG20: 09:59:31 | AH20: 3 | AI20: 648960 | AJ20: 70185 | AK20: 0 | AL20: 719145 | AR20: 3598507725109908 | AS20: 46202.465 | AT20: PCI2026 | AU20: Chamada CNPq/MCTI/FNDCT Nº 12/2026 - Programa PCI | AV20: Chamada: Chamada CNPq/MCTI/FNDCT Nº 12/2026 - Faixa 3: Projetos de Pesquisa vinculados a | AW20: 12/2026 | AX20: Chamada CNPq/MCTI/FNDCT Nº 12/2026 - Faixa 3: Projetos de Pesquisa vinculados a UPs Grandes (acima de 200 servidores) | AY20: 27/04/2026 | AZ20: 27/06/2026 | BA20: ceciliacguedes@gmail.com | BB20: 402215/2026-5 | BC20: Cecília Chaves Guedes e Silva | BD20: Instituto de Pesquisas Energéticas e Nucleares | BE20: IPEN/CNEN | BF20: =IF(AND(BG20,BI20,BL20,BM20),TRUE,FALSE) -> TRUE | BG20: TRUE | BH20: 2005 | BI20: TRUE | BJ20: Faixa 3 | BK20: Faixa 3 (6 propostas) | BL20: TRUE | BM20: TRUE | BN20: TRUE | BO20: - Instituto de Pesquisas Energéticas e Nucleares: (Servidor público - Pesquisadora) - Instituto de Pesquisas Energéticas e Nucleares: (Servidor público - Professor de pós-graduação) - Instituto de Pesquisas Energéticas e Nucleares: (Servidor público - Membro do comitê de Bolsas PIBIC/PROBIT) - Fundação de Amparo à Pesquisa do Estado de São Paulo: (Membro de comitê assessor) - Associação Brasileira de Cerâmica: (COLABORADOR - Membro do Conselho Diretor) | BP20: =IF(IFERROR(VLOOKUP(A20,[1]Planilha1!$A:$A,1,0),FALSE)=FALSE,FALSE,TRUE) -> TRUE
A21: 402276/2026-4 | B21: APQ | D21: 46204 | E21: 47664 | F21: 53431685234 | G21: Charles Eugene Zartman | H21: http://lattes.cnpq.br/1704819172861021 | I21: Charles Eugene Zartman | K21: Charles Eugene Zartman, Vania Nobuko Yoshikawa, Dirce Leimi Komura, Maria de Lourdes da Costa Soares Morais, Alberto Vicentini, Mike Hopkins, Matheus Lopes Silva, Ires Paula de Andrade Miranda, Flavia Machado Durgante, | L21: 5116774 | M21: BIOCOLABS: Biodiversidade da Flora e Funga Conservada através de Laboratórios da botânica e Aquisição de Bioextratos Amazônicos | N21: PROGRAMA BASICO DE BOTANICA | O21: BO | P21: Ciências Biológicas | Q21: Taxonomia Vegetal | R21: Instituto Nacional de Pesquisas da Amazônia | S21: INPA | T21: AM | U21: NO | V21: Brasil | W21: Instituto Nacional de Pesquisas da Amazônia | X21: INPA | Y21: AM | Z21: NO | AA21: Brasil | AB21: DCTI | AC21: COEBI | AD21: 26/06/2026 | AE21: 11:21:19 | AF21: 27/06/2026 | AG21: 10:03:22 | AH21: 10 | AI21: 1115520 | AJ21: 49500 | AK21: 0 | AL21: 1165020 | AM21: Instituto Nacional de Pesquisas da Amazônia | AN21: INPA | AO21: AM | AP21: NO | AQ21: Brasil | AR21: 1704819172861021 | AS21: 46202.465 | AT21: PCI2026 | AU21: Chamada CNPq/MCTI/FNDCT Nº 12/2026 - Programa PCI | AV21: Chamada: Chamada CNPq/MCTI/FNDCT Nº 12/2026 - Faixa 3: Projetos de Pesquisa vinculados a | AW21: 12/2026 | AX21: Chamada CNPq/MCTI/FNDCT Nº 12/2026 - Faixa 3: Projetos de Pesquisa vinculados a UPs Grandes (acima de 200 servidores) | AY21: 27/04/2026 | AZ21: 27/06/2026 | BA21: chaszartman@gmail.com | BB21: 402276/2026-4 | BC21: Charles Eugene Zartman | BD21: Instituto Nacional de Pesquisas da Amazônia | BE21: INPA | BF21: =IF(AND(BG21,BI21,BL21,BM21),TRUE,FALSE) -> TRUE | BG21: TRUE | BH21: 2004 | BI21: TRUE | BJ21: Faixa 3 | BK21: Faixa 3 (15 propostas) | BL21: TRUE | BM21: TRUE | BN21: TRUE | BO21: - Instituto Nacional de Pesquisas da Amazônia: (Orientador - Nucleo permanente PPG-BOT INPA) - Instituto Nacional de Pesquisas da Amazônia: (Servidor público - Pesquisador Titular III) | BP21: =IF(IFERROR(VLOOKUP(A21,[1]Planilha1!$A:$A,1,0),FALSE)=FALSE,FALSE,TRUE) -> TRUE
A22: 402243/2026-9 | B22: APQ | D22: 46204 | E22: 47664 | F22: 09471587824 | G22: Cláudia Vilega Rodrigues | H22: http://lattes.cnpq.br/9527193250756102 | I22: Cláudia Vilega Rodrigues | K22: Cláudia Vilega Rodrigues, Carlos Alexandre Wuensche de Souza, Odylio Denys de Aguiar, Ana Carolina Mattiuci Figueiredo, Marina Machado Cunha e Mello, Fernando Falkenberg Marques, Gustavo Henrique da Silva Santos, | L22: 5116741 | M22: Da Instrumentação de Fronteira à Análise de Dados Astrofísicos: Integração e Resultados | N22: PROGRAMA BASICO DE ASTRONOMIA | O22: FA | P22: Ciências Exatas e da Terra | Q22: Processamento de Dados Astronômicos | R22: Instituto Nacional de Pesquisas Espaciais | S22: INPE | T22: SP | U22: SE | V22: Brasil | W22: Instituto Nacional de Pesquisas Espaciais | X22: INPE | Y22: SP | Z22: SE | AA22: Brasil | AB22: DCTI | AC22: COCEC | AD22: 26/06/2026 | AE22: 17:43:05 | AF22: 27/06/2026 | AG22: 10:01:28 | AH22: 7 | AI22: 1460400 | AJ22: 39840 | AK22: 0 | AL22: 1500240 | AM22: Instituto Nacional de Pesquisas Espaciais | AN22: INPE | AO22: SP | AP22: SE | AQ22: Brasil | AR22: 9527193250756102 | AS22: 46202.465 | AT22: PCI2026 | AU22: Chamada CNPq/MCTI/FNDCT Nº 12/2026 - Programa PCI | AV22: Chamada: Chamada CNPq/MCTI/FNDCT Nº 12/2026 - Faixa 3: Projetos de Pesquisa vinculados a | AW22: 12/2026 | AX22: Chamada CNPq/MCTI/FNDCT Nº 12/2026 - Faixa 3: Projetos de Pesquisa vinculados a UPs Grandes (acima de 200 servidores) | AY22: 27/04/2026 | AZ22: 27/06/2026 | BA22: claudia.rodrigues@inpe.br | BB22: 402243/2026-9 | BC22: Cláudia Vilega Rodrigues | BD22: Instituto Nacional de Pesquisas Espaciais | BE22: INPE | BF22: =IF(AND(BG22,BI22,BL22,BM22),TRUE,FALSE) -> TRUE | BG22: TRUE | BH22: 1997 | BI22: TRUE | BJ22: Faixa 3 | BK22: Faixa 3 (20 propostas) | BL22: TRUE | BM22: TRUE | BN22: TRUE | BO22: - Instituto Nacional de Pesquisas Espaciais: (Pesquisador titular) - Laboratório Nacional de Astrofísica: (COLABORADOR - não há) - Conselho Nacional de Desenvolvimento Científico e Tecnológico: (Assessor - Nao se aplica) - International Astronomical Union: (Membro da Comissão B6 - Membro da Comissão B6) - SOuthern Astrophysical Research Telescope: (Membro do Conselho Diretor - Membro do Conselho Diretor) | BP22: =IF(IFERROR(VLOOKUP(A22,[1]Planilha1!$A:$A,1,0),FALSE)=FALSE,FALSE,TRUE) -> TRUE
A23: 402298/2026-8 | B23: APQ | D23: 46204 | E23: 47664 | F23: 27021726600 | G23: Clédola Cássia Oliveira de Tello | H23: http://lattes.cnpq.br/7628216289944686 | I23: Clédola Cássia Oliveira de Tello | K23: Clédola Cássia Oliveira de Tello, Rogerio Pimenta Mourao, Heloisa Maria Santos Oliveira, Jamile Salim Fuina, Daisy Mary Marchezini dos Santos, Maria Judite Afonso Haucz, Thais Braga Teixeira, Isabella Lobo Filgueiras de Miranda | L23: 5116796 | M23: Capacitação técnico-científica para o projeto do CENTENA - Centro Tecnológico Nuclear e Ambiental | N23: PROGRAMA BASICO DE ENGENHARIA NUCLEAR | O23: EN | P23: Engenharias | Q23: Rejeitos de Combustível Nuclear | R23: COMISSAO NACIONAL DE ENERGIA NUCLEAR | S23: CNEN | T23: RJ | U23: SE | V23: Brasil | W23: COMISSAO NACIONAL DE ENERGIA NUCLEAR | X23: CNEN | Y23: RJ | Z23: SE | AA23: Brasil | AB23: DCTI | AC23: COBEN | AD23: 26/06/2026 | AE23: 18:40:07 | AF23: 27/06/2026 | AG23: 10:04:47 | AH23: 10 | AI23: 1395680 | AJ23: 104320 | AK23: 0 | AL23: 1500000 | AM23: COMISSAO NACIONAL DE ENERGIA NUCLEAR | AN23: CNEN | AO23: RJ | AP23: SE | AQ23: Brasil | AR23: 7628216289944686 | AS23: 46202.465 | AT23: PCI2026 | AU23: Chamada CNPq/MCTI/FNDCT Nº 12/2026 - Programa PCI | AV23: Chamada: Chamada CNPq/MCTI/FNDCT Nº 12/2026 - Faixa 3: Projetos de Pesquisa vinculados a | AW23: 12/2026 | AX23: Chamada CNPq/MCTI/FNDCT Nº 12/2026 - Faixa 3: Projetos de Pesquisa vinculados a UPs Grandes (acima de 200 servidores) | AY23: 27/04/2026 | AZ23: 27/06/2026 | BA23: tellocc@cdtn.br | BB23: 402298/2026-8 | BC23: Clédola Cássia Oliveira de Tello | BD23: COMISSAO NACIONAL DE ENERGIA NUCLEAR | BE23: CNEN | BF23: =IF(AND(BG23,BI23,BL23,BM23),TRUE,FALSE) -> TRUE | BG23: TRUE | BH23: 2001 | BI23: TRUE | BJ23: Faixa 3 | BK23: Faixa 3 (32 propostas) | BL23: TRUE | BM23: TRUE | BN23: TRUE | BO23: - COMISSAO NACIONAL DE ENERGIA NUCLEAR: (Servidor público - Tecnologista Senior) - Associação Brasileira para Desenvolvimento de Atividades Nucleares.: (Membro de comitê assessor) - Centro de Desenvolvimento da Tecnologia Nuclear: (em branco) | BP23: =IF(IFERROR(VLOOKUP(A23,[1]Planilha1!$A:$A,1,0),FALSE)=FALSE,FALSE,TRUE) -> TRUE
A24: 402357/2026-4 | B24: APQ | D24: 46204 | E24: 47664 | F24: 72952229287 | G24: Cleo Quaresma Dias Júnior | H24: http://lattes.cnpq.br/9857237626091379 | I24: Cleo Quaresma Dias Júnior | K24: Cleo Quaresma Dias Júnior, Luiz Antonio Candido, Aline Corrêa de Sousa, Alderlene Pimentel de Brito, Keila Rêgo Mendes, Israel de Jesus Sampaio Filho, Flávia Regina Capellotto Costa, Bruce Rider Forsberg, Carlos Alberto Nobre | L24: 5116855 | M24: Amazônia Central como Hotspot Emergente de Mudanças: Plataforma Integrada de Monitoramento e Modelagem para Estudos de Impactos Hidroclimático e Ambiental | N24: Programa Basico de Ciências Ambientais | O24: CA | P24: Outra | Q24: Ciências Ambientais | R24: Instituto Nacional de Pesquisas da Amazônia | S24: INPA | T24: AM | U24: NO | V24: Brasil | W24: Instituto Nacional de Pesquisas da Amazônia | X24: INPA | Y24: AM | Z24: NO | AA24: Brasil | AB24: DCTI | AC24: COCAM | AD24: 27/06/2026 | AE24: 15:57:17 | AF24: 27/06/2026 | AG24: 15:57:32 | AH24: 9 | AI24: 1347060 | AJ24: 148940 | AK24: 0 | AL24: 1496000 | AM24: Instituto Nacional de Pesquisas da Amazônia | AN24: INPA | AO24: AM | AP24: NO | AQ24: Brasil | AR24: 9857237626091379 | AS24: 46202.465 | AT24: PCI2026 | AU24: Chamada CNPq/MCTI/FNDCT Nº 12/2026 - Programa PCI | AV24: Chamada: Chamada CNPq/MCTI/FNDCT Nº 12/2026 - Faixa 3: Projetos de Pesquisa vinculados a | AW24: 12/2026 | AX24: Chamada CNPq/MCTI/FNDCT Nº 12/2026 - Faixa 3: Projetos de Pesquisa vinculados a UPs Grandes (acima de 200 servidores) | AY24: 27/04/2026 | AZ24: 27/06/2026 | BA24: cleo.quaresma@ifpa.edu.br | BB24: 402357/2026-4 | BC24: Cleo Quaresma Dias Júnior | BD24: Instituto Nacional de Pesquisas da Amazônia | BE24: INPA | BF24: =IF(AND(BG24,BI24,BL24,BM24),TRUE,FALSE) -> TRUE | BG24: TRUE | BH24: 2015 | BI24: TRUE | BJ24: Faixa 3 | BK24: Faixa 3 (15 propostas) | BL24: TRUE | BM24: TRUE | BN24: TRUE | BO24: - Instituto Nacional de Pesquisas da Amazônia: (COLABORADOR - Colaborador PPG em Clima e Ambiente) - Instituto Nacional de Pesquisas da Amazônia: (COLABORADOR - Coordenador da Micrometeorologia do ATTO) - Instituto Nacional de Pesquisas da Amazônia: (Servidor público - Pesquisador) - Universidade Federal do Pará: (COLABORADOR - Colaborador PPG em Ciências Ambientais) - Max-Planck-Institut für Biogeochemie - Jena: (COLABORADOR - Colaborador) - Universität Leipzig: (COLABORADOR - Colaborador) - Universidade Federal de Santa Maria: (COLABORADOR - Colaborador) - Universíade de Taubaté: (COLABORADOR - Colaborador) - Universidade de São Paulo: (em branco) | BP24: =IF(IFERROR(VLOOKUP(A24,[1]Planilha1!$A:$A,1,0),FALSE)=FALSE,FALSE,TRUE) -> TRUE
A25: 401137/2026-0 | B25: APQ | D25: 46204 | E25: 47664 | F25: 13881249800 | G25: Cléria Mendonça de Moraes | H25: http://lattes.cnpq.br/4518337589148307 | I25: Cléria Mendonça de Moraes | K25: Cléria Mendonça de Moraes, Newton Ricardo Pereira Souza, Cecil Albert Boston, Julio Cesar Fraulob Aquino, Beatriz Helena Baldez Vasconcelos, Luciana da Silva Barros, Jackeline da Costa Maciel Silva, Augusto Vicente Ferreira | L25: 5115153 | M25: Horto Didático integrado ao Ensino, à Pesquisa e à Inovação de bioprodutos a partir de Plantas Medicinais da Amazônia Setentrional | N25: PROGRAMA BASICO DE SAUDE COLETIVA | O25: SN | P25: Ciências da Saúde | Q25: Epidemiologia | R25: Universidade Federal de Roraima | S25: UFRR | T25: RR | U25: NO | V25: Brasil | W25: Universidade Federal de Roraima | X25: UFRR | Y25: RR | Z25: NO | AA25: Brasil | AB25: DCTI | AC25: COSAU | AD25: 27/05/2026 | AE25: 23:50:44 | AF25: 27/05/2026 | AG25: 23:50:51 | AH25: 12 | AI25: 1440000 | AJ25: 150000 | AK25: 0 | AL25: 1590000 | AM25: Universidade Federal de Roraima | AN25: UFRR | AO25: RR | AP25: NO | AQ25: Brasil | AR25: 4518337589148307 | AS25: 46202.465 | AT25: PCI2026 | AU25: Chamada CNPq/MCTI/FNDCT Nº 12/2026 - Programa PCI | AV25: Chamada: Chamada CNPq/MCTI/FNDCT Nº 12/2026 - Faixa 3: Projetos de Pesquisa vinculados a | AW25: 12/2026 | AX25: Chamada CNPq/MCTI/FNDCT Nº 12/2026 - Faixa 3: Projetos de Pesquisa vinculados a UPs Grandes (acima de 200 servidores) | AY25: 27/04/2026 | AZ25: 27/06/2026 | BA25: clemmsp@gmail.com | BB25: 401137/2026-0 | BC25: Cléria Mendonça de Moraes | BD25: Universidade Federal de Roraima | BE25: UFRR | BF25: =IF(AND(BG25,BI25,BL25,BM25),TRUE,FALSE) -> FALSE | BG25: FALSE | BH25: 2000 | BI25: FALSE | BJ25: Faixa 3 | BK25: Faixa 3 (1 propostas) | BL25: TRUE | BM25: TRUE | BN25: TRUE | BO25: - Universidade Federal de Roraima: (Servidor público - Professor do Magistério Superior) - Fundação Oswaldo Cruz: (em branco) | BP25: =IF(IFERROR(VLOOKUP(A25,[1]Planilha1!$A:$A,1,0),FALSE)=FALSE,FALSE,TRUE) -> FALSE
A26: 401983/2026-9 | B26: APQ | D26: 46204 | E26: 47664 | F26: 59264594000 | G26: Cristiano Max Wrasse | H26: http://lattes.cnpq.br/2348934439826171 | I26: Cristiano Max Wrasse | K26: Cristiano Max Wrasse, Clezio Marcos De Nardin, Delano Gobbi, Diego Barros Silva, Emilia Correia, Fábio Becker Guedes, Jean Carlo Santos, Joaquim Eduardo Rezende Costa, Láysa Cristina Araujo Resende Chagas, Lígia Alves da | L26: 5116464 | M26: Desenvolvimento e implementação de produtos de clima espacial para proteção às infraestruturas críticas | N26: Programa Basico de Geociência | O26: GC | P26: Ciências Exatas e da Terra | Q26: Geofísica | R26: Instituto Nacional de Pesquisas Espaciais | S26: INPE | T26: SP | U26: SE | V26: Brasil | W26: Instituto Nacional de Pesquisas Espaciais | X26: INPE | Y26: SP | Z26: SE | AA26: Brasil | AB26: DCTI | AC26: COCQG | AD26: 25/06/2026 | AE26: 16:13:45 | AF26: 25/06/2026 | AG26: 16:17:50 | AH26: 3 | AI26: 648960 | AJ26: 0 | AK26: 0 | AL26: 648960 | AM26: Instituto Nacional de Pesquisas Espaciais | AN26: INPE | AO26: SP | AP26: SE | AQ26: Brasil | AR26: 2348934439826171 | AS26: 46202.465 | AT26: PCI2026 | AU26: Chamada CNPq/MCTI/FNDCT Nº 12/2026 - Programa PCI | AV26: Chamada: Chamada CNPq/MCTI/FNDCT Nº 12/2026 - Faixa 3: Projetos de Pesquisa vinculados a | AW26: 12/2026 | AX26: Chamada CNPq/MCTI/FNDCT Nº 12/2026 - Faixa 3: Projetos de Pesquisa vinculados a UPs Grandes (acima de 200 servidores) | AY26: 27/04/2026 | AZ26: 27/06/2026 | BA26: cristiano.wrasse@gmail.com | BB26: 401983/2026-9 | BC26: Cristiano Max Wrasse | BD26: Instituto Nacional de Pesquisas Espaciais | BE26: INPE | BF26: =IF(AND(BG26,BI26,BL26,BM26),TRUE,FALSE) -> TRUE | BG26: TRUE | BH26: 2004 | BI26: TRUE | BJ26: Faixa 3 | BK26: Faixa 3 (20 propostas) | BL26: TRUE | BM26: TRUE | BN26: TRUE | BO26: - Instituto Nacional de Pesquisas Espaciais: (Servidor público - Pesquisador) | BP26: =IF(IFERROR(VLOOKUP(A26,[1]Planilha1!$A:$A,1,0),FALSE)=FALSE,FALSE,TRUE) -> TRUE
A27: 402263/2026-0 | B27: APQ | D27: 46204 | E27: 47664 | F27: 48882291200 | G27: Cristine Bastos do Amarante | H27: http://lattes.cnpq.br/4101983776191966 | I27: Cristine Bastos do Amarante | K27: Cristine Bastos do Amarante, Amilcar Carvalho Mendes, Tarcízio Macedo, José Francisco Berrêdo Reis da Silva, Marcos Paulo Alves de Sousa, Sâmia Batista e Silva, Gerson Valente da Costa, Jose Paulo Sarmento, Lourdes de | L27: 5116761 | M27: Fortalecimento do Ecossistema de Inovação do MPEG: estratégias para aumento de TRL e valoração de tecnologias para a bioeconomia e o desenvolvimento regional  INOVAGOELDI | N27: PROGRAMA BASICO DE ADMINISTRACAO | O27: AE | P27: Ciências Sociais Aplicadas | Q27: Planejamento em Ciência e Tecnologia | R27: Museu Paraense Emílio Goeldi | S27: MPEG | T27: PA | U27: NO | V27: Brasil | W27: Museu Paraense Emílio Goeldi | X27: MPEG | Y27: PA | Z27: NO | AA27: Brasil | AB27: DCTI | AC27: COSAE | AD27: 26/06/2026 | AE27: 12:44:09 | AF27: 27/06/2026 | AG27: 10:02:34 | AH27: 6 | AI27: 1023360 | AJ27: 130000 | AK27: 0 | AL27: 1153360 | AR27: 4101983776191966 | AS27: 46202.465 | AT27: PCI2026 | AU27: Chamada CNPq/MCTI/FNDCT Nº 12/2026 - Programa PCI | AV27: Chamada: Chamada CNPq/MCTI/FNDCT Nº 12/2026 - Faixa 3: Projetos de Pesquisa vinculados a | AW27: 12/2026 | AX27: Chamada CNPq/MCTI/FNDCT Nº 12/2026 - Faixa 3: Projetos de Pesquisa vinculados a UPs Grandes (acima de 200 servidores) | AY27: 27/04/2026 | AZ27: 27/06/2026 | BA27: cristineamarante@yahoo.com.br | BB27: 402263/2026-0 | BC27: Cristine Bastos do Amarante | BD27: Museu Paraense Emílio Goeldi | BE27: MPEG | BF27: =IF(AND(BG27,BI27,BL27,BM27),TRUE,FALSE) -> TRUE | BG27: TRUE | BH27: 2010 | BI27: TRUE | BJ27: Faixa 3 | BK27: Faixa 3 (24 propostas) | BL27: TRUE | BM27: TRUE | BN27: FALSE | BO27: - Museu Paraense Emílio Goeldi: (TECNOLOGISTA SÊNIOR) | BP27: =IF(IFERROR(VLOOKUP(A27,[1]Planilha1!$A:$A,1,0),FALSE)=FALSE,FALSE,TRUE) -> TRUE
A28: 401130/2026-6 | B28: APQ | D28: 46204 | E28: 47664 | F28: 26807621850 | G28: Daniel Alexandre Baptista Bonifacio | H28: http://lattes.cnpq.br/0153111515550957 | I28: Daniel Alexandre Baptista Bonifacio | K28: Daniel Alexandre Baptista Bonifacio, Maria da Penha Albuquerque Potiens, Mario Olimpio de Menezes, Orlando Rodrigues Junior, Marcelo Tatit Sapienza, Marcelo Bender Perotoni, Eriki Masahiko Takara, Raphael Elias Diniz, | L28: 5114998 | M28: Dosimetria Personalizada para Iodoterapia: Integração de Monitoramento Vestível em Estudo Clínico Piloto | N28: PROGRAMA BASICO DE ENGENHARIA NUCLEAR | O28: EN | P28: Engenharias | Q28: Instrumentação para Medida e Controle de Radiação | R28: Instituto de Pesquisas Energéticas e Nucleares | S28: IPEN/CNEN | T28: SP | U28: SE | V28: Brasil | W28: Instituto de Pesquisas Energéticas e Nucleares | X28: IPEN/CNEN | Y28: SP | Z28: SE | AA28: Brasil | AB28: DCTI | AC28: COBEN | AD28: 27/05/2026 | AE28: 19:15:39 | AF28: 27/05/2026 | AG28: 19:15:46 | AH28: 7 | AI28: 1070160 | AJ28: 100000 | AK28: 0 | AL28: 1170160 | AM28: COMISSAO NACIONAL DE ENERGIA NUCLEAR | AN28: CNEN | AO28: RJ | AP28: SE | AQ28: Brasil | AR28: 0153111515550957 | AS28: 46202.465 | AT28: PCI2026 | AU28: Chamada CNPq/MCTI/FNDCT Nº 12/2026 - Programa PCI | AV28: Chamada: Chamada CNPq/MCTI/FNDCT Nº 12/2026 - Faixa 3: Projetos de Pesquisa vinculados a | AW28: 12/2026 | AX28: Chamada CNPq/MCTI/FNDCT Nº 12/2026 - Faixa 3: Projetos de Pesquisa vinculados a UPs Grandes (acima de 200 servidores) | AY28: 27/04/2026 | AZ28: 27/06/2026 | BA28: daniel.bonifacio@ipen.br | BB28: 401130/2026-6 | BC28: Daniel Alexandre Baptista Bonifacio | BD28: Instituto de Pesquisas Energéticas e Nucleares | BE28: IPEN/CNEN | BF28: =TRUE -> TRUE | BG28: TRUE | BH28: 2011 | BI28: TRUE | BJ28: Faixa 3 | BK28: Faixa 3 (6 propostas) | BL28: TRUE | BM28: =TRUE -> TRUE | BN28: =TRUE -> TRUE | BO28: - COMISSAO NACIONAL DE ENERGIA NUCLEAR: (Servidor público - Pesquisador) - SOLUCOES E INSTRUMENTACOES AVANCADAS LTDA - ME: (Sócio-fundador - Sócio-fundador) | BP28: =IF(IFERROR(VLOOKUP(A28,[1]Planilha1!$A:$A,1,0),FALSE)=FALSE,FALSE,TRUE) -> TRUE
A29: 401124/2026-6 | B29: APQ | D29: 46204 | E29: 47664 | F29: 05426093717 | G29: Daniel Pedra Adesse | H29: http://lattes.cnpq.br/8127213004748485 | I29: Daniel Pedra Adesse | K29: Daniel Pedra Adesse, Vladimir Pedro Peralva Borges Martins, Carolina Moreira dos Santos, Andre Luiz Land Curi, Fábio César Sousa Nogueira, Emilly Caroline dos Santos Moraes, Guilherme Andrade de Santana, Gustavo Pinheiro | L29: 5114877 | M29: Estratégias terapêuticas antifibróticas baseadas em aptâmeros para reparo retiniano na toxoplasmose ocular | N29: PROGRAMA BASICO DE PARASITOLOGIA | O29: MP | P29: Ciências Biológicas | Q29: Protozoologia Parasitária Humana | R29: Fundação Oswaldo Cruz | S29: FIOCRUZ | T29: RJ | U29: SE | V29: Brasil | W29: Fundação Oswaldo Cruz | X29: FIOCRUZ | Y29: RJ | Z29: SE | AA29: Brasil | AB29: DCTI | AC29: COBIO | AD29: 27/05/2026 | AE29: 17:16:04 | AF29: 27/05/2026 | AG29: 17:16:15 | AH29: 4 | AI29: 755040 | AJ29: 0 | AK29: 0 | AL29: 755040 | AM29: Fundação Oswaldo Cruz | AN29: FIOCRUZ | AO29: RJ | AP29: SE | AQ29: Brasil | AR29: 8127213004748485 | AS29: 46202.465 | AT29: PCI2026 | AU29: Chamada CNPq/MCTI/FNDCT Nº 12/2026 - Programa PCI | AV29: Chamada: Chamada CNPq/MCTI/FNDCT Nº 12/2026 - Faixa 3: Projetos de Pesquisa vinculados a | AW29: 12/2026 | AX29: Chamada CNPq/MCTI/FNDCT Nº 12/2026 - Faixa 3: Projetos de Pesquisa vinculados a UPs Grandes (acima de 200 servidores) | AY29: 27/04/2026 | AZ29: 27/06/2026 | BA29: adesse@ioc.fiocruz.br | BB29: 401124/2026-6 | BC29: Daniel Pedra Adesse | BD29: Fundação Oswaldo Cruz | BE29: FIOCRUZ | BF29: =IF(AND(BG29,BI29,BL29,BM29),TRUE,FALSE) -> FALSE | BG29: FALSE | BH29: 2010 | BI29: FALSE | BJ29: Faixa 3 | BK29: Faixa 3 (3 propostas) | BL29: TRUE | BM29: TRUE | BN29: TRUE | BO29: - Fundação Oswaldo Cruz: (Servidor público - Pesquisador Titular) - Sociedade Brasileira de Protozoologia: (Membro Ordinário - Membro Ordinário) | BP29: =IF(IFERROR(VLOOKUP(A29,[1]Planilha1!$A:$A,1,0),FALSE)=FALSE,FALSE,TRUE) -> FALSE
A30: 401125/2026-2 | B30: APQ | D30: 46204 | E30: 47664 | F30: 05426093717 | G30: Daniel Pedra Adesse | H30: http://lattes.cnpq.br/8127213004748485 | I30: Daniel Pedra Adesse | K30: Daniel Pedra Adesse, Vladimir Pedro Peralva Borges Martins, Carolina Moreira dos Santos, Andre Luiz Land Curi, Emilly Caroline dos Santos Moraes, Guilherme Andrade de Santana, Gustavo Pinheiro de Araujo, Hilda Petrs Silva, | L30: 5114884 | M30: Estratégias terapêuticas antifibróticas baseadas em aptâmeros para reparo retiniano na toxoplasmose ocular | N30: PROGRAMA BASICO DE PARASITOLOGIA | O30: MP | P30: Ciências Biológicas | Q30: Protozoologia Parasitária Humana | R30: Fundação Oswaldo Cruz | S30: FIOCRUZ | T30: RJ | U30: SE | V30: Brasil | W30: Fundação Oswaldo Cruz | X30: FIOCRUZ | Y30: RJ | Z30: SE | AA30: Brasil | AB30: DCTI | AC30: COBIO | AD30: 27/05/2026 | AE30: 16:28:18 | AF30: 27/05/2026 | AG30: 17:20:26 | AH30: 4 | AI30: 755040 | AJ30: 0 | AK30: 0 | AL30: 755040 | AM30: Fundação Oswaldo Cruz | AN30: FIOCRUZ | AO30: RJ | AP30: SE | AQ30: Brasil | AR30: 8127213004748485 | AS30: 46202.465 | AT30: PCI2026 | AU30: Chamada CNPq/MCTI/FNDCT Nº 12/2026 - Programa PCI | AV30: Chamada: Chamada CNPq/MCTI/FNDCT Nº 12/2026 - Faixa 3: Projetos de Pesquisa vinculados a | AW30: 12/2026 | AX30: Chamada CNPq/MCTI/FNDCT Nº 12/2026 - Faixa 3: Projetos de Pesquisa vinculados a UPs Grandes (acima de 200 servidores) | AY30: 27/04/2026 | AZ30: 27/06/2026 | BA30: adesse@ioc.fiocruz.br | BB30: 401125/2026-2 | BC30: Daniel Pedra Adesse | BD30: Fundação Oswaldo Cruz | BE30: FIOCRUZ | BF30: =IF(AND(BG30,BI30,BL30,BM30),TRUE,FALSE) -> FALSE | BG30: FALSE | BH30: 2010 | BI30: FALSE | BJ30: Faixa 3 | BK30: Faixa 3 (3 propostas) | BL30: TRUE | BM30: TRUE | BN30: TRUE | BO30: - Fundação Oswaldo Cruz: (Servidor público - Pesquisador Titular) - Sociedade Brasileira de Protozoologia: (Membro Ordinário - Membro Ordinário) | BP30: =IF(IFERROR(VLOOKUP(A30,[1]Planilha1!$A:$A,1,0),FALSE)=FALSE,FALSE,TRUE) -> FALSE
A31: 402373/2026-0 | B31: APQ | D31: 46204 | E31: 47664 | F31: 36893266804 | G31: Daniela Aparecida Ferreira | H31: http://lattes.cnpq.br/7495449835021676 | I31: Daniela Aparecida Ferreira | K31: Daniela Aparecida Ferreira, Diogo Menezes Costa, Edithe da Silva Pereira, Scott Joseph Allen, Erêndira Oliveira, Juliane Roberta Chaves e Chaves, Lígia Carla Albino Marigliani, Jamily Barros Macedo, Camila Rosa do Nascimento | L31: 5116871 | M31: Arqueologia das relações globais na Amazônia: consolidação de competências científicas, redes de colaboração e formação de novos pesquisadores | N31: PROGRAMA BASICO DE ARQUEOLOGIA | O31: CS | P31: Ciências Humanas | Q31: Arqueologia Histórica | R31: Museu Paraense Emílio Goeldi | S31: MPEG | T31: PA | U31: NO | V31: Brasil | W31: Museu Paraense Emílio Goeldi | X31: MPEG | Y31: PA | Z31: NO | AA31: Brasil | AB31: DCTI | AC31: COSAE | AD31: 27/06/2026 | AE31: 18:07:53 | AF31: 27/06/2026 | AG31: 18:07:58 | AH31: 9 | AI31: 973440 | AJ31: 140608 | AK31: 0 | AL31: 1114048 | AM31: Museu Paraense Emílio Goeldi | AN31: MPEG | AO31: PA | AP31: NO | AQ31: Brasil | AR31: 7495449835021676 | AS31: 46202.465 | AT31: PCI2026 | AU31: Chamada CNPq/MCTI/FNDCT Nº 12/2026 - Programa PCI | AV31: Chamada: Chamada CNPq/MCTI/FNDCT Nº 12/2026 - Faixa 3: Projetos de Pesquisa vinculados a | AW31: 12/2026 | AX31: Chamada CNPq/MCTI/FNDCT Nº 12/2026 - Faixa 3: Projetos de Pesquisa vinculados a UPs Grandes (acima de 200 servidores) | AY31: 27/04/2026 | AZ31: 27/06/2026 | BA31: ferreiraapdaniela@gmail.com | BB31: 402373/2026-0 | BC31: Daniela Aparecida Ferreira | BD31: Museu Paraense Emílio Goeldi | BE31: MPEG | BF31: =IF(AND(BG31,BI31,BL31,BM31),TRUE,FALSE) -> TRUE | BG31: TRUE | BH31: 2025 | BI31: TRUE | BJ31: Faixa 3 | BK31: Faixa 3 (24 propostas) | BL31: TRUE | BM31: TRUE | BN31: TRUE | BO31: - Universidade Federal de Pernambuco: (COLABORADOR - Pesquisadora) - Universidade Federal do Oeste do Pará: (COLABORADOR - Pesquisadora) - Universidade Federal do Oeste do Pará: (COLABORADOR - Estágio pós-doutoral) - Universidade Federal do Pará: (em branco) - Museu Paraense Emílio Goeldi: (Servidor público - Pesquisadora) | BP31: =IF(IFERROR(VLOOKUP(A31,[1]Planilha1!$A:$A,1,0),FALSE)=FALSE,FALSE,TRUE) -> TRUE
A32: 401842/2026-6 | B32: APQ | D32: 46204 | E32: 47664 | F32: 03223856609 | G32: Danielle Palma de Oliveira | H32: http://lattes.cnpq.br/4347006311423350 | I32: Danielle Palma de Oliveira | K32: Danielle Palma de Oliveira, Flavia Renata Abe, Arthur Lima de Oliveira, Andréia Machado Leopoldino, Jaime Eduardo Cecilio Hallak | L32: 5116238 | M32: Desenvolvimento de uma plataforma de edição gênica por CRISPR-Cas9 em zebrafish para aplicações translacionais biotecnológicas e de neurofenotipagem | N32: PROGRAMA BASICO DE FARMACIA | O32: FR | P32: Ciências da Saúde | Q32: Avaliação e analises toxicológicas | R32: Universidade de São Paulo | S32: USP | T32: SP | U32: SE | V32: Brasil | W32: Universidade de São Paulo | X32: USP | Y32: SP | Z32: SE | AA32: Brasil | AB32: DCTI | AC32: COSAU | AD32: 22/06/2026 | AE32: 13:32:39 | AF32: 22/06/2026 | AG32: 13:32:55 | AH32: 3 | AI32: 570960 | AJ32: 808000 | AK32: 0 | AL32: 1378960 | AM32: Universidade de São Paulo | AN32: USP | AO32: SP | AP32: SE | AQ32: Brasil | AR32: 4347006311423350 | AS32: 46202.465 | AT32: PCI2026 | AU32: Chamada CNPq/MCTI/FNDCT Nº 12/2026 - Programa PCI | AV32: Chamada: Chamada CNPq/MCTI/FNDCT Nº 12/2026 - Faixa 3: Projetos de Pesquisa vinculados a | AW32: 12/2026 | AX32: Chamada CNPq/MCTI/FNDCT Nº 12/2026 - Faixa 3: Projetos de Pesquisa vinculados a UPs Grandes (acima de 200 servidores) | AY32: 27/04/2026 | AZ32: 27/06/2026 | BA32: oemaildadani@gmail.com | BB32: 401842/2026-6 | BC32: Danielle Palma de Oliveira | BD32: Universidade de São Paulo | BE32: USP | BF32: =IF(AND(BG32,BI32,BL32,BM32),TRUE,FALSE) -> FALSE | BG32: FALSE | BH32: 2005 | BI32: FALSE | BJ32: Faixa 3 | BK32: Faixa 3 (1 propostas) | BL32: TRUE | BM32: FALSE | BN32: FALSE | BO32: - FACULDADE DE CIÊNCIAS FARMACÊUTICAS DE RIBEIRÃO PRETO: (Servidor público - Professor Associado) - Universidade Estadual Paulista Júlio de Mesquita Filho: (COLABORADOR - colaborador) - Altox - assessoria Lider em Toxicologia: (consultora - atividade de consultoria) - Hispanic Organization of Toxicologists: (conselheira - Board councilor 2025 - 2026) | BP32: =IF(IFERROR(VLOOKUP(A32,[1]Planilha1!$A:$A,1,0),FALSE)=FALSE,FALSE,TRUE) -> FALSE
A33: 401212/2026-2 | B33: APQ | D33: 46204 | E33: 47664 | F33: 07510402824 | G33: Denise Maria Zezell | H33: http://lattes.cnpq.br/3524890504250775 | I33: Denise Maria Zezell | K33: Denise Maria Zezell, Elaine Bortoleti de Araújo, Emerson Soares Bernardes, Joaquim Cezar Felipe, Leandro Luongo de Matos | L33: 5115546 | M33: Capacitação Institucional em biofotônica, imagem hiperespectral e inteligência artificial para avaliação de tecidos biológicos e resposta a terapias radiofarmacêuticas | N33: PROGRAMA BASICO DE FISICA | O33: FA | P33: Ciências Exatas e da Terra | Q33: Prop. Óticas e Espectrosc. da Mat. Condens; Outras Inter. da | R33: COMISSAO NACIONAL DE ENERGIA NUCLEAR | S33: CNEN | T33: RJ | U33: SE | V33: Brasil | W33: COMISSAO NACIONAL DE ENERGIA NUCLEAR | X33: CNEN | Y33: RJ | Z33: SE | AA33: Brasil | AB33: DCTI | AC33: COCEC | AD33: 10/06/2026 | AE33: 12:56:12 | AF33: 10/06/2026 | AG33: 12:56:28 | AH33: 4 | AI33: 698880 | AJ33: 148620 | AK33: 0 | AL33: 847500 | AR33: 3524890504250775 | AS33: 46202.465 | AT33: PCI2026 | AU33: Chamada CNPq/MCTI/FNDCT Nº 12/2026 - Programa PCI | AV33: Chamada: Chamada CNPq/MCTI/FNDCT Nº 12/2026 - Faixa 3: Projetos de Pesquisa vinculados a | AW33: 12/2026 | AX33: Chamada CNPq/MCTI/FNDCT Nº 12/2026 - Faixa 3: Projetos de Pesquisa vinculados a UPs Grandes (acima de 200 servidores) | AY33: 27/04/2026 | AZ33: 27/06/2026 | BA33: zezell@gmail.com | BB33: 401212/2026-2 | BC33: Denise Maria Zezell | BD33: COMISSAO NACIONAL DE ENERGIA NUCLEAR | BE33: CNEN | BF33: =IF(AND(BG33,BI33,BL33,BM33),TRUE,FALSE) -> TRUE | BG33: TRUE | BH33: 1991 | BI33: TRUE | BJ33: Faixa 3 | BK33: Faixa 3 (32 propostas) | BL33: TRUE | BM33: TRUE | BN33: TRUE | BO33: - COMISSAO NACIONAL DE ENERGIA NUCLEAR: (Pesquisadora Titular) - COMISSAO NACIONAL DE ENERGIA NUCLEAR: (Servidor público - Coordenadora de Programa de Pós-Graduação) - Universidade de São Paulo: (COLABORADOR - Outro (docente do PPG Tecnologia Nuclear)) - Instituto de Pesquisas Energéticas Nucleares: (Servidor público - Pesquisadora Titular) - Instituto de Pesquisas Energéticas Nucleares: (Servidor público - Coordenadora da Pós-graduaçao Profiissional) - Fundação de Amparo à Ciência e Tecnologia do Estado de Pernambuco: (Membro de comitê assessor) - Optical Society of America: (Membro de comitê assessor) - Optical Society of America: (Membro de comitê assessor) - Third Word Academy of Sciences: (Membro de comitê assessor) - Universidade Federal de Pernambuco: (em branco) - Ministerio de Ciência, Tecnologia e Inovações: (Membro de comitê assessor) - Ministerio de Ciência, Tecnologia e Inovações: (Membro de comitê assessor) - Fundação de Amparo à Pesquisa do Estado de Minas Gerais: (Membro de comitê assessor) - Hospital das Clínicas da Faculdade de Medicina da USP: (em branco) - Ministério da Ciência, Tecnologia e Inovações: (Servidor público - BRICS Working Group of Photonics) - Ministério da Ciência, Tecnologia e Inovações: (Servidor público - Membro CCFOTO Comissão Consultiva de Fotônica) | BP33: =IF(IFERROR(VLOOKUP(A33,[1]Planilha1!$A:$A,1,0),FALSE)=FALSE,FALSE,TRUE) -> TRUE
A34: 402412/2026-5 | B34: APQ | D34: 46204 | E34: 47664 | F34: 61990817220 | G34: Diana Cruz Rodrigues | H34: http://lattes.cnpq.br/8998988531329512 | I34: Diana Cruz Rodrigues | K34: Diana Cruz Rodrigues, Ana Vilacy Moreira Galucio, Helena Pinto Lima, Sâmia Batista e Silva, Tarcízio Macedo, Mayara Larrys Gomes de Assis Nogueira, Dávila Suelen Souza Corrêa, Sandra Rufino | L34: 5116910 | M34: Observatório de Tecnologia Social da Amazônia | N34: PROGRAMA BASICO DE ADMINISTRACAO | O34: AE | P34: Ciências Sociais Aplicadas | Q34: Planejamento em Ciência e Tecnologia | R34: Museu Paraense Emílio Goeldi | S34: MPEG | T34: PA | U34: NO | V34: Brasil | W34: Museu Paraense Emílio Goeldi | X34: MPEG | Y34: PA | Z34: NO | AA34: Brasil | AB34: DCTI | AC34: COSAE | AD34: 27/06/2026 | AE34: 23:52:48 | AF34: 27/06/2026 | AG34: 23:52:55 | AH34: 4 | AI34: 561600 | AJ34: 73000 | AK34: 0 | AL34: 634600 | AM34: Museu Paraense Emílio Goeldi | AN34: MPEG | AO34: PA | AP34: NO | AQ34: Brasil | AR34: 8998988531329512 | AS34: 46202.465 | AT34: PCI2026 | AU34: Chamada CNPq/MCTI/FNDCT Nº 12/2026 - Programa PCI | AV34: Chamada: Chamada CNPq/MCTI/FNDCT Nº 12/2026 - Faixa 3: Projetos de Pesquisa vinculados a | AW34: 12/2026 | AX34: Chamada CNPq/MCTI/FNDCT Nº 12/2026 - Faixa 3: Projetos de Pesquisa vinculados a UPs Grandes (acima de 200 servidores) | AY34: 27/04/2026 | AZ34: 27/06/2026 | BA34: dicruzrodrigues@gmail.com | BB34: 402412/2026-5 | BC34: Diana Cruz Rodrigues | BD34: Museu Paraense Emílio Goeldi | BE34: MPEG | BF34: =IF(AND(BG34,BI34,BL34,BM34),TRUE,FALSE) -> TRUE | BG34: TRUE | BH34: 2019 | BI34: TRUE | BJ34: Faixa 3 | BK34: Faixa 3 (24 propostas) | BL34: TRUE | BM34: TRUE | BN34: TRUE | BO34: - Museu Paraense Emílio Goeldi: (Servidor público - Tecnologista) - Universidade da Amazônia: (CELETISTA - Professora) - Universidade Federal do Pará: (COLABORADOR - Membro de projeto de pesquisa) - Universidade Federal Rural da Amazônia: (Pesquisadora voluntária - Membro de projeto de pesquisa) - Associação Brasileira de Ensino, Pesquisa e Extensão em Tecnologia Social: (Voluntária - Coordenadora da Regional Norte) | BP34: =IF(IFERROR(VLOOKUP(A34,[1]Planilha1!$A:$A,1,0),FALSE)=FALSE,FALSE,TRUE) -> TRUE
A35: 401868/2026-5 | B35: APQ | D35: 46204 | E35: 47664 | F35: 02277747874 | G35: Dolores Ribeiro Ricci Lazar | H35: http://lattes.cnpq.br/4289995849705434 | I35: Dolores Ribeiro Ricci Lazar | K35: Dolores Ribeiro Ricci Lazar, Anderson Zanardi de Freitas, Carlos Roberto Jorge Soares, Cecília Chaves Guedes e Silva, Larissa Otubo, Flavio Machado de Souza Carvalho, Martha Simões Ribeiro, Niklaus Ursus Wetter, Ricardo | L35: 5116301 | M35: MXenos e seus compósitos: síntese, processamento e aplicações em saúde e energia | N35: PROGRAMA BASICO DE ENGENHARIA DE MATERIAIS E METALURGIA | O35: MM | P35: Engenharias | Q35: Cerâmicos | R35: COMISSAO NACIONAL DE ENERGIA NUCLEAR | S35: CNEN | T35: RJ | U35: SE | V35: Brasil | W35: COMISSAO NACIONAL DE ENERGIA NUCLEAR | X35: CNEN | Y35: RJ | Z35: SE | AA35: Brasil | AB35: DCTI | AC35: COBEN | AD35: 23/06/2026 | AE35: 11:43:39 | AF35: 23/06/2026 | AG35: 13:49:18 | AH35: 7 | AI35: 1300260 | AJ35: 106805 | AK35: 0 | AL35: 1407065 | AM35: COMISSAO NACIONAL DE ENERGIA NUCLEAR | AN35: CNEN | AO35: RJ | AP35: SE | AQ35: Brasil | AR35: 4289995849705434 | AS35: 46202.465 | AT35: PCI2026 | AU35: Chamada CNPq/MCTI/FNDCT Nº 12/2026 - Programa PCI | AV35: Chamada: Chamada CNPq/MCTI/FNDCT Nº 12/2026 - Faixa 3: Projetos de Pesquisa vinculados a | AW35: 12/2026 | AX35: Chamada CNPq/MCTI/FNDCT Nº 12/2026 - Faixa 3: Projetos de Pesquisa vinculados a UPs Grandes (acima de 200 servidores) | AY35: 27/04/2026 | AZ35: 27/06/2026 | BA35: drlazar@gmail.com | BB35: 401868/2026-5 | BC35: Dolores Ribeiro Ricci Lazar | BD35: COMISSAO NACIONAL DE ENERGIA NUCLEAR | BE35: CNEN | BF35: =IF(AND(BG35,BI35,BL35,BM35),TRUE,FALSE) -> TRUE | BG35: TRUE | BH35: 2002 | BI35: TRUE | BJ35: Faixa 3 | BK35: Faixa 3 (32 propostas) | BL35: TRUE | BM35: TRUE | BN35: TRUE | BO35: - COMISSAO NACIONAL DE ENERGIA NUCLEAR: (Servidor público - Pesquisador) - Universidade de São Paulo: (Professor de Pós-Graduação - Docente do Programa de Tecnologia Nuclear) | BP35: =IF(IFERROR(VLOOKUP(A35,[1]Planilha1!$A:$A,1,0),FALSE)=FALSE,FALSE,TRUE) -> TRUE
A36: 402379/2026-8 | B36: APQ | D36: 46204 | E36: 47664 | F36: 05666762818 | G36: Duclerc Fernandes Parra | H36: http://lattes.cnpq.br/1691114842151172 | I36: Duclerc Fernandes Parra | K36: Duclerc Fernandes Parra, Clotilde Coppini Pereira | L36: 5116877 | M36: Uso da Radiação Ionizante para Avaliação da Degradação na Formação de Microplásticos em Filmes Agrícolas Biodegradáveis | N36: PROGRAMA BASICO DE ENGENHARIA DE MATERIAIS E METALURGIA | O36: MM | P36: Engenharias | Q36: Materiais Não-Metálicos | R36: COMISSAO NACIONAL DE ENERGIA NUCLEAR | S36: CNEN | T36: RJ | U36: SE | V36: Brasil | W36: COMISSAO NACIONAL DE ENERGIA NUCLEAR | X36: CNEN | Y36: RJ | Z36: SE | AA36: Brasil | AB36: DCTI | AC36: COBEN | AD36: 27/06/2026 | AE36: 19:09:32 | AF36: 27/06/2026 | AG36: 19:09:40 | AH36: 3 | AI36: 492480 | AJ36: 44928 | AK36: 0 | AL36: 537408 | AM36: COMISSAO NACIONAL DE ENERGIA NUCLEAR | AN36: CNEN | AO36: RJ | AP36: SE | AQ36: Brasil | AR36: 1691114842151172 | AS36: 46202.465 | AT36: PCI2026 | AU36: Chamada CNPq/MCTI/FNDCT Nº 12/2026 - Programa PCI | AV36: Chamada: Chamada CNPq/MCTI/FNDCT Nº 12/2026 - Faixa 3: Projetos de Pesquisa vinculados a | AW36: 12/2026 | AX36: Chamada CNPq/MCTI/FNDCT Nº 12/2026 - Faixa 3: Projetos de Pesquisa vinculados a UPs Grandes (acima de 200 servidores) | AY36: 27/04/2026 | AZ36: 27/06/2026 | BA36: parduclerc@yahoo.com.br | BB36: 402379/2026-8 | BC36: Duclerc Fernandes Parra | BD36: COMISSAO NACIONAL DE ENERGIA NUCLEAR | BE36: CNEN | BF36: =IF(AND(BG36,BI36,BL36,BM36),TRUE,FALSE) -> TRUE | BG36: TRUE | BH36: 1996 | BI36: TRUE | BJ36: Faixa 3 | BK36: Faixa 3 (32 propostas) | BL36: TRUE | BM36: TRUE | BN36: TRUE | BO36: - COMISSAO NACIONAL DE ENERGIA NUCLEAR: (Servidor público - Pesquisador Adjunto) | BP36: =IF(IFERROR(VLOOKUP(A36,[1]Planilha1!$A:$A,1,0),FALSE)=FALSE,FALSE,TRUE) -> TRUE
A37: 402307/2026-7 | B37: APQ | D37: 46204 | E37: 47664 | F37: 97108030772 | G37: Eliane D Elia | H37: http://lattes.cnpq.br/2739863135439867 | I37: Eliane D Elia | K37: Eliane D Elia, Victor Magno Paiva, Erica Cristina de Fatima Teixeira Machado de Melo, Fellipe dos Santos Pereira, Iris Gonçalves da Silva Moreira, Annelise Casellato, Emerson Schwingel Ribeiro, Natasha Midori Suguihiro, Marco | L37: 5116805 | M37: Desenvolvimento de Pontos Quânticos de Carbono a partir de Biomassa para Aplicações Estratégicas em Proteção de Materiais, Sustentabilidade Industrial e Valorização de CO2; | N37: PROGRAMA BASICO DE ENGENHARIA DE MATERIAIS E METALURGIA | O37: MM | P37: Engenharias | Q37: Corrosão | R37: Universidade Federal do Rio de Janeiro | S37: UFRJ | T37: RJ | U37: SE | V37: Brasil | W37: Universidade Federal do Rio de Janeiro | X37: UFRJ | Y37: RJ | Z37: SE | AA37: Brasil | AB37: DCTI | AC37: COBEN | AD37: 27/06/2026 | AE37: 11:05:46 | AF37: 27/06/2026 | AG37: 11:05:51 | AH37: 7 | AI37: 1152060 | AJ37: 117844 | AK37: 0 | AL37: 1269904 | AM37: Universidade Federal do Rio de Janeiro | AN37: UFRJ | AO37: RJ | AP37: SE | AQ37: Brasil | AR37: 2739863135439867 | AS37: 46202.465 | AT37: PCI2026 | AU37: Chamada CNPq/MCTI/FNDCT Nº 12/2026 - Programa PCI | AV37: Chamada: Chamada CNPq/MCTI/FNDCT Nº 12/2026 - Faixa 3: Projetos de Pesquisa vinculados a | AW37: 12/2026 | AX37: Chamada CNPq/MCTI/FNDCT Nº 12/2026 - Faixa 3: Projetos de Pesquisa vinculados a UPs Grandes (acima de 200 servidores) | AY37: 27/04/2026 | AZ37: 27/06/2026 | BA37: eliane@iq.ufrj.br | BB37: 402307/2026-7 | BC37: Eliane D Elia | BD37: Universidade Federal do Rio de Janeiro | BE37: UFRJ | BF37: =IF(AND(BG37,BI37,BL37,BM37),TRUE,FALSE) -> FALSE | BG37: FALSE | BH37: 1996 | BI37: FALSE | BJ37: Faixa 3 | BK37: Faixa 3 (6 propostas) | BL37: TRUE | BM37: TRUE | BN37: TRUE | BO37: - Universidade Federal do Rio de Janeiro: (Servidor público - PROFESSOR_TITULAR) - UFRJ: (em branco) | BP37: =IF(IFERROR(VLOOKUP(A37,[1]Planilha1!$A:$A,1,0),FALSE)=FALSE,FALSE,TRUE) -> FALSE
A38: 402100/2026-3 | B38: APQ | D38: 46204 | E38: 47664 | F38: 14671860821 | G38: Elisabete Inacio Santiago | H38: http://lattes.cnpq.br/4409120770460899 | I38: Elisabete Inacio Santiago | K38: Elisabete Inacio Santiago, Almir Oliveira Neto, Fabio Coral Fonseca, Estevam Vitorio Spinacé | L38: 5116592 | M38: Capacitação institucional em novas energias: contribuindo com uma transição energética sustentável | N38: Programa Básico de Engenharia de Energia | O38: EN | P38: Engenharias | Q38: Sistemas Híbridos e Sistemas Não-convencionais de | R38: COMISSAO NACIONAL DE ENERGIA NUCLEAR | S38: CNEN | T38: RJ | U38: SE | V38: Brasil | W38: COMISSAO NACIONAL DE ENERGIA NUCLEAR | X38: CNEN | Y38: RJ | Z38: SE | AA38: Brasil | AB38: DCTI | AC38: COBEN | AD38: 26/06/2026 | AE38: 13:47:15 | AF38: 27/06/2026 | AG38: 09:52:38 | AH38: 5 | AI38: 1051440 | AJ38: 132000 | AK38: 0 | AL38: 1183440 | AM38: Universidade de São Paulo | AN38: USP | AO38: SP | AP38: SE | AQ38: Brasil | AR38: 4409120770460899 | AS38: 46202.465 | AT38: PCI2026 | AU38: Chamada CNPq/MCTI/FNDCT Nº 12/2026 - Programa PCI | AV38: Chamada: Chamada CNPq/MCTI/FNDCT Nº 12/2026 - Faixa 3: Projetos de Pesquisa vinculados a | AW38: 12/2026 | AX38: Chamada CNPq/MCTI/FNDCT Nº 12/2026 - Faixa 3: Projetos de Pesquisa vinculados a UPs Grandes (acima de 200 servidores) | AY38: 27/04/2026 | AZ38: 27/06/2026 | BA38: elisabete.santiago@usp.br | BB38: 402100/2026-3 | BC38: Elisabete Inacio Santiago | BD38: COMISSAO NACIONAL DE ENERGIA NUCLEAR | BE38: CNEN | BF38: =TRUE -> TRUE | BG38: TRUE | BH38: 2001 | BI38: TRUE | BJ38: Faixa 3 | BK38: Faixa 3 (32 propostas) | BL38: TRUE | BM38: =TRUE -> TRUE | BN38: =TRUE -> TRUE | BO38: - Universidade Federal de São Carlos: (PROFESSOR_VISITANTE - Pesquisador Visitante) - Instituto de Pesquisas Energéticas e Nucleares: (Servidor público - Pesquisadora Titular) - Universidade de São Paulo: (COLABORADOR - Professor de Pós-Graduação) - Universidade de São Paulo: (Servidor público - Representante da CPG IPEN/USP) - Universidade Estadual de Campinas: (em branco) | BP38: =IF(IFERROR(VLOOKUP(A38,[1]Planilha1!$A:$A,1,0),FALSE)=FALSE,FALSE,TRUE) -> TRUE
A39: 401189/2026-0 | B39: APQ | D39: 46204 | E39: 47664 | F39: 12314676300 | G39: Elita Fontenele Urano de Carvalho | H39: http://lattes.cnpq.br/1122522095905469 | I39: Elita Fontenele Urano de Carvalho | K39: Elita Fontenele Urano de Carvalho, Lauro Roberto dos Santos, Ricardo Mendes Leal Neto, Michelangelo Durazzo, Eriki Masahiko Takara | L39: 5115506 | M39: Capacitação Institucional do IPEN/CECON em Tecnologia de Fabricação de Combustível Nuclear de Nitreto de Urânio para Microrreatores | N39: PROGRAMA BASICO DE ENGENHARIA NUCLEAR | O39: EN | P39: Engenharias | Q39: Conversão, Enriquecimento e Fabricação de Combustível | R39: COMISSAO NACIONAL DE ENERGIA NUCLEAR | S39: CNEN | T39: RJ | U39: SE | V39: Brasil | W39: COMISSAO NACIONAL DE ENERGIA NUCLEAR | X39: CNEN | Y39: RJ | Z39: SE | AA39: Brasil | AB39: DCTI | AC39: COBEN | AD39: 08/06/2026 | AE39: 09:35:23 | AF39: 08/06/2026 | AG39: 09:35:39 | AH39: 2 | AI39: 374400 | AJ39: 48672 | AK39: 0 | AL39: 423072 | AR39: 1122522095905469 | AS39: 46202.465 | AT39: PCI2026 | AU39: Chamada CNPq/MCTI/FNDCT Nº 12/2026 - Programa PCI | AV39: Chamada: Chamada CNPq/MCTI/FNDCT Nº 12/2026 - Faixa 3: Projetos de Pesquisa vinculados a | AW39: 12/2026 | AX39: Chamada CNPq/MCTI/FNDCT Nº 12/2026 - Faixa 3: Projetos de Pesquisa vinculados a UPs Grandes (acima de 200 servidores) | AY39: 27/04/2026 | AZ39: 27/06/2026 | BA39: elitaucf@gmail.com | BB39: 401189/2026-0 | BC39: Elita Fontenele Urano de Carvalho | BD39: COMISSAO NACIONAL DE ENERGIA NUCLEAR | BE39: CNEN | BF39: =IF(AND(BG39,BI39,BL39,BM39),TRUE,FALSE) -> TRUE | BG39: TRUE | BH39: 2004 | BI39: TRUE | BJ39: Faixa 3 | BK39: Faixa 3 (32 propostas) | BL39: TRUE | BM39: TRUE | BN39: FALSE | BO39: - instituto de pesquisas energéticas e nucleares: (SERVIDOR_PUBLICO - Tecnologista Senior) - instituto de pesquisas energéticas e nucleares: (SERVIDOR_PUBLICO - Tecnologista Senior) - Universidade Comunitária da Região de Chapecó: (em branco) - Universidade do Extremo Sul Catarinense: (em branco) - Universidade Federal de Santa Catarina: (em branco) - INSTITUTO PESQUISAS ENERGETICAS E NUCLEARES: (em branco) - COMISSAO NACIONAL DE ENERGIA NUCLEAR: (em branco) | BP39: =IF(IFERROR(VLOOKUP(A39,[1]Planilha1!$A:$A,1,0),FALSE)=FALSE,FALSE,TRUE) -> TRUE
A40: 402073/2026-6 | B40: APQ | D40: 46204 | E40: 47664 | F40: 17976073249 | G40: Elizabeth Gusmão Affonso | H40: http://lattes.cnpq.br/3096604627879612 | I40: Elizabeth Gusmão Affonso | K40: Elizabeth Gusmão Affonso, Rogério Souza de Jesus, Paulo Adelino de Medeiros, Yury Oliveira Chaves, Valdelira Lia Araújo Fernandes, Elcimara Cardoso Pereira, Alana Cristina Vinhote da Silva | L40: 5116564 | M40: Aquicultura como elo de fortalecimento da bioeconomia circular na Amazônia | N40: PROGRAMA BASICO DE AQUICULTURA | O40: AQ | P40: Ciências Agrárias | Q40: Aqüicultura | R40: Instituto Nacional de Pesquisas da Amazônia | S40: INPA | T40: AM | U40: NO | V40: Brasil | W40: Instituto Nacional de Pesquisas da Amazônia | X40: INPA | Y40: AM | Z40: NO | AA40: Brasil | AB40: DCTI | AC40: COAGR | AD40: 26/06/2026 | AE40: 22:00:04 | AF40: 27/06/2026 | AG40: 09:51:02 | AH40: 9 | AI40: 1352640 | AJ40: 122208 | AK40: 0 | AL40: 1474848 | AM40: Instituto Nacional de Pesquisas da Amazônia | AN40: INPA | AO40: AM | AP40: NO | AQ40: Brasil | AR40: 3096604627879612 | AS40: 46202.465 | AT40: PCI2026 | AU40: Chamada CNPq/MCTI/FNDCT Nº 12/2026 - Programa PCI | AV40: Chamada: Chamada CNPq/MCTI/FNDCT Nº 12/2026 - Faixa 3: Projetos de Pesquisa vinculados a | AW40: 12/2026 | AX40: Chamada CNPq/MCTI/FNDCT Nº 12/2026 - Faixa 3: Projetos de Pesquisa vinculados a UPs Grandes (acima de 200 servidores) | AY40: 27/04/2026 | AZ40: 27/06/2026 | BA40: pgusmao1@yahoo.com.br | BB40: 402073/2026-6 | BC40: Elizabeth Gusmão Affonso | BD40: Instituto Nacional de Pesquisas da Amazônia | BE40: INPA | BF40: =IF(AND(BG40,BI40,BL40,BM40),TRUE,FALSE) -> TRUE | BG40: TRUE | BH40: 2000 | BI40: TRUE | BJ40: Faixa 3 | BK40: Faixa 3 (15 propostas) | BL40: TRUE | BM40: TRUE | BN40: TRUE | BO40: - Instituto Nacional de Pesquisas da Amazônia: (Servidor público - Pesquisador Titular III) - UNIVERSIDADE NILTON LINS: (CELETISTA - Professora Adjunta, Nível I) - Fundação de Amparo a Pesquisa do Estado do Amazonas: (Membro de comitê assessor) - SECRETARIA DE PRODUÇÃO RURAL: (Membro de comitê assessor) | BP40: =IF(IFERROR(VLOOKUP(A40,[1]Planilha1!$A:$A,1,0),FALSE)=FALSE,FALSE,TRUE) -> TRUE
A41: 402201/2026-4 | B41: APQ | D41: 46204 | E41: 47664 | F41: 09338080200 | G41: Eloisa Helena de Aguiar Andrade | H41: http://lattes.cnpq.br/3827055876022373 | I41: Eloisa Helena de Aguiar Andrade | K41: Eloisa Helena de Aguiar Andrade, Kheytiany Hellen da Silva Lopes, Ely Simone Cajueiro Gurgel, Marlia Regina Coelho-Ferreira | L41: 5116695 | M41: Bioprospecção na Floresta Nacional de Caxiuanã: Abordagens Etnobotânicas, Químicas e Anatômicas para Conservação e Bioeconomia | N41: PROGRAMA BASICO DE BOTANICA | O41: BO | P41: Ciências Biológicas | Q41: Botânica Aplicada | R41: Museu Paraense Emílio Goeldi | S41: MPEG | T41: PA | U41: NO | V41: Brasil | W41: Museu Paraense Emílio Goeldi | X41: MPEG | Y41: PA | Z41: NO | AA41: Brasil | AB41: DCTI | AC41: COEBI | AD41: 26/06/2026 | AE41: 17:38:43 | AF41: 27/06/2026 | AG41: 09:58:43 | AH41: 5 | AI41: 1010880 | AJ41: 185856 | AK41: 0 | AL41: 1196736 | AM41: Universidade Federal do Pará | AN41: UFPA | AO41: PA | AP41: NO | AQ41: Brasil | AR41: 3827055876022373 | AS41: 46202.465 | AT41: PCI2026 | AU41: Chamada CNPq/MCTI/FNDCT Nº 12/2026 - Programa PCI | AV41: Chamada: Chamada CNPq/MCTI/FNDCT Nº 12/2026 - Faixa 3: Projetos de Pesquisa vinculados a | AW41: 12/2026 | AX41: Chamada CNPq/MCTI/FNDCT Nº 12/2026 - Faixa 3: Projetos de Pesquisa vinculados a UPs Grandes (acima de 200 servidores) | AY41: 27/04/2026 | AZ41: 27/06/2026 | BA41: eloisa@museu-goeldi.br | BB41: 402201/2026-4 | BC41: Eloisa Helena de Aguiar Andrade | BD41: Museu Paraense Emílio Goeldi | BE41: MPEG | BF41: =IF(AND(BG41,BI41,BL41,BM41),TRUE,FALSE) -> TRUE | BG41: TRUE | BH41: 2008 | BI41: TRUE | BJ41: Faixa 3 | BK41: Faixa 3 (24 propostas) | BL41: TRUE | BM41: TRUE | BN41: FALSE | BO41: - Museu Paraense Emílio Goeldi: (Pesquisador Adjunto I) - Universidade Federal do Pará: (Servidor público - Professor adjunto) - Universidade Federal da Paraíba: (em branco) | BP41: =IF(IFERROR(VLOOKUP(A41,[1]Planilha1!$A:$A,1,0),FALSE)=FALSE,FALSE,TRUE) -> TRUE
A42: 401989/2026-7 | B42: APQ | D42: 46204 | E42: 47664 | F42: 27288306810 | G42: Elvis Joacir De França | H42: http://lattes.cnpq.br/1716496767364751 | I42: Elvis Joacir De França | K42: Elvis Joacir De França, Cláudio José Mesquita Menezes, Luiz Carlos Gonçalves Filho, Valderes Moraes de Almeida, Rômulo Pinto Tenório, Fernando Roberto de Andrade Lima, Everton Rodrigues da Silva, Carlos Alberto Brayner de | L42: 5116472 | M42: PROGRAMA DE CAPACITAÇÃO INSTITUCIONAL DOS LABORATÓRIOS MULTIUSUÁRIOS INTEGRADOS PARA APLICAÇÕES NUCLEARES NAS REGIÕES NORTE E NORDESTE  LINAN-PCI | N42: PROGRAMA BASICO DE ENGENHARIA NUCLEAR | O42: EN | P42: Engenharias | Q42: Aplicações de Radioisótopos | R42: COMISSAO NACIONAL DE ENERGIA NUCLEAR | S42: CNEN | T42: RJ | U42: SE | V42: Brasil | W42: COMISSAO NACIONAL DE ENERGIA NUCLEAR | X42: CNEN | Y42: RJ | Z42: SE | AA42: Brasil | AB42: DCTI | AC42: COBEN | AD42: 25/06/2026 | AE42: 16:46:27 | AF42: 25/06/2026 | AG42: 16:46:30 | AH42: 9 | AI42: 1072800 | AJ42: 105000 | AK42: 0 | AL42: 1177800 | AM42: COMISSAO NACIONAL DE ENERGIA NUCLEAR | AN42: CNEN | AO42: RJ | AP42: SE | AQ42: Brasil | AR42: 1716496767364751 | AS42: 46202.465 | AT42: PCI2026 | AU42: Chamada CNPq/MCTI/FNDCT Nº 12/2026 - Programa PCI | AV42: Chamada: Chamada CNPq/MCTI/FNDCT Nº 12/2026 - Faixa 3: Projetos de Pesquisa vinculados a | AW42: 12/2026 | AX42: Chamada CNPq/MCTI/FNDCT Nº 12/2026 - Faixa 3: Projetos de Pesquisa vinculados a UPs Grandes (acima de 200 servidores) | AY42: 27/04/2026 | AZ42: 27/06/2026 | BA42: ejfranca@gmail.com | BB42: 401989/2026-7 | BC42: Elvis Joacir De França | BD42: COMISSAO NACIONAL DE ENERGIA NUCLEAR | BE42: CNEN | BF42: =IF(AND(BG42,BI42,BL42,BM42),TRUE,FALSE) -> TRUE | BG42: TRUE | BH42: 2006 | BI42: TRUE | BJ42: Faixa 3 | BK42: Faixa 3 (32 propostas) | BL42: TRUE | BM42: TRUE | BN42: TRUE | BO42: - Universidade de São Paulo: (COLABORADOR - Pesquisador) - COMISSAO NACIONAL DE ENERGIA NUCLEAR: (Servidor público - Pesquisador Associado) - COMISSAO NACIONAL DE ENERGIA NUCLEAR: (Servidor público - Chefia SEPID) - COMISSAO NACIONAL DE ENERGIA NUCLEAR: (Servidor público - Coordenador CEUA) - Universidade Federal de Pernambuco: (Professor Doutor - Professor Doutor Permanente) - COMISSAO NACIONAL DE ENERGIA NUCLEAR: (em branco) | BP42: =IF(IFERROR(VLOOKUP(A42,[1]Planilha1!$A:$A,1,0),FALSE)=FALSE,FALSE,TRUE) -> TRUE
A43: 402011/2026-0 | B43: APQ | D43: 46204 | E43: 47664 | F43: 36268839811 | G43: Erêndira Oliveira | H43: http://lattes.cnpq.br/1336094438987346 | I43: Erêndira Oliveira | K43: Erêndira Oliveira, Helena Pinto Lima, Daniela Aparecida Ferreira, Cristiana Nunes Galvão de Barros Barreto, Igor Morais Mariano Rodrigues, Edithe da Silva Pereira, Sâmia Batista e Silva, Marcia Bezerra de Almeida, Filipe de | L43: 5116501 | M43: Acervos em Rede: preservação digital, gestão da informação e socialização do patrimônio arqueológico amazônico | N43: PROGRAMA BASICO DE ARQUEOLOGIA | O43: CS | P43: Ciências Humanas | Q43: Teoria e Método em Arqueologia | R43: Museu Paraense Emílio Goeldi | S43: MPEG | T43: PA | U43: NO | V43: Brasil | W43: Museu Paraense Emílio Goeldi | X43: MPEG | Y43: PA | Z43: NO | AA43: Brasil | AB43: DCTI | AC43: COSAE | AD43: 26/06/2026 | AE43: 00:13:16 | AF43: 26/06/2026 | AG43: 00:13:25 | AH43: 6 | AI43: 449280 | AJ43: 58406.4 | AK43: 0 | AL43: 507686.4 | AM43: Museu Paraense Emílio Goeldi | AN43: MPEG | AO43: PA | AP43: NO | AQ43: Brasil | AR43: 1336094438987346 | AS43: 46202.465 | AT43: PCI2026 | AU43: Chamada CNPq/MCTI/FNDCT Nº 12/2026 - Programa PCI | AV43: Chamada: Chamada CNPq/MCTI/FNDCT Nº 12/2026 - Faixa 3: Projetos de Pesquisa vinculados a | AW43: 12/2026 | AX43: Chamada CNPq/MCTI/FNDCT Nº 12/2026 - Faixa 3: Projetos de Pesquisa vinculados a UPs Grandes (acima de 200 servidores) | AY43: 27/04/2026 | AZ43: 27/06/2026 | BA43: erendiraoliveira@museu-goeldi.br | BB43: 402011/2026-0 | BC43: Erêndira Oliveira | BD43: Museu Paraense Emílio Goeldi | BE43: MPEG | BF43: =IF(AND(BG43,BI43,BL43,BM43),TRUE,FALSE) -> TRUE | BG43: TRUE | BH43: 2022 | BI43: TRUE | BJ43: Faixa 3 | BK43: Faixa 3 (24 propostas) | BL43: TRUE | BM43: TRUE | BN43: TRUE | BO43: - Museu Paraense Emílio Goeldi: (Servidor público - Tecnologista/Pesquisadora) - Museu Paraense Emílio Goeldi: (Servidor público - Professora Permanente) - Museu da Amazonia: (COLABORADOR - Pesquisadora) - Sociedade de Arqueologia Brasileira: (COLABORADOR - Membro de comissão de organização de evento) - Sociedade de Arqueologia Brasileira: (COLABORADOR - Membro de comissão de revisão de Regimento) | BP43: =IF(IFERROR(VLOOKUP(A43,[1]Planilha1!$A:$A,1,0),FALSE)=FALSE,FALSE,TRUE) -> TRUE
A44: 401237/2026-5 | B44: APQ | D44: 46204 | E44: 47664 | F44: 18438367852 | G44: Érika Renata Branco | H44: http://lattes.cnpq.br/3978060547725760 | I44: Érika Renata Branco | K44: Érika Renata Branco, Ana Rita de Lima, Adriana Caroprezo Morini, Daniele dos Santos Martins, José Ledamir Sindeaux Neto, Michele Velasco Oliveira da Silva, Lilian de Jesus Oliveira, Antônio Chaves de Assis Neto, Paula | L44: 5115574 | M44: Modelos 3D Phygitais como Estratégia Multissensorial para Ensino Inclusivo em Ciências da Saúde | N44: Programa Especial de Biotecnologia e Recursos Genéticos - COBRG | O44: BI | P44: Outra | Q44: Ensino | R44: Universidade Federal Rural da Amazônia | S44: UFRA | T44: PA | U44: NO | V44: Brasil | W44: Universidade Federal Rural da Amazônia | X44: UFRA | Y44: PA | Z44: NO | AA44: Brasil | AB44: DCTI | AC44: COBEN | AD44: 11/06/2026 | AE44: 15:53:28 | AF44: 11/06/2026 | AG44: 15:53:37 | AH44: 7 | AI44: 1223040 | AJ44: 122304 | AK44: 0 | AL44: 1345344 | AM44: Universidade Federal Rural da Amazônia | AN44: UFRA | AO44: PA | AP44: NO | AQ44: Brasil | AR44: 3978060547725760 | AS44: 46202.465 | AT44: PCI2026 | AU44: Chamada CNPq/MCTI/FNDCT Nº 12/2026 - Programa PCI | AV44: Chamada: Chamada CNPq/MCTI/FNDCT Nº 12/2026 - Faixa 3: Projetos de Pesquisa vinculados a | AW44: 12/2026 | AX44: Chamada CNPq/MCTI/FNDCT Nº 12/2026 - Faixa 3: Projetos de Pesquisa vinculados a UPs Grandes (acima de 200 servidores) | AY44: 27/04/2026 | AZ44: 27/06/2026 | BA44: ebranco.ufra@gmail.com | BB44: 401237/2026-5 | BC44: Érika Renata Branco | BD44: Universidade Federal Rural da Amazônia | BE44: UFRA | BF44: =IF(AND(BG44,BI44,BL44,BM44),TRUE,FALSE) -> FALSE | BG44: FALSE | BH44: 2007 | BI44: FALSE | BJ44: Faixa 3 | BK44: Faixa 3 (2 propostas) | BL44: TRUE | BM44: TRUE | BN44: TRUE | BO44: - Universidade Federal Rural da Amazônia: (Servidor público - Membro do Colegiado da Pós-Graduação em Saúde) - Universidade Federal Rural da Amazônia: (Docente - Docente do Programa de Pós-Graduação) - Universidade Federal Rural da Amazônia: (Servidor público - Membro Colegiado ISPA) - Universidade Federal Rural da Amazônia: (Servidor público - Membro Comissão Científica) - Universidade Federal Rural da Amazônia: (Servidor público - Professora Titular) - Universidade Federal Rural da Amazônia: (Coordenadora do PPGSPAA - Coordenadora do PPGSPAA) - Fundação de Amparo à Ciência e Tecnologia do Estado de Pernambuco: (Membro de comitê assessor) - Fundação de Amparo à Ciência e Tecnologia do Estado do Pará: (Membro de comitê assessor) | BP44: =IF(IFERROR(VLOOKUP(A44,[1]Planilha1!$A:$A,1,0),FALSE)=FALSE,FALSE,TRUE) -> FALSE
A45: 402177/2026-6 | B45: APQ | D45: 46204 | E45: 47664 | F45: 97650927849 | G45: Evaldo Jose Corat | H45: http://lattes.cnpq.br/0560039556461253 | I45: Evaldo Jose Corat | K45: Evaldo Jose Corat, Vladimir Jesus Trava-Airoldi, Erica Freire Antunes, Gisele Aparecida Amaral Labat, Ricardo Cotrin Teixeira, Eduardo Cezar Barbosa de Barros Aragão, Sergio Luiz Mineiro | L45: 5116671 | M45: CARBON4SPACE: Capacitação Institucional para Desenvolvimento de Aplicações Aeroespaciais com Materiais Avançados de Carbono | N45: PROGRAMA BASICO DE ENGENHARIA AEROESPACIAL | O45: EM | P45: Engenharias | Q45: Materiais e Processos para Engenharia Aeronáutica e | R45: Instituto Nacional de Pesquisas Espaciais | S45: INPE | T45: SP | U45: SE | V45: Brasil | W45: Instituto Nacional de Pesquisas Espaciais | X45: INPE | Y45: SP | Z45: SE | AA45: Brasil | AB45: DCTI | AC45: COENG | AD45: 26/06/2026 | AE45: 09:07:09 | AF45: 27/06/2026 | AG45: 09:57:18 | AH45: 5 | AI45: 1048320 | AJ45: 136281.6 | AK45: 0 | AL45: 1184601.6 | AM45: Instituto Nacional de Pesquisas Espaciais | AN45: INPE | AO45: SP | AP45: SE | AQ45: Brasil | AR45: 0560039556461253 | AS45: 46202.465 | AT45: PCI2026 | AU45: Chamada CNPq/MCTI/FNDCT Nº 12/2026 - Programa PCI | AV45: Chamada: Chamada CNPq/MCTI/FNDCT Nº 12/2026 - Faixa 3: Projetos de Pesquisa vinculados a | AW45: 12/2026 | AX45: Chamada CNPq/MCTI/FNDCT Nº 12/2026 - Faixa 3: Projetos de Pesquisa vinculados a UPs Grandes (acima de 200 servidores) | AY45: 27/04/2026 | AZ45: 27/06/2026 | BA45: evaldocorat@gmail.com | BB45: 402177/2026-6 | BC45: Evaldo Jose Corat | BD45: Instituto Nacional de Pesquisas Espaciais | BE45: INPE | BF45: =IF(AND(BG45,BI45,BL45,BM45),TRUE,FALSE) -> FALSE | BG45: TRUE | BH45: 1993 | BI45: TRUE | BJ45: Faixa 3 | BK45: Faixa 3 (20 propostas) | BL45: TRUE | BM45: FALSE | BN45: FALSE | BO45: - Laboratório Associado de Sensores e Materiais: (Servidor público ou celetista - Pesquisador Titular) - Universidade Federal de São Paulo: (Professor Colaborador - Professor Colaborador) | BP45: =IF(IFERROR(VLOOKUP(A45,[1]Planilha1!$A:$A,1,0),FALSE)=FALSE,FALSE,TRUE) -> FALSE
A46: 402076/2026-5 | B46: APQ | D46: 46204 | E46: 47664 | F46: 17639834805 | G46: Eveline De Robertis | H46: http://lattes.cnpq.br/8932748949591727 | I46: Eveline De Robertis | K46: Eveline De Robertis, Alberto de Paula Silva, Bárbara Alessandra Gonçalves Pinheiro Yamada, Renato Henrique Ferreira Branco, Isabela Araújo Resende, Andreia Fatima Sorice Genaro | L46: 5116567 | M46: Plataforma Integrada para a Gestão do Portfólio Institucional do INPE | N46: PROGRAMA BASICO DE ADMINISTRACAO | O46: AE | P46: Ciências Sociais Aplicadas | Q46: Planejamento em Ciência e Tecnologia | R46: Instituto Nacional de Pesquisas Espaciais | S46: INPE | T46: SP | U46: SE | V46: Brasil | W46: Instituto Nacional de Pesquisas Espaciais | X46: INPE | Y46: SP | Z46: SE | AA46: Brasil | AB46: DCTI | AC46: COSAE | AD46: 25/06/2026 | AE46: 18:25:57 | AF46: 27/06/2026 | AG46: 09:51:11 | AH46: 3 | AI46: 499200 | AJ46: 64896 | AK46: 0 | AL46: 564096 | AM46: Instituto Nacional de Pesquisas Espaciais | AN46: INPE | AO46: SP | AP46: SE | AQ46: Brasil | AR46: 8932748949591727 | AS46: 46202.465 | AT46: PCI2026 | AU46: Chamada CNPq/MCTI/FNDCT Nº 12/2026 - Programa PCI | AV46: Chamada: Chamada CNPq/MCTI/FNDCT Nº 12/2026 - Faixa 3: Projetos de Pesquisa vinculados a | AW46: 12/2026 | AX46: Chamada CNPq/MCTI/FNDCT Nº 12/2026 - Faixa 3: Projetos de Pesquisa vinculados a UPs Grandes (acima de 200 servidores) | AY46: 27/04/2026 | AZ46: 27/06/2026 | BA46: erobertis@yahoo.com.br | BB46: 402076/2026-5 | BC46: Eveline De Robertis | BD46: Instituto Nacional de Pesquisas Espaciais | BE46: INPE | BF46: =IF(AND(BG46,BI46,BL46,BM46),TRUE,FALSE) -> TRUE | BG46: TRUE | BH46: 2004 | BI46: TRUE | BJ46: Faixa 3 | BK46: Faixa 3 (20 propostas) | BL46: TRUE | BM46: TRUE | BN46: TRUE | BO46: - Instituto Nacional de Pesquisas Espaciais: (Servidor público - Pesquisadora) | BP46: =IF(IFERROR(VLOOKUP(A46,[1]Planilha1!$A:$A,1,0),FALSE)=FALSE,FALSE,TRUE) -> TRUE
A47: 402157/2026-5 | B47: APQ | D47: 46204 | E47: 47664 | F47: 58908013091 | G47: Ezequiel Echer | H47: http://lattes.cnpq.br/3869820274542343 | I47: Ezequiel Echer | K47: Ezequiel Echer, Alisson Dal Lago, Franciele Carlesso, Vânia Fátima Andrioli, Hadassa Raquel Peixoto Jácome, Paulo Ricardo Jauer, Eliah Fernanda de Maria de São Sabbas Tavares, Marcos Vinicius Dias Silveira, Ângela Machado dos | L47: 5116651 | M47: Apoio a Projetos de Pesquisa em Heliofísica, Ciências Planetárias e Aeronomia | N47: Programa Basico de Geociência | O47: GC | P47: Ciências Exatas e da Terra | Q47: Geofísica | R47: Instituto Nacional de Pesquisas Espaciais | S47: INPE | T47: SP | U47: SE | V47: Brasil | W47: Instituto Nacional de Pesquisas Espaciais | X47: INPE | Y47: SP | Z47: SE | AA47: Brasil | AB47: DCTI | AC47: COCQG | AD47: 26/06/2026 | AE47: 13:56:35 | AF47: 27/06/2026 | AG47: 09:56:08 | AH47: 6 | AI47: 1054560 | AJ47: 128867.24 | AK47: 0 | AL47: 1183427.2 | AM47: Instituto Nacional de Pesquisas Espaciais | AN47: INPE | AO47: SP | AP47: SE | AQ47: Brasil | AR47: 3869820274542343 | AS47: 46202.465 | AT47: PCI2026 | AU47: Chamada CNPq/MCTI/FNDCT Nº 12/2026 - Programa PCI | AV47: Chamada: Chamada CNPq/MCTI/FNDCT Nº 12/2026 - Faixa 3: Projetos de Pesquisa vinculados a | AW47: 12/2026 | AX47: Chamada CNPq/MCTI/FNDCT Nº 12/2026 - Faixa 3: Projetos de Pesquisa vinculados a UPs Grandes (acima de 200 servidores) | AY47: 27/04/2026 | AZ47: 27/06/2026 | BA47: ezequiel.echer@inpe.br | BB47: 402157/2026-5 | BC47: Ezequiel Echer | BD47: Instituto Nacional de Pesquisas Espaciais | BE47: INPE | BF47: =IF(AND(BG47,BI47,BL47,BM47),TRUE,FALSE) -> TRUE | BG47: TRUE | BH47: 2003 | BI47: TRUE | BJ47: Faixa 3 | BK47: Faixa 3 (20 propostas) | BL47: TRUE | BM47: TRUE | BN47: TRUE | BO47: - Instituto Nacional de Pesquisas Espaciais: (Servidor público - Pesquisador) | BP47: =IF(IFERROR(VLOOKUP(A47,[1]Planilha1!$A:$A,1,0),FALSE)=FALSE,FALSE,TRUE) -> TRUE
A48: 402226/2026-7 | B48: APQ | D48: 46204 | E48: 47664 | F48: 61186066253 | G48: Fabiana Alves Demeu | H48: http://lattes.cnpq.br/1807128280652473 | I48: Fabiana Alves Demeu | K48: Fabiana Alves Demeu, Jomel Francisco dos Santos, Uziel Bemvindo | L48: 5116723 | M48: Avaliação de Sistemas de criação de bezerras e novilhas leiteiras em clima tropical úmido com validação de bioacústica para monitoramento comportamental, fisiológico e de bem-estar | N48: PROGRAMA BASICO DE ZOOTECNIA | O48: ZT | P48: Ciências Agrárias | Q48: Produção Animal | R48: Instituto Federal de Educação Ciência e Tecnologia de Rondônia | S48: IFRO | T48: RO | U48: NO | V48: Brasil | W48: Instituto Federal de Educação Ciência e Tecnologia de Rondônia | X48: IFRO | Y48: RO | Z48: NO | AA48: Brasil | AB48: DCTI | AC48: COAGR | AD48: 26/06/2026 | AE48: 23:19:52 | AF48: 27/06/2026 | AG48: 10:00:11 | AH48: 4 | AI48: 748800 | AJ48: 74359.92 | AK48: 0 | AL48: 823159.92 | AM48: Instituto Federal de Educação Ciência e Tecnologia de Rondônia | AN48: IFRO | AO48: RO | AP48: NO | AQ48: Brasil | AR48: 1807128280652473 | AS48: 46202.465 | AT48: PCI2026 | AU48: Chamada CNPq/MCTI/FNDCT Nº 12/2026 - Programa PCI | AV48: Chamada: Chamada CNPq/MCTI/FNDCT Nº 12/2026 - Faixa 3: Projetos de Pesquisa vinculados a | AW48: 12/2026 | AX48: Chamada CNPq/MCTI/FNDCT Nº 12/2026 - Faixa 3: Projetos de Pesquisa vinculados a UPs Grandes (acima de 200 servidores) | AY48: 27/04/2026 | AZ48: 27/06/2026 | BA48: fabiana.demeu@hotmail.com.br | BB48: 402226/2026-7 | BC48: Fabiana Alves Demeu | BD48: Instituto Federal de Educação Ciência e Tecnologia de Rondônia | BE48: IFRO | BF48: =IF(AND(BG48,BI48,BL48,BM48),TRUE,FALSE) -> FALSE | BG48: FALSE | BH48: 2018 | BI48: FALSE | BJ48: Faixa 3 | BK48: Faixa 3 (1 propostas) | BL48: TRUE | BM48: TRUE | BN48: TRUE | BO48: - Instituto Federal de Educação Ciência e Tecnologia de Rondônia: (Servidor público - Professor) | BP48: =IF(IFERROR(VLOOKUP(A48,[1]Planilha1!$A:$A,1,0),FALSE)=FALSE,FALSE,TRUE) -> FALSE
A49: 402059/2026-3 | B49: APQ | D49: 46204 | E49: 47664 | F49: 78209781472 | G49: Fabiana Farias de Lima Guimarães | H49: http://lattes.cnpq.br/8796898263583929 | I49: Fabiana Farias de Lima Guimarães | K49: Fabiana Farias de Lima Guimarães, Suy Ferreira Hwang, Ana Maria Mendonca de Albuquerque Melo, Suelen Cristina de Lima, Leydianne Leite de Siqueira Patriota, Mércia Liane de Oliveira, Filipe Rolim Cordeiro, Erika Flavia Fortunata | L49: 5116550 | M49: Prospecção de Fitoterápicos Radioprotetores: Padronização de protocolos e cooperação multicêntrica por meio da LBDNet | N49: PROGRAMA BASICO DE ENGENHARIA NUCLEAR | O49: EN | P49: Engenharias | Q49: Aplicações de Radioisótopos | R49: Centro Regional de Ciências Nucleares do Nordeste | S49: CRCN/CNEN | T49: PE | U49: NE | V49: Brasil | W49: Centro Regional de Ciências Nucleares do Nordeste | X49: CRCN/CNEN | Y49: PE | Z49: NE | AA49: Brasil | AB49: DCTI | AC49: COBEN | AD49: 26/06/2026 | AE49: 09:34:44 | AF49: 27/06/2026 | AG49: 09:50:14 | AH49: 12 | AI49: 1339975 | AJ49: 148630 | AK49: 0 | AL49: 1488605 | AR49: 8796898263583929 | AS49: 46202.465 | AT49: PCI2026 | AU49: Chamada CNPq/MCTI/FNDCT Nº 12/2026 - Programa PCI | AV49: Chamada: Chamada CNPq/MCTI/FNDCT Nº 12/2026 - Faixa 3: Projetos de Pesquisa vinculados a | AW49: 12/2026 | AX49: Chamada CNPq/MCTI/FNDCT Nº 12/2026 - Faixa 3: Projetos de Pesquisa vinculados a UPs Grandes (acima de 200 servidores) | AY49: 27/04/2026 | AZ49: 27/06/2026 | BA49: fabiana.farias@cnen.gov.br | BB49: 402059/2026-3 | BC49: Fabiana Farias de Lima Guimarães | BD49: Centro Regional de Ciências Nucleares do Nordeste | BE49: CRCN/CNEN | BF49: =IF(AND(BG49,BI49,BL49,BM49),TRUE,FALSE) -> TRUE | BG49: TRUE | BH49: 2002 | BI49: TRUE | BJ49: Faixa 3 | BK49: Faixa 3 (1 propostas) | BL49: TRUE | BM49: TRUE | BN49: TRUE | BO49: - Centro Regional de Ciências Nucleares: (Servidor público - Pesquisador Titular) | BP49: =IF(IFERROR(VLOOKUP(A49,[1]Planilha1!$A:$A,1,0),FALSE)=FALSE,FALSE,TRUE) -> TRUE
A50: 402277/2026-0 | B50: APQ | D50: 46204 | E50: 47664 | F50: 00793102065 | G50: Fábio Baum | H50: http://lattes.cnpq.br/3487620318253385 | I50: Fábio Baum | K50: Fábio Baum, Ediane Karine Scherer Isernhagen, Daniel Augusto Cantane, Jose Ricardo Cezar Salgado | L50: 5116775 | M50: Materiais nanoestruturados para armazenamento de hidrogênio em estado sólido | N50: PROGRAMA BASICO DE QUIMICA | O50: QU | P50: Ciências Exatas e da Terra | Q50: Físico Química Inorgânica | R50: Universidade Federal da Integração Latino-Americana | S50: UNILA | T50: PR | U50: SU | V50: Brasil | W50: Universidade Federal da Integração Latino-Americana | X50: UNILA | Y50: PR | Z50: SU | AA50: Brasil | AB50: DCTI | AC50: COCQG | AD50: 26/06/2026 | AE50: 15:06:57 | AF50: 27/06/2026 | AG50: 10:03:24 | AH50: 7 | AI50: 479040 | AJ50: 68000 | AK50: 0 | AL50: 547040 | AM50: Universidade Federal da Integração Latino-Americana | AN50: UNILA | AO50: PR | AP50: SU | AQ50: Brasil | AR50: 3487620318253385 | AS50: 46202.465 | AT50: PCI2026 | AU50: Chamada CNPq/MCTI/FNDCT Nº 12/2026 - Programa PCI | AV50: Chamada: Chamada CNPq/MCTI/FNDCT Nº 12/2026 - Faixa 3: Projetos de Pesquisa vinculados a | AW50: 12/2026 | AX50: Chamada CNPq/MCTI/FNDCT Nº 12/2026 - Faixa 3: Projetos de Pesquisa vinculados a UPs Grandes (acima de 200 servidores) | AY50: 27/04/2026 | AZ50: 27/06/2026 | BA50: fabio.baum@unila.edu.br | BB50: 402277/2026-0 | BC50: Fábio Baum | BD50: Universidade Federal da Integração Latino-Americana | BE50: UNILA | BF50: =IF(AND(BG50,BI50,BL50,BM50),TRUE,FALSE) -> FALSE | BG50: FALSE | BH50: 2020 | BI50: FALSE | BJ50: Faixa 3 | BK50: Faixa 3 (4 propostas) | BL50: TRUE | BM50: TRUE | BN50: TRUE | BO50: - Universidade Federal da Integração Latino-Americana: (Servidor público - Professor do Magistério Superior) | BP50: =IF(IFERROR(VLOOKUP(A50,[1]Planilha1!$A:$A,1,0),FALSE)=FALSE,FALSE,TRUE) -> FALSE
A51: 401109/2026-7 | B51: APQ | D51: 46204 | E51: 47664 | F51: 73963470682 | G51: Fábio Gelape Faleiro | H51: http://lattes.cnpq.br/9679761162805267 | I51: Fábio Gelape Faleiro | K51: Fábio Gelape Faleiro, Nilton Tadeu Vilela Junqueira, Angelo Aparecido Barbosa Sussel, Ana Maria Costa, Keize Pereira Junqueira, Isaac Leandro de Almeida, Paulo Campos Christo Fernandes, Eudes de Almeida Cardoso, Patricia | L51: 5114688 | M51: Desenvolvimento de cultivares geneticamente superiores de maracujás (Passiflora L.) como alternativas para geração de emprego e renda em diferentes regiões do Brasil | N51: PROGRAMA BASICO DE AGRONOMIA | O51: AG | P51: Ciências Agrárias | Q51: Melhoramento Vegetal | R51: Empresa Brasileira de Pesquisa Agropecuária | S51: EMBRAPA | T51: DF | U51: CO | V51: Brasil | W51: Empresa Brasileira de Pesquisa Agropecuária | X51: EMBRAPA | Y51: DF | Z51: CO | AA51: Brasil | AB51: DCTI | AC51: COAGR | AD51: 26/05/2026 | AE51: 22:21:34 | AF51: 27/05/2026 | AG51: 16:51:28 | AH51: 6 | AI51: 1198080 | AJ51: 100000 | AK51: 0 | AL51: 1298080 | AM51: Empresa Brasileira de Pesquisa Agropecuária | AN51: EMBRAPA | AO51: DF | AP51: CO | AQ51: Brasil | AR51: 9679761162805267 | AS51: 46202.465 | AT51: PCI2026 | AU51: Chamada CNPq/MCTI/FNDCT Nº 12/2026 - Programa PCI | AV51: Chamada: Chamada CNPq/MCTI/FNDCT Nº 12/2026 - Faixa 3: Projetos de Pesquisa vinculados a | AW51: 12/2026 | AX51: Chamada CNPq/MCTI/FNDCT Nº 12/2026 - Faixa 3: Projetos de Pesquisa vinculados a UPs Grandes (acima de 200 servidores) | AY51: 27/04/2026 | AZ51: 27/06/2026 | BA51: fabiog.faleiro@gmail.com | BB51: 401109/2026-7 | BC51: Fábio Gelape Faleiro | BD51: Empresa Brasileira de Pesquisa Agropecuária | BE51: EMBRAPA | BF51: =IF(AND(BG51,BI51,BL51,BM51),TRUE,FALSE) -> FALSE | BG51: FALSE | BH51: 2000 | BI51: FALSE | BJ51: Faixa 3 | BK51: Faixa 3 (1 propostas) | BL51: TRUE | BM51: TRUE | BN51: TRUE | BO51: - Comissão Executiva do Plano da Lavoura Cacaueira Centro de Pesquisas do Cac: (COLABORADOR - Colaborador) - Universidade Federal de Viçosa: (COLABORADOR - colaborador) - Fundação de Amparo à Pesquisa do Estado de Minas Gerais: (OUTRO - Bolsista de Iniciação Científica/Colaborador) - Fundação de Amparo à Pesquisa do Estado de Minas Gerais: (COLABORADOR - Colaborador) - Empresa Brasileira de Pesquisa Agropecuária: (CELETISTA - Pesquisador III) - Empresa Brasileira de Pesquisa Agropecuária: (Servidor público - Membro Eleito do Comitê Técnico Interno) - Empresa Brasileira de Pesquisa Agropecuária: (Servidor público - Chefe Adjunto de Transferência de Tecnologia) - Universidade Católica de Brasília: (COLABORADOR - Orientador Credenciado) - Universidade Estadual de Santa Cruz: (COLABORADOR - Professor convidado / Colaborador) - Universidade de Brasília: (Professor credenciado - Pós - Professor credenciado) - Conselho Nacional de Desenvolvimento Científico e Tecnológico: (COLABORADOR - Colaborador) - Fundação Araucária de Apoio ao Desenvolvimento Científico e Tecnológico: (COLABORADOR - Colaborador) - Sociedade Brasileira de Melhoramento de Plantas: (COLABORADOR - Colaborador) - Sociedade Brasileira de Zootecnia: (COLABORADOR - Colaborador) - Sociedade Brasileira de Fruticultura: (COLABORADOR - Colaborador) - Programa Nacional de Pesquisa e Desenvolvimento do Café: (COLABORADOR - Colaborador) - União Pioneira de Integração Social: (COLABORADOR - Colaborador) - Universidade Federal de Lavras: (COLABORADOR - Colaborador) - Universidade Estadual do Norte Fluminense Darcy Ribeiro: (COLABORADOR - Colaborador) - Fundação de Amparo à Pesquisa do Estado da Bahia: (COLABORADOR - Colaborador) - Universidade Federal de Goiás: (COLABORADOR - Professor Credenciado) - Fundação de Apoio à Pesquisa do Distrito Federal: (COLABORADOR - Colaborador) - Fundação de Amparo à Pesquisa do Espírito Santo: (COLABORADOR - Colaborador) - Associação Brasileira de Recursos Genéticos: (COLABORADOR - Colaborador) - Fundação de Tecnologia do Estado do Acre: (COLABORADOR - Colaborador) - Fundação de Apoio à Pesquisa do Estado da Paraíba: (COLABORADOR - colaborador) - Empresa Brasileira de Pesquisa Agropecuária: (em branco) | BP51: =IF(IFERROR(VLOOKUP(A51,[1]Planilha1!$A:$A,1,0),FALSE)=FALSE,FALSE,TRUE) -> FALSE
A52: 402048/2026-1 | B52: APQ | D52: 46204 | E52: 47664 | F52: 01746963964 | G52: Fabricio Beggiato Baccaro | H52: http://lattes.cnpq.br/2034428391439802 | I52: Fabricio Beggiato Baccaro | K52: Fabricio Beggiato Baccaro, Adriano Costa Quaresma, Jochen Schongart, Clarissa Alves da Rosa, Flávia Regina Capellotto Costa, William Ernest Magnusson, Juliana Schietti de Almeida, Cintia Cornelius Frische, Elizandra Rego | L52: 5116539 | M52: Fortalecimento dos PELDs amazônicos do INPA por meio de ciência aberta, formação de recursos humanos e inovação científica | N52: PROGRAMA BASICO DE ECOLOGIA E LIMNOLOGIA | O52: EL | P52: Ciências Biológicas | Q52: Ecologia de Ecossistemas | R52: Instituto Nacional de Pesquisas da Amazônia | S52: INPA | T52: AM | U52: NO | V52: Brasil | W52: Instituto Nacional de Pesquisas da Amazônia | X52: INPA | Y52: AM | Z52: NO | AA52: Brasil | AB52: DCTI | AC52: COEBI | AD52: 26/06/2026 | AE52: 12:25:20 | AF52: 27/06/2026 | AG52: 09:49:26 | AH52: 8 | AI52: 1047240 | AJ52: 136100 | AK52: 0 | AL52: 1183340 | AM52: Instituto Nacional de Pesquisas da Amazônia | AN52: INPA | AO52: AM | AP52: NO | AQ52: Brasil | AR52: 2034428391439802 | AS52: 46202.465 | AT52: PCI2026 | AU52: Chamada CNPq/MCTI/FNDCT Nº 12/2026 - Programa PCI | AV52: Chamada: Chamada CNPq/MCTI/FNDCT Nº 12/2026 - Faixa 3: Projetos de Pesquisa vinculados a | AW52: 12/2026 | AX52: Chamada CNPq/MCTI/FNDCT Nº 12/2026 - Faixa 3: Projetos de Pesquisa vinculados a UPs Grandes (acima de 200 servidores) | AY52: 27/04/2026 | AZ52: 27/06/2026 | BA52: fabricio.baccaro@inpa.gov.br | BB52: 402048/2026-1 | BC52: Fabricio Beggiato Baccaro | BD52: Instituto Nacional de Pesquisas da Amazônia | BE52: INPA | BF52: =IF(AND(BG52,BI52,BL52,BM52),TRUE,FALSE) -> TRUE | BG52: TRUE | BH52: 2013 | BI52: TRUE | BJ52: Faixa 3 | BK52: Faixa 3 (15 propostas) | BL52: TRUE | BM52: TRUE | BN52: TRUE | BO52: - Instituto Nacional de Pesquisas da Amazônia: (Servidor público - PROFESSOR_TITULAR) - Instituto Nacional de Pesquisas da Amazônia: (Servidor público - Pesquisador) - EMBRAPA Amazônia Oriental: (COLABORADOR - Colaborador) - Universidade Federal do Pará: (em branco) - Lancaster University: (em branco) - George Washington University: (em branco) | BP52: =IF(IFERROR(VLOOKUP(A52,[1]Planilha1!$A:$A,1,0),FALSE)=FALSE,FALSE,TRUE) -> TRUE
A53: 402093/2026-7 | B53: APQ | D53: 46204 | E53: 47664 | F53: 87440660153 | G53: Fernanda de Pinho Werneck | H53: http://lattes.cnpq.br/0507204139787803 | I53: Fernanda de Pinho Werneck | K53: Fernanda de Pinho Werneck, Itanna Oliveira Fernandes, Marcio Luiz de Oliveira, Luiz Antônio Wanderley Peixoto, Mario Eric Cohn Haft, Lúcia Helena Rapp PyDaniel, Gabriel Jorgewich-Cohen, Maria Nazareth Ferreira da Silva, Paulo | L53: 5116585 | M53: Fortalecimento Científico Institucional e Disponibilização de Dados das Coleções Zoológicas do INPA: do campo e acervos às políticas públicas e popularização sobre a biodiversidade amazônica | N53: PROGRAMA BASICO DE ZOOLOGIA E RECURSOS PESQUEIROS DE AGUAS INTERIORES | O53: ZO | P53: Ciências Biológicas | Q53: Zoologia Aplicada | R53: Instituto Nacional de Pesquisas da Amazônia | S53: INPA | T53: AM | U53: NO | V53: Brasil | W53: Instituto Nacional de Pesquisas da Amazônia | X53: INPA | Y53: AM | Z53: NO | AA53: Brasil | AB53: DCTI | AC53: COEBI | AD53: 25/06/2026 | AE53: 18:54:23 | AF53: 27/06/2026 | AG53: 09:52:12 | AH53: 7 | AI53: 1123200 | AJ53: 39840 | AK53: 0 | AL53: 1163040 | AM53: Instituto Nacional de Pesquisas da Amazônia | AN53: INPA | AO53: AM | AP53: NO | AQ53: Brasil | AR53: 0507204139787803 | AS53: 46202.465 | AT53: PCI2026 | AU53: Chamada CNPq/MCTI/FNDCT Nº 12/2026 - Programa PCI | AV53: Chamada: Chamada CNPq/MCTI/FNDCT Nº 12/2026 - Faixa 3: Projetos de Pesquisa vinculados a | AW53: 12/2026 | AX53: Chamada CNPq/MCTI/FNDCT Nº 12/2026 - Faixa 3: Projetos de Pesquisa vinculados a UPs Grandes (acima de 200 servidores) | AY53: 27/04/2026 | AZ53: 27/06/2026 | BA53: fernanda.werneck@inpa.gov.br | BB53: 402093/2026-7 | BC53: Fernanda de Pinho Werneck | BD53: Instituto Nacional de Pesquisas da Amazônia | BE53: INPA | BF53: =IF(AND(BG53,BI53,BL53,BM53),TRUE,FALSE) -> TRUE | BG53: TRUE | BH53: 2012 | BI53: TRUE | BJ53: Faixa 3 | BK53: Faixa 3 (15 propostas) | BL53: TRUE | BM53: TRUE | BN53: TRUE | BO53: - Universidade de Brasília: (COLABORADOR - Pesquisadora colaboradora) - Universidade Federal da Paraíba: (COLABORADOR - Pesquisadora colaboradora) - Universidade Federal do Rio Grande do Norte: (COLABORADOR - Pesquisadora colaboradora) - Instituto Nacional de Pesquisas da Amazônia: (Servidor público - Pesquisadora Titular) - Universidade Federal do Amazonas: (Professor Colaborador - Professor Colaborador) - Instituto Chico Mendes de Conservação da Biodiversidade: (Membro de comitê assessor) - Universidade Federal do Rio Grande do Sul: (COLABORADOR - Colaboradora) - Instituto Chico Mendes de Conservação da Biodiversidade: (COLABORADOR - Comitê Científico do RAN/ICMBio) - Instituto Chico Mendes de Conservação da Biodiversidade: (COLABORADOR - Grupo de Assessoramento Técnico - GAT) - Universidade de São Paulo: (COLABORADOR - Docente colaboradora) - INSTITUTO CHICO MENDES DE CONSERVAÇÃO DA BIODIVERSIDADE: (Membro de comitê assessor) - Ministério da Ciência, Tecnologia e Inovações: (Membro de comitê assessor) - Sociedade Brasileira para o Progresso da Ciência - São Paulo: (Secretaria Regional Amazonas - Secretaria Regional Amazonas) - Instituto Serrapilheira: (Colaboradora - Colaboradora) - Pontifícia Universidade Católica do Rio Grande do Sul: (em branco) | BP53: =IF(IFERROR(VLOOKUP(A53,[1]Planilha1!$A:$A,1,0),FALSE)=FALSE,FALSE,TRUE) -> TRUE
A54: 402195/2026-4 | B54: APQ | D54: 46204 | E54: 47664 | F54: 83955917215 | G54: Fernando da Silva Carvalho Filho | H54: http://lattes.cnpq.br/7987049452090800 | I54: Fernando da Silva Carvalho Filho | K54: Fernando da Silva Carvalho Filho | L54: 5116689 | M54: Revitalização e curadoria da Coleção Entomológica do Museu Paraense Emílio Goeldi | N54: PROGRAMA BASICO DE ZOOLOGIA E RECURSOS PESQUEIROS DE AGUAS INTERIORES | O54: ZO | P54: Ciências Biológicas | Q54: Taxonomia dos Grupos Recentes | R54: Museu Paraense Emílio Goeldi | S54: MPEG | T54: PA | U54: NO | V54: Brasil | W54: Museu Paraense Emílio Goeldi | X54: MPEG | Y54: PA | Z54: NO | AA54: Brasil | AB54: DCTI | AC54: COEBI | AD54: 26/06/2026 | AE54: 16:45:12 | AF54: 27/06/2026 | AG54: 09:58:23 | AH54: 5 | AI54: 585000 | AJ54: 17950 | AK54: 0 | AL54: 602950 | AM54: Museu Paraense Emílio Goeldi | AN54: MPEG | AO54: PA | AP54: NO | AQ54: Brasil | AR54: 7987049452090800 | AS54: 46202.465 | AT54: PCI2026 | AU54: Chamada CNPq/MCTI/FNDCT Nº 12/2026 - Programa PCI | AV54: Chamada: Chamada CNPq/MCTI/FNDCT Nº 12/2026 - Faixa 3: Projetos de Pesquisa vinculados a | AW54: 12/2026 | AX54: Chamada CNPq/MCTI/FNDCT Nº 12/2026 - Faixa 3: Projetos de Pesquisa vinculados a UPs Grandes (acima de 200 servidores) | AY54: 27/04/2026 | AZ54: 27/06/2026 | BA54: fernanbio@yahoo.com.br | BB54: 402195/2026-4 | BC54: Fernando da Silva Carvalho Filho | BD54: Museu Paraense Emílio Goeldi | BE54: MPEG | BF54: =IF(AND(BG54,BI54,BL54,BM54),TRUE,FALSE) -> TRUE | BG54: TRUE | BH54: 2012 | BI54: TRUE | BJ54: Faixa 3 | BK54: Faixa 3 (24 propostas) | BL54: TRUE | BM54: TRUE | BN54: TRUE | BO54: - Museu Paraense Emílio Goeldi: (Servidor público - Pesquisador) - Universidade Federal do Pará: (em branco) | BP54: =IF(IFERROR(VLOOKUP(A54,[1]Planilha1!$A:$A,1,0),FALSE)=FALSE,FALSE,TRUE) -> TRUE
A55: 402213/2026-2 | B55: APQ | D55: 46204 | E55: 47664 | F55: 03968311175 | G55: Fernando Elias da Silva | H55: http://lattes.cnpq.br/7374917289764220 | I55: Fernando Elias da Silva | K55: Fernando Elias da Silva, Bárbara Simões Santos Leal, Lis Fernandes Stegmann, Mário Augusto Gonçalves Jardim, Leandro Valle Ferreira, Nayara Dias Alves Teixeira, Bernard Josiah Barlow, Joice Nunes Ferreira, Carolina da Silva | L55: 5116708 | M55: MONITORA-BIO: MONItoramento e avaliação de disTúrbios compOstos sobRe A Biodiversidade e servIços ecOssistêmicos na Amazônia Oriental | N55: PROGRAMA BASICO DE ECOLOGIA E LIMNOLOGIA | O55: EL | P55: Ciências Biológicas | Q55: Ecologia de Ecossistemas | R55: Museu Paraense Emílio Goeldi | S55: MPEG | T55: PA | U55: NO | V55: Brasil | W55: Museu Paraense Emílio Goeldi | X55: MPEG | Y55: PA | Z55: NO | AA55: Brasil | AB55: DCTI | AC55: COEBI | AD55: 26/06/2026 | AE55: 12:02:19 | AF55: 27/06/2026 | AG55: 09:59:25 | AH55: 14 | AI55: 1009920 | AJ55: 130000 | AK55: 0 | AL55: 1139920 | AM55: Museu Paraense Emílio Goeldi | AN55: MPEG | AO55: PA | AP55: NO | AQ55: Brasil | AR55: 7374917289764220 | AS55: 46202.465 | AT55: PCI2026 | AU55: Chamada CNPq/MCTI/FNDCT Nº 12/2026 - Programa PCI | AV55: Chamada: Chamada CNPq/MCTI/FNDCT Nº 12/2026 - Faixa 3: Projetos de Pesquisa vinculados a | AW55: 12/2026 | AX55: Chamada CNPq/MCTI/FNDCT Nº 12/2026 - Faixa 3: Projetos de Pesquisa vinculados a UPs Grandes (acima de 200 servidores) | AY55: 27/04/2026 | AZ55: 27/06/2026 | BA55: fernandosilva@museu-goeldi.br | BB55: 402213/2026-2 | BC55: Fernando Elias da Silva | BD55: Museu Paraense Emílio Goeldi | BE55: MPEG | BF55: =IF(AND(BG55,BI55,BL55,BM55),TRUE,FALSE) -> TRUE | BG55: TRUE | BH55: 2020 | BI55: TRUE | BJ55: Faixa 3 | BK55: Faixa 3 (24 propostas) | BL55: TRUE | BM55: TRUE | BN55: TRUE | BO55: - Museu Paraense Emílio Goeldi: (Professor permanente - Professor) - Museu Paraense Emílio Goeldi: (Servidor público - Pesquisador) - Universidade Federal de Santa Catarina: (em branco) | BP55: =IF(IFERROR(VLOOKUP(A55,[1]Planilha1!$A:$A,1,0),FALSE)=FALSE,FALSE,TRUE) -> TRUE
A56: 401102/2026-2 | B56: APQ | D56: 46204 | E56: 47664 | F56: 27802245842 | G56: Fernando Luiz Affonso Fonseca | H56: http://lattes.cnpq.br/6772382797320564 | I56: Fernando Luiz Affonso Fonseca | K56: Fernando Luiz Affonso Fonseca, Glaucia Raquel Luciano da Veiga, Beatriz da Costa Aguiar Alves Reis, Sarah Isabel Pinto Monteiro do Nascimento Alves | L56: 5114566 | M56: Programa Translacional de Diagnóstico Avançado e Medicina de Precisão | N56: PROGRAMA BASICO DE MEDICINA | O56: MD | P56: Ciências da Saúde | Q56: Anatomia Patológica e Patologia Clínica | R56: Faculdade de Medicina do ABC | S56: FMABC | T56: SP | U56: SE | V56: Brasil | W56: Faculdade de Medicina do ABC | X56: FMABC | Y56: SP | Z56: SE | AA56: Brasil | AB56: DCTI | AC56: COSAU | AD56: 27/05/2026 | AE56: 12:00:20 | AF56: 27/05/2026 | AG56: 16:46:50 | AH56: 7 | AI56: 1423240 | AJ56: 76000 | AK56: 0 | AL56: 1499240 | AR56: 6772382797320564 | AS56: 46202.465 | AT56: PCI2026 | AU56: Chamada CNPq/MCTI/FNDCT Nº 12/2026 - Programa PCI | AV56: Chamada: Chamada CNPq/MCTI/FNDCT Nº 12/2026 - Faixa 3: Projetos de Pesquisa vinculados a | AW56: 12/2026 | AX56: Chamada CNPq/MCTI/FNDCT Nº 12/2026 - Faixa 3: Projetos de Pesquisa vinculados a UPs Grandes (acima de 200 servidores) | AY56: 27/04/2026 | AZ56: 27/06/2026 | BA56: affonso.fonseca@unifesp.br | BB56: 401102/2026-2 | BC56: Fernando Luiz Affonso Fonseca | BD56: Faculdade de Medicina do ABC | BE56: FMABC | BF56: =IF(AND(BG56,BI56,BL56,BM56),TRUE,FALSE) -> FALSE | BG56: FALSE | BH56: 2005 | BI56: FALSE | BJ56: Faixa 3 | BK56: Faixa 3 (1 propostas) | BL56: TRUE | BM56: TRUE | BN56: TRUE | BO56: - Faculdade de Medicina do ABC: (CELETISTA - PROFESSOR_TITULAR) - Universidade Federal de São Paulo - Diadema: (Servidor público - Professor Adjunto IV) - Fundação de Amparo à Pesquisa do Estado de Minas Gerais: (ADHOC - Consultor ADHOC) - Escola Superior de Tecnologia de Saúde de Coimbra: (PROFESSOR_VISITANTE - Professor e Orientador) - International Society of Oncology and Biomarkers: (Membro Ordinário - Conselheiro) | BP56: =IF(IFERROR(VLOOKUP(A56,[1]Planilha1!$A:$A,1,0),FALSE)=FALSE,FALSE,TRUE) -> FALSE
A57: 402305/2026-4 | B57: APQ | D57: 46204 | E57: 47664 | F57: 43694705287 | G57: Francisca das Chagas do Amaral Souza | H57: http://lattes.cnpq.br/4281093837396621 | I57: Francisca das Chagas do Amaral Souza | K57: Francisca das Chagas do Amaral Souza, Edson Pablo da Silva, Bruna Ribeiro de Lima, Jaime Paiva Lopes Aguiar, Carlos Adam Conte Junior, Jelmir Craveiro De Andrade, Milena Botelho Pereira Soares, Leticia de Alencar Pereira | L57: 5116803 | M57: INOVA-BIOATIVOS INPA: Estruturação Institucional para Validação Tecnológica, Proteção e Transferência de Ativos da Biodiversidade Amazônica | N57: PROGRAMA BASICO DE CIENCIA E TECNOLOGIA DE ALIMENTOS | O57: AL | P57: Ciências Agrárias | Q57: Ciência de Alimentos | R57: Instituto Nacional de Pesquisas da Amazônia | S57: INPA | T57: AM | U57: NO | V57: Brasil | W57: Instituto Nacional de Pesquisas da Amazônia | X57: INPA | Y57: AM | Z57: NO | AA57: Brasil | AB57: DCTI | AC57: COAGR | AD57: 27/06/2026 | AE57: 10:54:06 | AF57: 27/06/2026 | AG57: 10:54:19 | AH57: 7 | AI57: 1272960 | AJ57: 150000 | AK57: 0 | AL57: 1422960 | AM57: Instituto Nacional de Pesquisas da Amazônia | AN57: INPA | AO57: AM | AP57: NO | AQ57: Brasil | AR57: 4281093837396621 | AS57: 46202.465 | AT57: PCI2026 | AU57: Chamada CNPq/MCTI/FNDCT Nº 12/2026 - Programa PCI | AV57: Chamada: Chamada CNPq/MCTI/FNDCT Nº 12/2026 - Faixa 3: Projetos de Pesquisa vinculados a | AW57: 12/2026 | AX57: Chamada CNPq/MCTI/FNDCT Nº 12/2026 - Faixa 3: Projetos de Pesquisa vinculados a UPs Grandes (acima de 200 servidores) | AY57: 27/04/2026 | AZ57: 27/06/2026 | BA57: francisca.souzainpa@gmail.com | BB57: 402305/2026-4 | BC57: Francisca das Chagas do Amaral Souza | BD57: Instituto Nacional de Pesquisas da Amazônia | BE57: INPA | BF57: =IF(AND(BG57,BI57,BL57,BM57),TRUE,FALSE) -> TRUE | BG57: TRUE | BH57: 2006 | BI57: TRUE | BJ57: Faixa 3 | BK57: Faixa 3 (15 propostas) | BL57: TRUE | BM57: TRUE | BN57: TRUE | BO57: - Instituto Nacional de Pesquisas da Amazônia: (Servidor público - Tecnologista Pleno III / Pesquisador) - Instituto Nacional de Pesquisas da Amazônia: (Servidor público - PROFESSOR_TITULAR) - Conselho Nacional de Desenvolvimento Científico e Tecnológico: (Membro de comitê assessor) - Fundação de Amaprao a Pesquisa: (Membro de comitê assessor) | BP57: =IF(IFERROR(VLOOKUP(A57,[1]Planilha1!$A:$A,1,0),FALSE)=FALSE,FALSE,TRUE) -> TRUE
A58: 402227/2026-3 | B58: APQ | D58: 46204 | E58: 47664 | F58: 00568682351 | G58: Francisca das Chagas Sobral Silva | H58: http://lattes.cnpq.br/1429305836290181 | I58: Francisca das Chagas Sobral Silva | K58: Francisca das Chagas Sobral Silva, Eliana Mosse Alhadeff, Ninoska Isabel Bojorge Ramirez, Patrícia Ribeiro Pereira | L58: 5116724 | M58: Desenvolvimento de Nanopartículas de Quitosana Encapsulando Alérgenos Nativos e Quimicamente Modificados de Ácaros da Poeira Doméstica para Imunoterapia Sublingual | N58: PROGRAMA BASICO DE ENGENHARIA QUIMICA | O58: EQ | P58: Engenharias | Q58: Processos Biotecnológicos e Alimentos | R58: Universidade Federal do Rio de Janeiro | S58: UFRJ | T58: RJ | U58: SE | V58: Brasil | W58: Universidade Federal do Rio de Janeiro | X58: UFRJ | Y58: RJ | Z58: SE | AA58: Brasil | AB58: DCTI | AC58: COBEN | AD58: 26/06/2026 | AE58: 15:40:31 | AF58: 27/06/2026 | AG58: 10:00:14 | AH58: 3 | AI58: 202560 | AJ58: 161400 | AK58: 0 | AL58: 363960 | AR58: 1429305836290181 | AS58: 46202.465 | AT58: PCI2026 | AU58: Chamada CNPq/MCTI/FNDCT Nº 12/2026 - Programa PCI | AV58: Chamada: Chamada CNPq/MCTI/FNDCT Nº 12/2026 - Faixa 3: Projetos de Pesquisa vinculados a | AW58: 12/2026 | AX58: Chamada CNPq/MCTI/FNDCT Nº 12/2026 - Faixa 3: Projetos de Pesquisa vinculados a UPs Grandes (acima de 200 servidores) | AY58: 27/04/2026 | AZ58: 27/06/2026 | BA58: kinhasobral@hotmail.com | BB58: 402227/2026-3 | BC58: Francisca das Chagas Sobral Silva | BD58: Universidade Federal do Rio de Janeiro | BE58: UFRJ | BF58: =IF(AND(BG58,BI58,BL58,BM58),TRUE,FALSE) -> FALSE | BG58: FALSE | BH58: 2017 | BI58: FALSE | BJ58: Faixa 3 | BK58: Faixa 3 (6 propostas) | BL58: TRUE | BM58: TRUE | BN58: FALSE | BO58: - Laboratório Extratos Alergênicos LTDA: (COLABORADOR - Pesquisador) - Universidade Federaldo Riode Janeiro: (em branco) | BP58: =IF(IFERROR(VLOOKUP(A58,[1]Planilha1!$A:$A,1,0),FALSE)=FALSE,FALSE,TRUE) -> FALSE
A59: 401884/2026-0 | B59: APQ | D59: 46204 | E59: 47664 | F59: 37185012287 | G59: Francisco Javier Rios | H59: http://lattes.cnpq.br/0122947337651561 | I59: Francisco Javier Rios | K59: Francisco Javier Rios, Monica Elizetti de Freitas, Tatiana Aparecida Fernandes de Lima, Liliani Pacheco Tavares Nazareth, Raquel Maia Mingote, Nilo Henrique Balzani Lopes, Ana Claudia Queiroz Ladeira | L59: 5116319 | M59: Desenvolvimento e implementação de método de análises de Elementos Terras Raras (ETRs), Urânio e Tório por LA-ICPMS em amostras de rochas, regolitos e argilas iônicas da mina de urânio Osamu Utsumi, Poços de Caldas, MG. | N59: Programa Basico de Geociência | O59: GC | P59: Ciências Exatas e da Terra | Q59: Geoquímica | R59: COMISSAO NACIONAL DE ENERGIA NUCLEAR | S59: CNEN | T59: RJ | U59: SE | V59: Brasil | W59: COMISSAO NACIONAL DE ENERGIA NUCLEAR | X59: CNEN | Y59: RJ | Z59: SE | AA59: Brasil | AB59: DCTI | AC59: COCQG | AD59: 23/06/2026 | AE59: 19:23:51 | AF59: 23/06/2026 | AG59: 19:24:00 | AH59: 1 | AI59: 249600 | AJ59: 32020 | AK59: 0 | AL59: 281620 | AM59: COMISSAO NACIONAL DE ENERGIA NUCLEAR | AN59: CNEN | AO59: RJ | AP59: SE | AQ59: Brasil | AR59: 0122947337651561 | AS59: 46202.465 | AT59: PCI2026 | AU59: Chamada CNPq/MCTI/FNDCT Nº 12/2026 - Programa PCI | AV59: Chamada: Chamada CNPq/MCTI/FNDCT Nº 12/2026 - Faixa 3: Projetos de Pesquisa vinculados a | AW59: 12/2026 | AX59: Chamada CNPq/MCTI/FNDCT Nº 12/2026 - Faixa 3: Projetos de Pesquisa vinculados a UPs Grandes (acima de 200 servidores) | AY59: 27/04/2026 | AZ59: 27/06/2026 | BA59: javier@cdtn.br | BB59: 401884/2026-0 | BC59: Francisco Javier Rios | BD59: COMISSAO NACIONAL DE ENERGIA NUCLEAR | BE59: CNEN | BF59: =IF(AND(BG59,BI59,BL59,BM59),TRUE,FALSE) -> TRUE | BG59: TRUE | BH59: 1995 | BI59: TRUE | BJ59: Faixa 3 | BK59: Faixa 3 (32 propostas) | BL59: TRUE | BM59: TRUE | BN59: TRUE | BO59: - COMISSAO NACIONAL DE ENERGIA NUCLEAR: (Servidor público - Pesquisador e Professor) - Comissão Nacional de Energia Nuclear: (Membro de comitê assessor) - Ministério Ciência Tecnologia e Inovações: (Membro de comitê assessor) | BP59: =IF(IFERROR(VLOOKUP(A59,[1]Planilha1!$A:$A,1,0),FALSE)=FALSE,FALSE,TRUE) -> TRUE
A60: 402414/2026-8 | B60: APQ | D60: 46204 | E60: 47664 | F60: 09123666803 | G60: Frederico Antonio Genezini | H60: http://lattes.cnpq.br/2759618347264783 | I60: Frederico Antonio Genezini | K60: Frederico Antonio Genezini, Artur Wilson Carbonari, Mitiko Saiki, Mauricio Moralles, Alexandre Pinho dos Santos Souza, Francine Franzotti da Silva Salvador, Rafael Henrique Lazzari Garcia, Mario Renteria | L60: 5116912 | M60: Corpus de Caracterização Nuclear para Materiais Magnéticos Avançados: Capacidade Técnica e Capital Humano para a Era do RMB - Reator Multipropósito Brasileiro | N60: PROGRAMA BASICO DE FISICA | O60: FA | P60: Ciências Exatas e da Terra | Q60: Métodos Experimentais e Instrumentação para Partículas | R60: COMISSAO NACIONAL DE ENERGIA NUCLEAR | S60: CNEN | T60: RJ | U60: SE | V60: Brasil | W60: COMISSAO NACIONAL DE ENERGIA NUCLEAR | X60: CNEN | Y60: RJ | Z60: SE | AA60: Brasil | AB60: DCTI | AC60: COCEC | AD60: 27/06/2026 | AE60: 23:59:39 | AF60: 27/06/2026 | AG60: 23:59:45 | AH60: 7 | AI60: 511160 | AJ60: 70000 | AK60: 0 | AL60: 581160 | AM60: COMISSAO NACIONAL DE ENERGIA NUCLEAR | AN60: CNEN | AO60: RJ | AP60: SE | AQ60: Brasil | AR60: 2759618347264783 | AS60: 46202.465 | AT60: PCI2026 | AU60: Chamada CNPq/MCTI/FNDCT Nº 12/2026 - Programa PCI | AV60: Chamada: Chamada CNPq/MCTI/FNDCT Nº 12/2026 - Faixa 3: Projetos de Pesquisa vinculados a | AW60: 12/2026 | AX60: Chamada CNPq/MCTI/FNDCT Nº 12/2026 - Faixa 3: Projetos de Pesquisa vinculados a UPs Grandes (acima de 200 servidores) | AY60: 27/04/2026 | AZ60: 27/06/2026 | BA60: fredzini@ipen.br | BB60: 402414/2026-8 | BC60: Frederico Antonio Genezini | BD60: COMISSAO NACIONAL DE ENERGIA NUCLEAR | BE60: CNEN | BF60: =IF(AND(BG60,BI60,BL60,BM60),TRUE,FALSE) -> TRUE | BG60: TRUE | BH60: 2004 | BI60: TRUE | BJ60: Faixa 3 | BK60: Faixa 3 (32 propostas) | BL60: TRUE | BM60: TRUE | BN60: TRUE | BO60: - COMISSAO NACIONAL DE ENERGIA NUCLEAR: (Servidor público - Pesquisador) - FUNDACAO DE APOIO E FOMENTO A INOVACAO TECNOLOGICA A PESQUISA E AO ENSINO: (Servidor público - diretor presidente) - International Atomic Energy Agency: (Servidor público - Membro do Technical working Group de Reatores) | BP60: =IF(IFERROR(VLOOKUP(A60,[1]Planilha1!$A:$A,1,0),FALSE)=FALSE,FALSE,TRUE) -> TRUE
A61: 402170/2026-1 | B61: APQ | D61: 46204 | E61: 47664 | F61: 39601074805 | G61: Gabriel Jorgewich-Cohen | H61: http://lattes.cnpq.br/9103194900446781 | I61: Gabriel Jorgewich-Cohen | K61: Gabriel Jorgewich-Cohen, Vera Maria Ferreira da Silva, Rodrigo de Souza Amaral, Douglas Aviz Bastos, Moysés Mendes de Lima, Jorge Luiz Ramos Lobato, George Henrique Rebêlo, Jose Antonio Alves Gomes | L61: 5116664 | M61: Monitoramento acústico de vertebrados aquáticos na Amazônia: ferramenta de popularização, sustentabilidade, governança e soberania nacional | N61: PROGRAMA BASICO DE MICROBIOLOGIA | O61: MP | P61: Ciências Biológicas | Q61: Biologia Geral | R61: Instituto Nacional de Pesquisas da Amazônia | S61: INPA | T61: AM | U61: NO | V61: Brasil | W61: Instituto Nacional de Pesquisas da Amazônia | X61: INPA | Y61: AM | Z61: NO | AA61: Brasil | AB61: DCTI | AC61: COBIO | AD61: 26/06/2026 | AE61: 13:59:43 | AF61: 27/06/2026 | AG61: 09:56:54 | AH61: 9 | AI61: 1346880 | AJ61: 153120 | AK61: 0 | AL61: 1500000 | AM61: Instituto Nacional de Pesquisas da Amazônia | AN61: INPA | AO61: AM | AP61: NO | AQ61: Brasil | AR61: 9103194900446781 | AS61: 46202.465 | AT61: PCI2026 | AU61: Chamada CNPq/MCTI/FNDCT Nº 12/2026 - Programa PCI | AV61: Chamada: Chamada CNPq/MCTI/FNDCT Nº 12/2026 - Faixa 3: Projetos de Pesquisa vinculados a | AW61: 12/2026 | AX61: Chamada CNPq/MCTI/FNDCT Nº 12/2026 - Faixa 3: Projetos de Pesquisa vinculados a UPs Grandes (acima de 200 servidores) | AY61: 27/04/2026 | AZ61: 27/06/2026 | BA61: gabrieljcohen2@gmail.com | BB61: 402170/2026-1 | BC61: Gabriel Jorgewich-Cohen | BD61: Instituto Nacional de Pesquisas da Amazônia | BE61: INPA | BF61: =IF(AND(BG61,BI61,BL61,BM61),TRUE,FALSE) -> TRUE | BG61: TRUE | BH61: 2023 | BI61: TRUE | BJ61: Faixa 3 | BK61: Faixa 3 (15 propostas) | BL61: TRUE | BM61: TRUE | BN61: TRUE | BO61: - Instituto Nacional de Pesquisas da Amazônia: (Servidor público - Pesquisador adjunto) | BP61: =IF(IFERROR(VLOOKUP(A61,[1]Planilha1!$A:$A,1,0),FALSE)=FALSE,FALSE,TRUE) -> TRUE
A62: 402238/2026-5 | B62: APQ | D62: 46204 | E62: 47664 | F62: 06336511847 | G62: Geilson Loureiro | H62: http://lattes.cnpq.br/7824447045520901 | I62: Geilson Loureiro | K62: Geilson Loureiro, Maurício Ribeiro Baldan, Guilherme Nader Kawassaki, Zulema Abraham, Jose Roberto Cecatto, Cesar Strauss, Francisco Carlos Rocha Fernandes | L62: 5116736 | M62: Autossuficiência Metrológica em Ondas Milimétricas: Desenvolvimento de Colimadores, Absorvedores e Radomes Nacionais para os Setores Aeroespacial, Defesa e Radioastronomia | N62: PROGRAMA BASICO DE ENGENHARIA AEROESPACIAL | O62: EM | P62: Engenharias | Q62: Materiais e Processos para Engenharia Aeronáutica e | R62: Instituto Nacional de Pesquisas Espaciais | S62: INPE | T62: SP | U62: SE | V62: Brasil | W62: Instituto Nacional de Pesquisas Espaciais | X62: INPE | Y62: SP | Z62: SE | AA62: Brasil | AB62: DCTI | AC62: COENG | AD62: 26/06/2026 | AE62: 17:33:54 | AF62: 27/06/2026 | AG62: 10:01:10 | AH62: 6 | AI62: 1038700 | AJ62: 149690 | AK62: 0 | AL62: 1188390 | AM62: Instituto Nacional de Pesquisas Espaciais | AN62: INPE | AO62: SP | AP62: SE | AQ62: Brasil | AR62: 7824447045520901 | AS62: 46202.465 | AT62: PCI2026 | AU62: Chamada CNPq/MCTI/FNDCT Nº 12/2026 - Programa PCI | AV62: Chamada: Chamada CNPq/MCTI/FNDCT Nº 12/2026 - Faixa 3: Projetos de Pesquisa vinculados a | AW62: 12/2026 | AX62: Chamada CNPq/MCTI/FNDCT Nº 12/2026 - Faixa 3: Projetos de Pesquisa vinculados a UPs Grandes (acima de 200 servidores) | AY62: 27/04/2026 | AZ62: 27/06/2026 | BA62: loureiro.geilson@gmail.com | BB62: 402238/2026-5 | BC62: Geilson Loureiro | BD62: Instituto Nacional de Pesquisas Espaciais | BE62: INPE | BF62: =IF(AND(BG62,BI62,BL62,BM62),TRUE,FALSE) -> TRUE | BG62: TRUE | BH62: 1999 | BI62: TRUE | BJ62: Faixa 3 | BK62: Faixa 3 (20 propostas) | BL62: TRUE | BM62: TRUE | BN62: TRUE | BO62: - Instituto Nacional de Pesquisas Espaciais: (Servidor público ou celetista - Tecnologista Senior III) - Instituto Nacional de Pesquisas Espaciais: (SERVIDOR_PUBLICO - PROFESSOR_TITULAR) - Instituto Nacional de Pesquisas Espaciais: (SERVIDOR_PUBLICO - Coord. Geral Infraestrutura e Pesq. Aplicadas) - Fundação de Amparo à Pesquisa do Estado de São Paulo: (Membro de comitê assessor) - International Astronautical Federation: (Membro de comitê assessor) | BP62: =IF(IFERROR(VLOOKUP(A62,[1]Planilha1!$A:$A,1,0),FALSE)=FALSE,FALSE,TRUE) -> TRUE
A63: 402154/2026-6 | B63: APQ | D63: 46204 | E63: 47664 | F63: 67812813215 | G63: Gemilson Soares Pontes | H63: http://lattes.cnpq.br/9081671233815990 | I63: Gemilson Soares Pontes | K63: Gemilson Soares Pontes, Rosemary Aparecida Roque, Felipe Moura Araujo da Silva, Sergio Massayoshi Nunomura, André Correa de Oliveira, Leonardo Brandão Matos, Cecilia Veronica Nunez, Renata Galvão de Azevedo | L63: 5116648 | M63: RIBioAMAZ  Rede Interdisciplinar de Inovação em Bioprospecção de Produtos Naturais Amazônicos para Aplicações Biomédicas e Biotecnológicas | N63: Programa Especial de Biotecnologia e Recursos Genéticos - COBRG | O63: BI | P63: Ciências Biológicas | Q63: Bioprospecção | R63: Instituto Nacional de Pesquisas da Amazônia | S63: INPA | T63: AM | U63: NO | V63: Brasil | W63: Instituto Nacional de Pesquisas da Amazônia | X63: INPA | Y63: AM | Z63: NO | AA63: Brasil | AB63: DCTI | AC63: COBEN | AD63: 26/06/2026 | AE63: 20:24:49 | AF63: 27/06/2026 | AG63: 09:55:57 | AH63: 7 | AI63: 1349400 | AJ63: 150000 | AK63: 0 | AL63: 1499400 | AM63: Instituto Nacional de Pesquisas da Amazônia | AN63: INPA | AO63: AM | AP63: NO | AQ63: Brasil | AR63: 9081671233815990 | AS63: 46202.465 | AT63: PCI2026 | AU63: Chamada CNPq/MCTI/FNDCT Nº 12/2026 - Programa PCI | AV63: Chamada: Chamada CNPq/MCTI/FNDCT Nº 12/2026 - Faixa 3: Projetos de Pesquisa vinculados a | AW63: 12/2026 | AX63: Chamada CNPq/MCTI/FNDCT Nº 12/2026 - Faixa 3: Projetos de Pesquisa vinculados a UPs Grandes (acima de 200 servidores) | AY63: 27/04/2026 | AZ63: 27/06/2026 | BA63: pontesbm1@gmail.com | BB63: 402154/2026-6 | BC63: Gemilson Soares Pontes | BD63: Instituto Nacional de Pesquisas da Amazônia | BE63: INPA | BF63: =IF(AND(BG63,BI63,BL63,BM63),TRUE,FALSE) -> TRUE | BG63: TRUE | BH63: 2012 | BI63: TRUE | BJ63: Faixa 3 | BK63: Faixa 3 (15 propostas) | BL63: TRUE | BM63: TRUE | BN63: TRUE | BO63: - Instituto Nacional de Pesquisas da Amazônia: (Servidor público - Pesquisador Titular II) - Universidade do Estado do Amazonas: (COLABORADOR - Professor do Mestrado em Hematologia) - Universidade Federal do Amazonas: (COLABORADOR - Mestrado e doutorado em Imunologia básica) | BP63: =IF(IFERROR(VLOOKUP(A63,[1]Planilha1!$A:$A,1,0),FALSE)=FALSE,FALSE,TRUE) -> TRUE
A64: 401988/2026-0 | B64: APQ | D64: 46204 | E64: 47664 | F64: 11252974841 | G64: Gilvan Sampaio de Oliveira | H64: http://lattes.cnpq.br/0236607123089481 | I64: Gilvan Sampaio de Oliveira | K64: Gilvan Sampaio de Oliveira, Chou Sin Chan, Daniela Carneiro Rodrigues, Silvio Nilo Figueroa Rivero, Julio Pablo Reyes Fernandez | L64: 5116470 | M64: Pesquisa e Desenvolvimento para a geração e disseminação de projeções climáticas futuras com ênfase em eventos extremos na América do Sul | N64: Programa Basico de Ciências Ambientais | O64: CA | P64: Ciências Exatas e da Terra | Q64: Climatologia | R64: Instituto Nacional de Pesquisas Espaciais | S64: INPE | T64: SP | U64: SE | V64: Brasil | W64: Instituto Nacional de Pesquisas Espaciais | X64: INPE | Y64: SP | Z64: SE | AA64: Brasil | AB64: DCTI | AC64: COCAM | AD64: 25/06/2026 | AE64: 16:40:22 | AF64: 25/06/2026 | AG64: 16:40:29 | AH64: 6 | AI64: 748800 | AJ64: 22000 | AK64: 0 | AL64: 770800 | AR64: 0236607123089481 | AS64: 46202.465 | AT64: PCI2026 | AU64: Chamada CNPq/MCTI/FNDCT Nº 12/2026 - Programa PCI | AV64: Chamada: Chamada CNPq/MCTI/FNDCT Nº 12/2026 - Faixa 3: Projetos de Pesquisa vinculados a | AW64: 12/2026 | AX64: Chamada CNPq/MCTI/FNDCT Nº 12/2026 - Faixa 3: Projetos de Pesquisa vinculados a UPs Grandes (acima de 200 servidores) | AY64: 27/04/2026 | AZ64: 27/06/2026 | BA64: gilvan.sampaio@inpe.br | BB64: 401988/2026-0 | BC64: Gilvan Sampaio de Oliveira | BD64: Instituto Nacional de Pesquisas Espaciais | BE64: INPE | BF64: =IF(AND(BG64,BI64,BL64,BM64),TRUE,FALSE) -> TRUE | BG64: TRUE | BH64: 2008 | BI64: TRUE | BJ64: Faixa 3 | BK64: Faixa 3 (20 propostas) | BL64: TRUE | BM64: TRUE | BN64: FALSE | BO64: - Instituto Nacional de Pesquisas Espaciais: (Pesquisador/Tecnologista Senior) - Comitê Interministerial sobre Mudança do Clima: (Membro de comitê assessor) | BP64: =IF(IFERROR(VLOOKUP(A64,[1]Planilha1!$A:$A,1,0),FALSE)=FALSE,FALSE,TRUE) -> TRUE
A65: 402336/2026-7 | B65: APQ | D65: 46204 | E65: 47664 | F65: 52397491249 | G65: Glenn Harvey Shepard Jr | H65: http://lattes.cnpq.br/6374563794926122 | I65: Glenn Harvey Shepard Jr | K65: Glenn Harvey Shepard Jr, Marlia Regina Coelho-Ferreira, Sue Anne Regina Ferreira da Costa, Tarcízio Macedo, Adenilson Raniery Sarges Pontes, Igor Alves Quadros, Lewis J Daly, Vitória Mendes Alves | L65: 5116834 | M65: A Floresta Sensível: O mundo sensorial indígena em diálogo com conhecimentos científicos no Museu Paraense Emílio Goeldi | N65: PROGRAMA BASICO DE ANTROPOLOGIA | O65: CS | P65: Ciências Humanas | Q65: Etnologia Indígena | R65: Museu Paraense Emílio Goeldi | S65: MPEG | T65: PA | U65: NO | V65: Brasil | W65: Museu Paraense Emílio Goeldi | X65: MPEG | Y65: PA | Z65: NO | AA65: Brasil | AB65: DCTI | AC65: COSAE | AD65: 27/06/2026 | AE65: 12:24:51 | AF65: 27/06/2026 | AG65: 12:24:58 | AH65: 13 | AI65: 590030 | AJ65: 59000 | AK65: 0 | AL65: 649030 | AM65: Museu Paraense Emílio Goeldi | AN65: MPEG | AO65: PA | AP65: NO | AQ65: Brasil | AR65: 6374563794926122 | AS65: 46202.465 | AT65: PCI2026 | AU65: Chamada CNPq/MCTI/FNDCT Nº 12/2026 - Programa PCI | AV65: Chamada: Chamada CNPq/MCTI/FNDCT Nº 12/2026 - Faixa 3: Projetos de Pesquisa vinculados a | AW65: 12/2026 | AX65: Chamada CNPq/MCTI/FNDCT Nº 12/2026 - Faixa 3: Projetos de Pesquisa vinculados a UPs Grandes (acima de 200 servidores) | AY65: 27/04/2026 | AZ65: 27/06/2026 | BA65: gshepardjr@gmail.com | BB65: 402336/2026-7 | BC65: Glenn Harvey Shepard Jr | BD65: Museu Paraense Emílio Goeldi | BE65: MPEG | BF65: =IF(AND(BG65,BI65,BL65,BM65),TRUE,FALSE) -> TRUE | BG65: TRUE | BH65: 1999 | BI65: TRUE | BJ65: Faixa 3 | BK65: Faixa 3 (24 propostas) | BL65: TRUE | BM65: TRUE | BN65: TRUE | BO65: - Instituto Nacional de Pesquisas da Amazônia: (Professor Credenciado - Professor Credenciado, Coordenação deEcologia) - Museu Paraense Emílio Goeldi: (Servidor público - Dept. Antropologia, Pesquisador Titular) - Museu Paraense Emílio Goeldi: (PROFESSOR_VISITANTE - Profesor permanente, PPGDS) - Middle Tennessee State University: (COLABORADOR - Pesquisador colaborador) - University of Turku: (em branco) - Universidade Federal do Amazonas: (PROFESSOR_VISITANTE - Professor permanente) - American Museum of Natural History: (PROFESSOR_VISITANTE - Professor visitante, Dept Antropologia) - Universidad Peruana Cayetano Heredia - UPCH: (em branco) | BP65: =IF(IFERROR(VLOOKUP(A65,[1]Planilha1!$A:$A,1,0),FALSE)=FALSE,FALSE,TRUE) -> TRUE
A66: 401094/2026-0 | B66: APQ | D66: 46204 | E66: 47664 | F66: 10990816613 | G66: Gustavo Alves de Melo | H66: http://lattes.cnpq.br/8077905004771803 | I66: Gustavo Alves de Melo | K66: Gustavo Alves de Melo, Maria Gabriela Mendonça Peixoto, Maria Cristina Angélico de Mendonça, André Luiz Marques Serrano | L66: 5112740 | M66: Desenvolvimento e validação da plataforma AgroCEP para monitoramento agroclimático e controle estatístico aplicado à eficiência e resiliência de sistemas produtivos frente às mudanças climáticas | N66: PROGRAMA BASICO DE ENGENHARIA DE PRODUCAO | O66: PE | P66: Engenharias | Q66: Suprimentos | R66: Universidade Federal de Viçosa | S66: UFV | T66: MG | U66: SE | V66: Brasil | W66: Universidade Federal de Viçosa | X66: UFV | Y66: MG | Z66: SE | AA66: Brasil | AB66: DCTI | AC66: COENG | AD66: 26/05/2026 | AE66: 22:09:24 | AF66: 26/05/2026 | AG66: 22:09:31 | AH66: 6 | AI66: 1370980 | AJ66: 129020 | AK66: 0 | AL66: 1500000 | AM66: Universidade Federal de Viçosa | AN66: UFV | AO66: MG | AP66: SE | AQ66: Brasil | AR66: 8077905004771803 | AS66: 46202.465 | AT66: PCI2026 | AU66: Chamada CNPq/MCTI/FNDCT Nº 12/2026 - Programa PCI | AV66: Chamada: Chamada CNPq/MCTI/FNDCT Nº 12/2026 - Faixa 3: Projetos de Pesquisa vinculados a | AW66: 12/2026 | AX66: Chamada CNPq/MCTI/FNDCT Nº 12/2026 - Faixa 3: Projetos de Pesquisa vinculados a UPs Grandes (acima de 200 servidores) | AY66: 27/04/2026 | AZ66: 27/06/2026 | BA66: gustavo.a.melo@ufv.br | BB66: 401094/2026-0 | BC66: Gustavo Alves de Melo | BD66: Universidade Federal de Viçosa | BE66: UFV | BF66: =IF(AND(BG66,BI66,BL66,BM66),TRUE,FALSE) -> FALSE | BG66: FALSE | BH66: 2024 | BI66: FALSE | BJ66: Faixa 3 | BK66: Faixa 3 (1 propostas) | BL66: TRUE | BM66: TRUE | BN66: TRUE | BO66: - Universidade Federal de Viçosa: (OUTRO - Pesquisador) - Universidade Federal de Viçosa: (Servidor público - Professor Adjunto 1) - Universidade Tecnológica Federal do Paraná: (Membro de grupo de pesquisa - Pesquisador) - Universidade do Sul de Santa Catarina: (Membro de grupo de pesquisa - Pesquisador) | BP66: =IF(IFERROR(VLOOKUP(A66,[1]Planilha1!$A:$A,1,0),FALSE)=FALSE,FALSE,TRUE) -> FALSE
A67: 401999/2026-2 | B67: APQ | D67: 46204 | E67: 47664 | F67: 29255363875 | G67: Helena Pinto Lima | H67: http://lattes.cnpq.br/4138407289238061 | I67: Helena Pinto Lima | K67: Helena Pinto Lima, Claudia Leonor López Garcés, Caroline Barros Soares, Brenda Bandeira de Azevedo, Larissa Ye'padiho Mota Duarte, Marlia Regina Coelho-Ferreira, Diana Cruz Rodrigues, Artur Garcia Gonçalves, yuri Kuikuro | L67: 5116485 | M67: Indigenizando o Museu Goeldi: acervos e territórios amazônicos em diálogo | N67: PROGRAMA BASICO DE ARQUEOLOGIA | O67: CS | P67: Ciências Humanas | Q67: Teoria e Método em Arqueologia | R67: Museu Paraense Emílio Goeldi | S67: MPEG | T67: PA | U67: NO | V67: Brasil | W67: Museu Paraense Emílio Goeldi | X67: MPEG | Y67: PA | Z67: NO | AA67: Brasil | AB67: DCTI | AC67: COSAE | AD67: 25/06/2026 | AE67: 18:19:47 | AF67: 25/06/2026 | AG67: 18:19:55 | AH67: 22 | AI67: 1039450 | AJ67: 148715 | AK67: 0 | AL67: 1188165 | AM67: Museu Paraense Emílio Goeldi | AN67: MPEG | AO67: PA | AP67: NO | AQ67: Brasil | AR67: 4138407289238061 | AS67: 46202.465 | AT67: PCI2026 | AU67: Chamada CNPq/MCTI/FNDCT Nº 12/2026 - Programa PCI | AV67: Chamada: Chamada CNPq/MCTI/FNDCT Nº 12/2026 - Faixa 3: Projetos de Pesquisa vinculados a | AW67: 12/2026 | AX67: Chamada CNPq/MCTI/FNDCT Nº 12/2026 - Faixa 3: Projetos de Pesquisa vinculados a UPs Grandes (acima de 200 servidores) | AY67: 27/04/2026 | AZ67: 27/06/2026 | BA67: lelenalima@gmail.com | BB67: 401999/2026-2 | BC67: Helena Pinto Lima | BD67: Museu Paraense Emílio Goeldi | BE67: MPEG | BF67: =IF(AND(BG67,BI67,BL67,BM67),TRUE,FALSE) -> TRUE | BG67: TRUE | BH67: 2008 | BI67: TRUE | BJ67: Faixa 3 | BK67: Faixa 3 (24 propostas) | BL67: TRUE | BM67: TRUE | BN67: TRUE | BO67: - Museu Paraense Emílio Goeldi: (Servidor público - Pesquisadora Titular) - Museu Paraense Emílio Goeldi: (Servidor público - Pesquisadora Adjunta/Associada) - Museu Paraense Emílio Goeldi: (Servidor público - Curadora da coleção arqueológica) - Museu Paraense Emílio Goeldi: (Servidor público - Docente permanente) - Museu Amazônico da Universidade Federal do Amazononas: (COLABORADOR - Professor - membro de colegiado) - Museu Amazônico da Universidade Federal do Amazononas: (COLABORADOR - Pesquisador colaborador) - Museu Amazônico da Universidade Federal do Amazononas: (COLABORADOR - Pesquisador associado) - Associação Indígena Kuikuro do Alto Xingu: (em branco) - Universidade Federal do Oeste do Pará: (em branco) - Universidade Federal do Pará: (em branco) - Conselho Nacional de Desenvolvimento Científico e Tecnológico: (Membro de comitê assessor) - Universitat Autònoma de Barcelona - UAB: (em branco) | BP67: =IF(IFERROR(VLOOKUP(A67,[1]Planilha1!$A:$A,1,0),FALSE)=FALSE,FALSE,TRUE) -> TRUE
A68: 402328/2026-4 | B68: APQ | D68: 46204 | E68: 47664 | F68: 50860623220 | G68: Hendrikus Gerardus Antonius van der Voort | H68: http://lattes.cnpq.br/8723849507527234 | I68: Hendrikus Gerardus Antonius van der Voort | K68: Hendrikus Gerardus Antonius van der Voort, Igor Morais Mariano Rodrigues, Lucia Hussak van Velthem, Claudia Leonor López Garcés, Suzana Primo dos Santos, Fabio Roberto Filpo Jacob, Camila Pereira Jácome, Jaime Xamen | L68: 5116826 | M68: Abertura de acervos culturais: acesso controlado online ao patrimônio cultural e linguístico indígena do MPEG | N68: PROGRAMA BASICO DE LINGUISTICA | O68: LL | P68: Lingüística, Letras e Artes | Q68: Teoria e Análise Lingüística | R68: Museu Paraense Emílio Goeldi | S68: MPEG | T68: PA | U68: NO | V68: Brasil | W68: Museu Paraense Emílio Goeldi | X68: MPEG | Y68: PA | Z68: NO | AA68: Brasil | AB68: DCTI | AC68: COCHS | AD68: 27/06/2026 | AE68: 12:03:26 | AF68: 27/06/2026 | AG68: 12:03:38 | AH68: 7 | AI68: 1073280 | AJ68: 104736 | AK68: 0 | AL68: 1178016 | AM68: Museu Paraense Emílio Goeldi | AN68: MPEG | AO68: PA | AP68: NO | AQ68: Brasil | AR68: 8723849507527234 | AS68: 46202.465 | AT68: PCI2026 | AU68: Chamada CNPq/MCTI/FNDCT Nº 12/2026 - Programa PCI | AV68: Chamada: Chamada CNPq/MCTI/FNDCT Nº 12/2026 - Faixa 3: Projetos de Pesquisa vinculados a | AW68: 12/2026 | AX68: Chamada CNPq/MCTI/FNDCT Nº 12/2026 - Faixa 3: Projetos de Pesquisa vinculados a UPs Grandes (acima de 200 servidores) | AY68: 27/04/2026 | AZ68: 27/06/2026 | BA68: hvoort@museu-goeldi.br | BB68: 402328/2026-4 | BC68: Hendrikus Gerardus Antonius van der Voort | BD68: Museu Paraense Emílio Goeldi | BE68: MPEG | BF68: =IF(AND(BG68,BI68,BL68,BM68),TRUE,FALSE) -> TRUE | BG68: TRUE | BH68: 2000 | BI68: TRUE | BJ68: Faixa 3 | BK68: Faixa 3 (24 propostas) | BL68: TRUE | BM68: TRUE | BN68: TRUE | BO68: - Museu Paraense Emílio Goeldi: (Servidor público - pesquisador titular) | BP68: =IF(IFERROR(VLOOKUP(A68,[1]Planilha1!$A:$A,1,0),FALSE)=FALSE,FALSE,TRUE) -> TRUE
A69: 402055/2026-8 | B69: APQ | D69: 46204 | E69: 47664 | F69: 09054537515 | G69: Herman Augusto Lepikson | H69: http://lattes.cnpq.br/1115148358376830 | I69: Herman Augusto Lepikson | K69: Herman Augusto Lepikson, Luis Carlos Moreno Ledezma, Anderson Farias de Souza Lima, Frederico Garcia de Oliveira, Pedro Xavier Alcantara, Alexandro Quirino da Silva | L69: 5116546 | M69: Desenvolvimento de um Robô Reconfigurável para Missões de Inspeção, Mapeamento e Manutenção de Estruturas Suspensas e em Áreas de Difícil Acesso | N69: PROGRAMA BASICO DE ENGENHARIA MECANICA | O69: EM | P69: Engenharias | Q69: Métodos de Síntese e Otimização Aplicados ao Projeto | R69: Universidade Federal da Bahia | S69: UFBA | T69: BA | U69: NE | V69: Brasil | W69: Universidade Federal da Bahia | X69: UFBA | Y69: BA | Z69: NE | AA69: Brasil | AB69: DCTI | AC69: COENG | AD69: 26/06/2026 | AE69: 18:40:19 | AF69: 27/06/2026 | AG69: 09:49:49 | AH69: 18 | AI69: 1320930 | AJ69: 160583 | AK69: 0 | AL69: 1481513 | AM69: SENAI - Departamento Regional da Bahia | AN69: SENAI/DR/BA | AO69: BA | AP69: NE | AQ69: Brasil | AR69: 1115148358376830 | AS69: 46202.465 | AT69: PCI2026 | AU69: Chamada CNPq/MCTI/FNDCT Nº 12/2026 - Programa PCI | AV69: Chamada: Chamada CNPq/MCTI/FNDCT Nº 12/2026 - Faixa 3: Projetos de Pesquisa vinculados a | AW69: 12/2026 | AX69: Chamada CNPq/MCTI/FNDCT Nº 12/2026 - Faixa 3: Projetos de Pesquisa vinculados a UPs Grandes (acima de 200 servidores) | AY69: 27/04/2026 | AZ69: 27/06/2026 | BA69: hlepikson@gmail.com | BB69: 402055/2026-8 | BC69: Herman Augusto Lepikson | BD69: Universidade Federal da Bahia | BE69: UFBA | BF69: =IF(AND(BG69,BI69,BL69,BM69),TRUE,FALSE) -> FALSE | BG69: FALSE | BH69: 1998 | BI69: FALSE | BJ69: Faixa 3 | BK69: Faixa 3 (1 propostas) | BL69: TRUE | BM69: TRUE | BN69: FALSE | BO69: - Universidade Federal da Bahia: (COLABORADOR - Professor Permanente) - Conselho Nacional de Saúde, Comissão Nacional de Ética em Pesquisa: (Membro de comitê assessor) - Conselho Nacional de Saúde, Comissão Nacional de Ética em Pesquisa: (Membro de comitê assessor) - Conselho Nacional de Saúde, Comissão Nacional de Ética em Pesquisa: (Membro de comitê assessor) - Conselho Nacional de Saúde, Comissão Nacional de Ética em Pesquisa: (Membro de comitê assessor) - SENAI - Departamento Regional da Bahia: (CELETISTA - PROFESSOR_TITULAR) - SENAI - Departamento Regional da Bahia: (CELETISTA - Pesquisador Líder de ISIs) - UNIVERSIDADE SENAI CIMATEC: (em branco) | BP69: =IF(IFERROR(VLOOKUP(A69,[1]Planilha1!$A:$A,1,0),FALSE)=FALSE,FALSE,TRUE) -> FALSE
A70: 402338/2026-0 | B70: APQ | D70: 46204 | E70: 47664 | F70: 08339536648 | G70: Izabela Fonseca Aleixo | H70: http://lattes.cnpq.br/4484010814909501 | I70: Izabela Fonseca Aleixo | K70: Izabela Fonseca Aleixo, Caroline Schmaedeck Lara, Paulo de Tarso Barbosa Sampaio, Gil Vieira, Raquel da Silva Medeiros, Rayssa Gomes Vasconcelos, Thiago da Silva Nascimento, Flávio Mauro Souza Bruno, Gloria Cecilia Macia | L70: 5116836 | M70: Plataforma integrada de monitoramento fenológico e vulnerabilidade climática na Amazônia Central: soluções tecnológicas aplicadas à bioeconomia amazônica | N70: PROGRAMA BASICO DE RECURSOS FLORESTAIS E ENGENHARIA FLORESTAL | O70: RF | P70: Ciências Agrárias | Q70: Silvicultura | R70: Instituto Nacional de Pesquisas da Amazônia | S70: INPA | T70: AM | U70: NO | V70: Brasil | W70: Instituto Nacional de Pesquisas da Amazônia | X70: INPA | Y70: AM | Z70: NO | AA70: Brasil | AB70: DCTI | AC70: COAGR | AD70: 27/06/2026 | AE70: 12:42:58 | AF70: 27/06/2026 | AG70: 12:43:09 | AH70: 6 | AI70: 1048320 | AJ70: 131000 | AK70: 0 | AL70: 1179320 | AM70: Instituto Nacional de Pesquisas da Amazônia | AN70: INPA | AO70: AM | AP70: NO | AQ70: Brasil | AR70: 4484010814909501 | AS70: 46202.465 | AT70: PCI2026 | AU70: Chamada CNPq/MCTI/FNDCT Nº 12/2026 - Programa PCI | AV70: Chamada: Chamada CNPq/MCTI/FNDCT Nº 12/2026 - Faixa 3: Projetos de Pesquisa vinculados a | AW70: 12/2026 | AX70: Chamada CNPq/MCTI/FNDCT Nº 12/2026 - Faixa 3: Projetos de Pesquisa vinculados a UPs Grandes (acima de 200 servidores) | AY70: 27/04/2026 | AZ70: 27/06/2026 | BA70: izabela.faleixo@gmail.com | BB70: 402338/2026-0 | BC70: Izabela Fonseca Aleixo | BD70: Instituto Nacional de Pesquisas da Amazônia | BE70: INPA | BF70: =IF(AND(BG70,BI70,BL70,BM70),TRUE,FALSE) -> TRUE | BG70: TRUE | BH70: 2019 | BI70: TRUE | BJ70: Faixa 3 | BK70: Faixa 3 (15 propostas) | BL70: TRUE | BM70: TRUE | BN70: TRUE | BO70: - Instituto Nacional de Pesquisas da Amazônia: (Servidor público - PROFESSOR_TITULAR) | BP70: =IF(IFERROR(VLOOKUP(A70,[1]Planilha1!$A:$A,1,0),FALSE)=FALSE,FALSE,TRUE) -> TRUE
A71: 400941/2026-0 | B71: APQ | D71: 46204 | E71: 47664 | F71: 59560762400 | G71: Jair Max Furtunato Maia | H71: http://lattes.cnpq.br/2756083344723640 | I71: Jair Max Furtunato Maia | K71: Jair Max Furtunato Maia, Marta Regina Silva Pereira, Caroliny Almeida Coelho, José Do Rosário Costa Junior | L71: 5105694 | M71: Biomonitoramento de Metais Pesados por Briófitas no Médio Rio Madeira: Fortalecimento Institucional na Amazônia Ocidental | N71: PROGRAMA BASICO DE ECOLOGIA E LIMNOLOGIA | O71: EL | P71: Ciências Biológicas | Q71: Ecologia de Ecossistemas | R71: Universidade do Estado do Amazonas | S71: UEA | T71: AM | U71: NO | V71: Brasil | W71: Universidade do Estado do Amazonas | X71: UEA | Y71: AM | Z71: NO | AA71: Brasil | AB71: DCTI | AC71: COEBI | AD71: 05/05/2026 | AE71: 21:58:29 | AF71: 05/05/2026 | AG71: 21:58:34 | AH71: 3 | AI71: 549120 | AJ71: 149600 | AK71: 0 | AL71: 698720 | AM71: Universidade do Estado do Amazonas | AN71: UEA | AO71: AM | AP71: NO | AQ71: Brasil | AR71: 2756083344723640 | AS71: 46202.465 | AT71: PCI2026 | AU71: Chamada CNPq/MCTI/FNDCT Nº 12/2026 - Programa PCI | AV71: Chamada: Chamada CNPq/MCTI/FNDCT Nº 12/2026 - Faixa 3: Projetos de Pesquisa vinculados a | AW71: 12/2026 | AX71: Chamada CNPq/MCTI/FNDCT Nº 12/2026 - Faixa 3: Projetos de Pesquisa vinculados a UPs Grandes (acima de 200 servidores) | AY71: 27/04/2026 | AZ71: 27/06/2026 | BA71: jmaia@uea.edu.br | BB71: 400941/2026-0 | BC71: Jair Max Furtunato Maia | BD71: Universidade do Estado do Amazonas | BE71: UEA | BF71: =IF(AND(BG71,BI71,BL71,BM71),TRUE,FALSE) -> FALSE | BG71: FALSE | BH71: 2003 | BI71: FALSE | BJ71: Faixa 3 | BK71: Faixa 3 (1 propostas) | BL71: TRUE | BM71: TRUE | BN71: TRUE | BO71: - Universidade do Estado do Amazonas: (Servidor público - Professor Associado) - Fundação de Amparo a Pesquisa do Estado do Amazonas: (Membro de comitê assessor) | BP71: =IF(IFERROR(VLOOKUP(A71,[1]Planilha1!$A:$A,1,0),FALSE)=FALSE,FALSE,TRUE) -> FALSE
A72: 402222/2026-1 | B72: APQ | D72: 46204 | E72: 47664 | F72: 54223555634 | G72: Jefferson José Vilela | H72: http://lattes.cnpq.br/0948970682519019 | I72: Jefferson José Vilela | K72: Jefferson José Vilela, Amir Zacarias Mesquita, Sergio Almeida Cunha Filgueiras, Pablo Andrade Grossi, Daniel de Almeida Magalhães Campolina, Hugo Moura Dalle, Luiz Cláudio Andrade Souza, Patrícia Mendes de Azevedo, | L72: 5116718 | M72: Gestão de Envelhecimento e Planejamento do Descomissionamento de Instalações Nucleares do CDTN/CNEN | N72: PROGRAMA BASICO DE ENGENHARIA NUCLEAR | O72: EN | P72: Engenharias | Q72: Rejeitos de Combustível Nuclear | R72: COMISSAO NACIONAL DE ENERGIA NUCLEAR | S72: CNEN | T72: RJ | U72: SE | V72: Brasil | W72: COMISSAO NACIONAL DE ENERGIA NUCLEAR | X72: CNEN | Y72: RJ | Z72: SE | AA72: Brasil | AB72: DCTI | AC72: COBEN | AD72: 26/06/2026 | AE72: 19:36:40 | AF72: 27/06/2026 | AG72: 09:59:58 | AH72: 5 | AI72: 960960 | AJ72: 96000 | AK72: 0 | AL72: 1056960 | AM72: COMISSAO NACIONAL DE ENERGIA NUCLEAR | AN72: CNEN | AO72: RJ | AP72: SE | AQ72: Brasil | AR72: 0948970682519019 | AS72: 46202.465 | AT72: PCI2026 | AU72: Chamada CNPq/MCTI/FNDCT Nº 12/2026 - Programa PCI | AV72: Chamada: Chamada CNPq/MCTI/FNDCT Nº 12/2026 - Faixa 3: Projetos de Pesquisa vinculados a | AW72: 12/2026 | AX72: Chamada CNPq/MCTI/FNDCT Nº 12/2026 - Faixa 3: Projetos de Pesquisa vinculados a UPs Grandes (acima de 200 servidores) | AY72: 27/04/2026 | AZ72: 27/06/2026 | BA72: jjv@cdtn.br | BB72: 402222/2026-1 | BC72: Jefferson José Vilela | BD72: COMISSAO NACIONAL DE ENERGIA NUCLEAR | BE72: CNEN | BF72: =IF(AND(BG72,BI72,BL72,BM72),TRUE,FALSE) -> TRUE | BG72: TRUE | BH72: 1999 | BI72: TRUE | BJ72: Faixa 3 | BK72: Faixa 3 (32 propostas) | BL72: TRUE | BM72: TRUE | BN72: TRUE | BO72: - COMISSAO NACIONAL DE ENERGIA NUCLEAR: (Servidor público - Pesquisador Titular III) | BP72: =IF(IFERROR(VLOOKUP(A72,[1]Planilha1!$A:$A,1,0),FALSE)=FALSE,FALSE,TRUE) -> TRUE
A73: 401040/2026-7 | B73: APQ | D73: 46204 | E73: 47664 | F73: 05074263808 | G73: Jesualdo Luiz Rossi | H73: http://lattes.cnpq.br/0763948174052925 | I73: Jesualdo Luiz Rossi | K73: Jesualdo Luiz Rossi, Marina Fuser Pillis, Cristiano Stefano Mucsi, Renato Altobelli Antunes, Luis Gallego Martinez, Larissa Otubo, Marcos Tadeu D Azeredo Orlando, Xabier Turrillas, Camila Boldrini Nascimento, Carlos Augusto | L73: 5111274 | M73: Ligas de alta entropia, obtenção, processamento, otimização e inovação com uso intensivo de metais especiais | N73: PROGRAMA BASICO DE ENGENHARIA DE MATERIAIS E METALURGIA | O73: MM | P73: Engenharias | Q73: Estrutura dos Metais e Ligas | R73: Instituto de Pesquisas Energéticas e Nucleares | S73: IPEN/CNEN | T73: SP | U73: SE | V73: Brasil | W73: Instituto de Pesquisas Energéticas e Nucleares | X73: IPEN/CNEN | Y73: SP | Z73: SE | AA73: Brasil | AB73: DCTI | AC73: COBEN | AD73: 23/05/2026 | AE73: 22:54:13 | AF73: 23/05/2026 | AG73: 22:54:20 | AH73: 16 | AI73: 1247900 | AJ73: 147817.52 | AK73: 0 | AL73: 1395717.5 | AM73: COMISSAO NACIONAL DE ENERGIA NUCLEAR | AN73: CNEN | AO73: RJ | AP73: SE | AQ73: Brasil | AR73: 0763948174052925 | AS73: 46202.465 | AT73: PCI2026 | AU73: Chamada CNPq/MCTI/FNDCT Nº 12/2026 - Programa PCI | AV73: Chamada: Chamada CNPq/MCTI/FNDCT Nº 12/2026 - Faixa 3: Projetos de Pesquisa vinculados a | AW73: 12/2026 | AX73: Chamada CNPq/MCTI/FNDCT Nº 12/2026 - Faixa 3: Projetos de Pesquisa vinculados a UPs Grandes (acima de 200 servidores) | AY73: 27/04/2026 | AZ73: 27/06/2026 | BA73: jelrossi@gmail.com | BB73: 401040/2026-7 | BC73: Jesualdo Luiz Rossi | BD73: Instituto de Pesquisas Energéticas e Nucleares | BE73: IPEN/CNEN | BF73: =IF(AND(BG73,BI73,BL73,BM73),TRUE,FALSE) -> TRUE | BG73: TRUE | BH73: 1991 | BI73: TRUE | BJ73: Faixa 3 | BK73: Faixa 3 (6 propostas) | BL73: TRUE | BM73: TRUE | BN73: TRUE | BO73: - Universidade de São Paulo: (OUTRO - PROFESSOR_TITULAR) - COMISSAO NACIONAL DE ENERGIA NUCLEAR: (Servidor público - PESQUISADOR TITULAR III) - COMISSAO NACIONAL DE ENERGIA NUCLEAR: (Servidor público - Gerente de Centro) - Instituto de Pesqisas Energéticas e Nucleares: (Servidor público - Pesquisador) | BP73: =IF(IFERROR(VLOOKUP(A73,[1]Planilha1!$A:$A,1,0),FALSE)=FALSE,FALSE,TRUE) -> TRUE
A74: 402037/2026-0 | B74: APQ | D74: 46204 | E74: 47664 | F74: 03001867540 | G74: Jhielson Montino Pimentel | H74: http://lattes.cnpq.br/9924232256219620 | I74: Jhielson Montino Pimentel | K74: Jhielson Montino Pimentel, Ivan João de Queiroz Filho, Herman Augusto Lepikson, Daniel Oliveira de Almeida, Álvaro Souza de Araújo, Carlos Eduardo Conceicao Santos de Almeida, Rodrigo Silveira de Santiago, João Pedro | L74: 5116528 | M74: Desenvolvimento de ferramenta robótica teleoperada para prevenção à formação de biofilme em embarcações | N74: PROGRAMA BASICO DE ENGENHARIA ELETRICA | O74: EE | P74: Engenharias | Q74: Robótica e mecatrônica | R74: UNIVERSIDADE SENAI CIMATEC | S74: CIMATEC | T74: BA | U74: NE | V74: Brasil | W74: UNIVERSIDADE SENAI CIMATEC | X74: CIMATEC | Y74: BA | Z74: NE | AA74: Brasil | AB74: DCTI | AC74: COENG | AD74: 26/06/2026 | AE74: 17:17:44 | AF74: 27/06/2026 | AG74: 09:48:46 | AH74: 25 | AI74: 1299810 | AJ74: 144400 | AK74: 0 | AL74: 1444210 | AR74: 9924232256219620 | AS74: 46202.465 | AT74: PCI2026 | AU74: Chamada CNPq/MCTI/FNDCT Nº 12/2026 - Programa PCI | AV74: Chamada: Chamada CNPq/MCTI/FNDCT Nº 12/2026 - Faixa 3: Projetos de Pesquisa vinculados a | AW74: 12/2026 | AX74: Chamada CNPq/MCTI/FNDCT Nº 12/2026 - Faixa 3: Projetos de Pesquisa vinculados a UPs Grandes (acima de 200 servidores) | AY74: 27/04/2026 | AZ74: 27/06/2026 | BA74: jhielsonm@fieb.org.br | BB74: 402037/2026-0 | BC74: Jhielson Montino Pimentel | BD74: UNIVERSIDADE SENAI CIMATEC | BE74: CIMATEC | BF74: =IF(AND(BG74,BI74,BL74,BM74),TRUE,FALSE) -> FALSE | BG74: FALSE | BH74: 2023 | BI74: FALSE | BJ74: Faixa 3 | BK74: Faixa 3 (1 propostas) | BL74: TRUE | BM74: TRUE | BN74: TRUE | BO74: - SENAI CIMATEC: (CELETISTA - Engenheiro Líder - Robótica - Especialista IV) | BP74: =IF(IFERROR(VLOOKUP(A74,[1]Planilha1!$A:$A,1,0),FALSE)=FALSE,FALSE,TRUE) -> FALSE
A75: 401993/2026-4 | B75: APQ | D75: 46204 | E75: 47664 | F75: 73397334853 | G75: Joaquim Eduardo Rezende Costa | H75: http://lattes.cnpq.br/7275059047419031 | I75: Joaquim Eduardo Rezende Costa | K75: Joaquim Eduardo Rezende Costa, Clezio Marcos De Nardin, Cristiano Max Wrasse, Delano Gobbi, Diego Barros Silva, Emilia Correia, Fábio Becker Guedes, Jean Carlo Santos, Láysa Cristina Araujo Resende Chagas, Lígia Alves | L75: 5116476 | M75: Pesquisa em clima espacial para proteção às infraestruturas críticas | N75: Programa Basico de Geociência | O75: GC | P75: Ciências Exatas e da Terra | Q75: Geofísica | R75: Instituto Nacional de Pesquisas Espaciais | S75: INPE | T75: SP | U75: SE | V75: Brasil | W75: Instituto Nacional de Pesquisas Espaciais | X75: INPE | Y75: SP | Z75: SE | AA75: Brasil | AB75: DCTI | AC75: COCQG | AD75: 25/06/2026 | AE75: 16:20:00 | AF75: 25/06/2026 | AG75: 16:50:33 | AH75: 3 | AI75: 648960 | AJ75: 0 | AK75: 0 | AL75: 648960 | AR75: 7275059047419031 | AS75: 46202.465 | AT75: PCI2026 | AU75: Chamada CNPq/MCTI/FNDCT Nº 12/2026 - Programa PCI | AV75: Chamada: Chamada CNPq/MCTI/FNDCT Nº 12/2026 - Faixa 3: Projetos de Pesquisa vinculados a | AW75: 12/2026 | AX75: Chamada CNPq/MCTI/FNDCT Nº 12/2026 - Faixa 3: Projetos de Pesquisa vinculados a UPs Grandes (acima de 200 servidores) | AY75: 27/04/2026 | AZ75: 27/06/2026 | BA75: joaquim.costa@inpe.br | BB75: 401993/2026-4 | BC75: Joaquim Eduardo Rezende Costa | BD75: Instituto Nacional de Pesquisas Espaciais | BE75: INPE | BF75: =IF(AND(BG75,BI75,BL75,BM75),TRUE,FALSE) -> TRUE | BG75: TRUE | BH75: 1990 | BI75: TRUE | BJ75: Faixa 3 | BK75: Faixa 3 (20 propostas) | BL75: TRUE | BM75: TRUE | BN75: TRUE | BO75: - Instituto Nacional de Pesquisas Espaciais: (PESQUISADOR TITULAR III) | BP75: =IF(IFERROR(VLOOKUP(A75,[1]Planilha1!$A:$A,1,0),FALSE)=FALSE,FALSE,TRUE) -> TRUE
A76: 402106/2026-1 | B76: APQ | D76: 46204 | E76: 47664 | F76: 53185005287 | G76: Jochen Schongart | H76: http://lattes.cnpq.br/2468979908831549 | I76: Jochen Schongart | K76: Jochen Schongart, Maria Teresa Fernandez Piedade, Layon Oreste Demarchi, Flavia Machado Durgante, Camila Cherem Ribas, Maria Julia Ferreira, Caroline Schmaedeck Lara, Aline Lopes, Florian Karl Wittmann, Elizabeth | L76: 5116598 | M76: Pesquisas interdisciplinares e interculturais para fortalecer a gestão territorial de áreas úmidas amazônicas | N76: PROGRAMA BASICO DE ECOLOGIA E LIMNOLOGIA | O76: EL | P76: Ciências Biológicas | Q76: Ecologia de Ecossistemas | R76: Instituto Nacional de Pesquisas da Amazônia | S76: INPA | T76: AM | U76: NO | V76: Brasil | W76: Instituto Nacional de Pesquisas da Amazônia | X76: INPA | Y76: AM | Z76: NO | AA76: Brasil | AB76: DCTI | AC76: COEBI | AD76: 26/06/2026 | AE76: 16:53:14 | AF76: 27/06/2026 | AG76: 09:53:03 | AH76: 10 | AI76: 1361400 | AJ76: 136151.6 | AK76: 0 | AL76: 1497551.6 | AM76: Instituto Nacional de Pesquisas da Amazônia | AN76: INPA | AO76: AM | AP76: NO | AQ76: Brasil | AR76: 2468979908831549 | AS76: 46202.465 | AT76: PCI2026 | AU76: Chamada CNPq/MCTI/FNDCT Nº 12/2026 - Programa PCI | AV76: Chamada: Chamada CNPq/MCTI/FNDCT Nº 12/2026 - Faixa 3: Projetos de Pesquisa vinculados a | AW76: 12/2026 | AX76: Chamada CNPq/MCTI/FNDCT Nº 12/2026 - Faixa 3: Projetos de Pesquisa vinculados a UPs Grandes (acima de 200 servidores) | AY76: 27/04/2026 | AZ76: 27/06/2026 | BA76: jochen.schongart@inpa.gov.br | BB76: 402106/2026-1 | BC76: Jochen Schongart | BD76: Instituto Nacional de Pesquisas da Amazônia | BE76: INPA | BF76: =IF(AND(BG76,BI76,BL76,BM76),TRUE,FALSE) -> FALSE | BG76: TRUE | BH76: 2003 | BI76: FALSE | BJ76: Faixa 3 | BK76: Faixa 3 (15 propostas) | BL76: TRUE | BM76: TRUE | BN76: TRUE | BO76: - Instituto Nacional de Pesquisas da Amazônia: (Servidor público - Docente permanente PPG-CFT) - Instituto Nacional de Pesquisas da Amazônia: (Vice Lider do Grupo de Pesquisa MAUA) - Instituto Nacional de Pesquisas da Amazônia: (Servidor público - Docente permanente PPG-ECO) - Instituto Nacional de Pesquisas da Amazônia: (Servidor público - Conselheiro Comitê Científico Projeto ATTO) - Instituto Nacional de Pesquisas da Amazônia: (Membro Comitê Científico - Conselheiro Comitê Científico LBA) - Instituto Nacional de Pesquisas da Amazônia: (Servidor público - Membro CDRDSU) - Instituto Nacional de Pesquisas da Amazônia: (Servidor público - Pesquisador Titular do INPA) - Instituto Nacional de Pesquisas da Amazônia: (Avaliador - Comissão de seleção de doutorado (PPG-CFT)) - Instituto Nacional de Pesquisas da Amazônia: (Servidor público - Conselheiro da CODAM) - Instituto Nacional de Pesquisas da Amazônia: (Servidor público - Membro Comitê Avaliaçãp PIBIC Ecologia) - Instituto Nacional de Pesquisas da Amazônia: (Servidor público - Membro Conselho Deliberativo da Resex BRBJ) - Instituto Nacional de Pesquisas da Amazônia: (Servidor público - Docente permanente PPG-MPGAP) - Universidade Federal do Amazonas: (PROFESSOR_VISITANTE - Colaborador) - Ernst-Moritz-Arndt-University Greifswald: (PROFESSOR_VISITANTE - Docente) - Karlsruher Institut für Technologie: (em branco) - MINISTERIO DO MEIO AMBIENTE: (Conselheiro - Membro do Comitê Nacional de Zonas Úmidas) | BP76: =IF(IFERROR(VLOOKUP(A76,[1]Planilha1!$A:$A,1,0),FALSE)=FALSE,FALSE,TRUE) -> FALSE
A77: 401101/2026-6 | B77: APQ | D77: 46204 | E77: 47664 | F77: 42301149749 | G77: Jose Abdalla Helayel Neto | H77: http://lattes.cnpq.br/4044332658989430 | I77: Jose Abdalla Helayel Neto | K77: Jose Abdalla Helayel Neto, Renato Melchiades Doria, Celso Melchiades Doria, Denis Cocuroci, Francisco Carlos Pinheiro Nunes, Erica da Silva Martins Carvalho, Washington Inácio de Souza Soares, Flavio Imbert Domingos, Luís | L77: 5114499 | M77: STEM: Educação 4.0 e inovações fotônicas | N77: PROGRAMA BASICO DE EDUCACAO | O77: ED | P77: Ciências Humanas | Q77: Ensino-Aprendizagem | R77: Centro Brasileiro de Pesquisas Físicas | S77: CBPF | T77: RJ | U77: SE | V77: Brasil | W77: Centro Brasileiro de Pesquisas Físicas | X77: CBPF | Y77: RJ | Z77: SE | AA77: Brasil | AB77: DCTI | AC77: COEDC | AD77: 27/05/2026 | AE77: 13:33:44 | AF77: 27/05/2026 | AG77: 16:43:12 | AH77: 13 | AI77: 1349220 | AJ77: 150000 | AK77: 0 | AL77: 1499220 | AM77: Centro Brasileiro de Pesquisas Físicas | AN77: CBPF | AO77: RJ | AP77: SE | AQ77: Brasil | AR77: 4044332658989430 | AS77: 46202.465 | AT77: PCI2026 | AU77: Chamada CNPq/MCTI/FNDCT Nº 12/2026 - Programa PCI | AV77: Chamada: Chamada CNPq/MCTI/FNDCT Nº 12/2026 - Faixa 3: Projetos de Pesquisa vinculados a | AW77: 12/2026 | AX77: Chamada CNPq/MCTI/FNDCT Nº 12/2026 - Faixa 3: Projetos de Pesquisa vinculados a UPs Grandes (acima de 200 servidores) | AY77: 27/04/2026 | AZ77: 27/06/2026 | BA77: josehelayel@gmail.com | BB77: 401101/2026-6 | BC77: Jose Abdalla Helayel Neto | BD77: Centro Brasileiro de Pesquisas Físicas | BE77: CBPF | BF77: =IF(AND(BG77,BI77,BL77,BM77),TRUE,FALSE) -> FALSE | BG77: TRUE | BH77: 1983 | BI77: FALSE | BJ77: Faixa 3 | BK77: Faixa 2 (24 propostas) | BL77: FALSE | BM77: TRUE | BN77: TRUE | BO77: - Centro Brasileiro de Pesquisas Físicas: (SERVIDOR_PUBLICO - Pesquisador Titular) - Grupo de Física Teórica José Leite Lopes: (Membro Efetivo - Pesquisador) - Aprendanet - Petrópolis: (COLABORADOR - Colaborador na Coordenação Científica) - Instituto Federal de Educação, Ciência e Tecnologia do Rio de Janeiro: (COLABORADOR - Professor-Colaborador) | BP77: =IF(IFERROR(VLOOKUP(A77,[1]Planilha1!$A:$A,1,0),FALSE)=FALSE,FALSE,TRUE) -> FALSE
A78: 401134/2026-1 | B78: APQ | D78: 46204 | E78: 47664 | F78: 00794506445 | G78: Jose Adson Oliveira Guedes da Cunha | H78: http://lattes.cnpq.br/3912060609881766 | I78: Jose Adson Oliveira Guedes da Cunha | K78: Jose Adson Oliveira Guedes da Cunha, Alexandre José Henrique de Oliveira Luna | L78: 5115108 | M78: Plataforma de Serious Game para Experimentação e Sistematização de Nudges em Ambientes Digitais | N78: PROGRAMA BASICO DE CIENCIA DA COMPUTACAO | O78: CC | P78: Ciências Exatas e da Terra | Q78: Sistemas de Informação | R78: Universidade Federal da Paraíba | S78: UFPB | T78: PB | U78: NE | V78: Brasil | W78: Universidade Federal da Paraíba | X78: UFPB | Y78: PB | Z78: NE | AA78: Brasil | AB78: DCTI | AC78: COCEC | AD78: 27/05/2026 | AE78: 22:24:05 | AF78: 27/05/2026 | AG78: 22:24:13 | AH78: 4 | AI78: 187200 | AJ78: 0 | AK78: 0 | AL78: 187200 | AM78: Universidade Federal da Paraíba | AN78: UFPB | AO78: PB | AP78: NE | AQ78: Brasil | AR78: 3912060609881766 | AS78: 46202.465 | AT78: PCI2026 | AU78: Chamada CNPq/MCTI/FNDCT Nº 12/2026 - Programa PCI | AV78: Chamada: Chamada CNPq/MCTI/FNDCT Nº 12/2026 - Faixa 3: Projetos de Pesquisa vinculados a | AW78: 12/2026 | AX78: Chamada CNPq/MCTI/FNDCT Nº 12/2026 - Faixa 3: Projetos de Pesquisa vinculados a UPs Grandes (acima de 200 servidores) | AY78: 27/04/2026 | AZ78: 27/06/2026 | BA78: adsoncunha@gmail.com | BB78: 401134/2026-1 | BC78: Jose Adson Oliveira Guedes da Cunha | BD78: Universidade Federal da Paraíba | BE78: UFPB | BF78: =IF(AND(BG78,BI78,BL78,BM78),TRUE,FALSE) -> FALSE | BG78: FALSE | BH78: 2016 | BI78: FALSE | BJ78: Faixa 3 | BK78: Faixa 3 (2 propostas) | BL78: TRUE | BM78: TRUE | BN78: TRUE | BO78: - Universidade Federal da Paraíba: (Servidor público - Professor Adjunto) - Escola Nacional de Administração Pública: (COLABORADOR - Colaborador) - SECRETARIA DE ESTADO DA SAUDE - SES: (Bolsista - Bolsista) | BP78: =IF(IFERROR(VLOOKUP(A78,[1]Planilha1!$A:$A,1,0),FALSE)=FALSE,FALSE,TRUE) -> FALSE
A79: 402326/2026-1 | B79: APQ | D79: 46204 | E79: 47664 | F79: 00655044884 | G79: Jose Bustillos | H79: http://lattes.cnpq.br/6677363162414640 | I79: Jose Bustillos | K79: Jose Bustillos, Maria Claudia França da Cunha Felinto, Hermi Felinto de Brito, Caroline Kako Ostermann | L79: 5116824 | M79: Sensores eletro-ópticos multimodais baseados em pontos quânticos e nanopartículas cerâmicas para detecção de contaminantes emergentes | N79: PROGRAMA BASICO DE QUIMICA | O79: QU | P79: Ciências Exatas e da Terra | Q79: Química Analítica | R79: COMISSAO NACIONAL DE ENERGIA NUCLEAR | S79: CNEN | T79: RJ | U79: SE | V79: Brasil | W79: COMISSAO NACIONAL DE ENERGIA NUCLEAR | X79: CNEN | Y79: RJ | Z79: SE | AA79: Brasil | AB79: DCTI | AC79: COCQG | AD79: 27/06/2026 | AE79: 11:58:29 | AF79: 27/06/2026 | AG79: 11:58:37 | AH79: 4 | AI79: 686400 | AJ79: 99146.66 | AK79: 0 | AL79: 785546.66 | AM79: COMISSAO NACIONAL DE ENERGIA NUCLEAR | AN79: CNEN | AO79: RJ | AP79: SE | AQ79: Brasil | AR79: 6677363162414640 | AS79: 46202.465 | AT79: PCI2026 | AU79: Chamada CNPq/MCTI/FNDCT Nº 12/2026 - Programa PCI | AV79: Chamada: Chamada CNPq/MCTI/FNDCT Nº 12/2026 - Faixa 3: Projetos de Pesquisa vinculados a | AW79: 12/2026 | AX79: Chamada CNPq/MCTI/FNDCT Nº 12/2026 - Faixa 3: Projetos de Pesquisa vinculados a UPs Grandes (acima de 200 servidores) | AY79: 27/04/2026 | AZ79: 27/06/2026 | BA79: ovega@ipen.br | BB79: 402326/2026-1 | BC79: Jose Bustillos | BD79: COMISSAO NACIONAL DE ENERGIA NUCLEAR | BE79: CNEN | BF79: =IF(AND(BG79,BI79,BL79,BM79),TRUE,FALSE) -> FALSE | BG79: TRUE | BH79: 1996 | BI79: FALSE | BJ79: Faixa 3 | BK79: Faixa 3 (32 propostas) | BL79: TRUE | BM79: TRUE | BN79: TRUE | BO79: - COMISSAO NACIONAL DE ENERGIA NUCLEAR: (Servidor público ou celetista - Pesquisador) - Universidade do Estado do Amazonas: (PROFESSOR_VISITANTE - Professor visitante) - Instituto Nacional de Pesquisas da Amazônia: (em branco) - Instituto de Botânica: (em branco) - Espaço Lógico Software e Comércio Ltda.: (em branco) | BP79: =IF(IFERROR(VLOOKUP(A79,[1]Planilha1!$A:$A,1,0),FALSE)=FALSE,FALSE,TRUE) -> FALSE
A80: 402016/2026-2 | B80: APQ | D80: 46204 | E80: 47664 | F80: 48876143734 | G80: Jose Domingos Ardisson | H80: http://lattes.cnpq.br/6486792705300520 | I80: Jose Domingos Ardisson | K80: Jose Domingos Ardisson, Adelina Pinheiro Santos, Adriana Silva de Albuquerque, Alice Freitas Versiani, Amanda Keller dos Reis Alfeu, Andre Felipe de Oliveira, Bianca Cardenas Moreno Lima, Caíque Amorim Silveira, Clascidia | L80: 5116506 | M80: Nanoplataformas multifuncionais: tecnologias habilitadoras para diagnóstico, terapias responsivas e sistemas teranósticos | N80: PROGRAMA BASICO DE FISICA | O80: FA | P80: Ciências Exatas e da Terra | Q80: Física da Matéria Condensada | R80: COMISSAO NACIONAL DE ENERGIA NUCLEAR | S80: CNEN | T80: RJ | U80: SE | V80: Brasil | W80: COMISSAO NACIONAL DE ENERGIA NUCLEAR | X80: CNEN | Y80: RJ | Z80: SE | AA80: Brasil | AB80: DCTI | AC80: COCEC | AD80: 26/06/2026 | AE80: 02:27:52 | AF80: 26/06/2026 | AG80: 02:28:13 | AH80: 5 | AI80: 1248000 | AJ80: 144213.33 | AK80: 0 | AL80: 1392213.3 | AR80: 6486792705300520 | AS80: 46202.465 | AT80: PCI2026 | AU80: Chamada CNPq/MCTI/FNDCT Nº 12/2026 - Programa PCI | AV80: Chamada: Chamada CNPq/MCTI/FNDCT Nº 12/2026 - Faixa 3: Projetos de Pesquisa vinculados a | AW80: 12/2026 | AX80: Chamada CNPq/MCTI/FNDCT Nº 12/2026 - Faixa 3: Projetos de Pesquisa vinculados a UPs Grandes (acima de 200 servidores) | AY80: 27/04/2026 | AZ80: 27/06/2026 | BA80: jdr@cdtn.br | BB80: 402016/2026-2 | BC80: Jose Domingos Ardisson | BD80: COMISSAO NACIONAL DE ENERGIA NUCLEAR | BE80: CNEN | BF80: =IF(AND(BG80,BI80,BL80,BM80),TRUE,FALSE) -> TRUE | BG80: TRUE | BH80: 1995 | BI80: TRUE | BJ80: Faixa 3 | BK80: Faixa 3 (32 propostas) | BL80: TRUE | BM80: TRUE | BN80: TRUE | BO80: - COMISSAO NACIONAL DE ENERGIA NUCLEAR: (Pesquisador titular) - Centro de Desenvolvimento da Tecnologia Nuclear: (Chefe Substituto da DIIMM/CDTN/CNEN) - Centro de Desenvolvimento da Tecnologia Nuclear: (Chefe Substituto DO SENAN/CDTN/CNEN) | BP80: =IF(IFERROR(VLOOKUP(A80,[1]Planilha1!$A:$A,1,0),FALSE)=FALSE,FALSE,TRUE) -> TRUE
A81: 401982/2026-2 | B81: APQ | D81: 46204 | E81: 47664 | F81: 17944662826 | G81: José Eduardo May | H81: http://lattes.cnpq.br/3462281514752860 | I81: José Eduardo May | K81: José Eduardo May, Valeri Vlassov Vladimirovich, Rafael Lopes Costa, Cristiano Enke, Graziela da Silva Savonov | L81: 5116463 | M81: Tubos de Calor Alumínio - Água para Uso em Controle Térmico de Satélites | N81: PROGRAMA BASICO DE ENGENHARIA MECANICA | O81: EM | P81: Engenharias | Q81: Engenharia Térmica | R81: Instituto Nacional de Pesquisas Espaciais | S81: INPE | T81: SP | U81: SE | V81: Brasil | W81: Instituto Nacional de Pesquisas Espaciais | X81: INPE | Y81: SP | Z81: SE | AA81: Brasil | AB81: DCTI | AC81: COENG | AD81: 25/06/2026 | AE81: 16:15:48 | AF81: 25/06/2026 | AG81: 16:17:47 | AH81: 9 | AI81: 1396720 | AJ81: 126547.2 | AK81: 0 | AL81: 1523267.2 | AM81: Instituto Nacional de Pesquisas Espaciais | AN81: INPE | AO81: SP | AP81: SE | AQ81: Brasil | AR81: 3462281514752860 | AS81: 46202.465 | AT81: PCI2026 | AU81: Chamada CNPq/MCTI/FNDCT Nº 12/2026 - Programa PCI | AV81: Chamada: Chamada CNPq/MCTI/FNDCT Nº 12/2026 - Faixa 3: Projetos de Pesquisa vinculados a | AW81: 12/2026 | AX81: Chamada CNPq/MCTI/FNDCT Nº 12/2026 - Faixa 3: Projetos de Pesquisa vinculados a UPs Grandes (acima de 200 servidores) | AY81: 27/04/2026 | AZ81: 27/06/2026 | BA81: jose.may@inpe.br | BB81: 401982/2026-2 | BC81: José Eduardo May | BD81: Instituto Nacional de Pesquisas Espaciais | BE81: INPE | BF81: =IF(AND(BG81,BI81,BL81,BM81),TRUE,FALSE) -> TRUE | BG81: TRUE | BH81: 2004 | BI81: TRUE | BJ81: Faixa 3 | BK81: Faixa 3 (20 propostas) | BL81: TRUE | BM81: TRUE | BN81: TRUE | BO81: - Instituto Nacional de Pesquisas Espaciais: (Servidor público - TEcnologista) | BP81: =IF(IFERROR(VLOOKUP(A81,[1]Planilha1!$A:$A,1,0),FALSE)=FALSE,FALSE,TRUE) -> TRUE
A82: 401966/2026-7 | B82: APQ | D82: 46204 | E82: 47664 | F82: 10507108272 | G82: José Francisco Berrêdo Reis da Silva | H82: http://lattes.cnpq.br/1338038101910673 | I82: José Francisco Berrêdo Reis da Silva | K82: José Francisco Berrêdo Reis da Silva, Ana Paula Linhares Pereira, Paula Godinho Ribeiro, Admilson Moreira Torres, Luís Roberto Takiyama, Pedro Walfir Martins e Souza Filho, Vinicius Tavares Kütter, Zoneibe Augusto Silva Luz, | L82: 5116446 | M82: Baseline de metais e saúde dos sedimentos/solos de manguezais da Margem Equatorial Norte para a avaliação de serviços ecossistêmicos e desenvolvimento da Região Amazônica. | N82: Programa Basico de Geociência | O82: GC | P82: Ciências Exatas e da Terra | Q82: Geologia | R82: Museu Paraense Emílio Goeldi | S82: MPEG | T82: PA | U82: NO | V82: Brasil | W82: Museu Paraense Emílio Goeldi | X82: MPEG | Y82: PA | Z82: NO | AA82: Brasil | AB82: DCTI | AC82: COCQG | AD82: 25/06/2026 | AE82: 15:11:38 | AF82: 25/06/2026 | AG82: 15:12:34 | AH82: 9 | AI82: 1358448 | AJ82: 135844.8 | AK82: 0 | AL82: 1494292.8 | AM82: Museu Paraense Emílio Goeldi | AN82: MPEG | AO82: PA | AP82: NO | AQ82: Brasil | AR82: 1338038101910673 | AS82: 46202.465 | AT82: PCI2026 | AU82: Chamada CNPq/MCTI/FNDCT Nº 12/2026 - Programa PCI | AV82: Chamada: Chamada CNPq/MCTI/FNDCT Nº 12/2026 - Faixa 3: Projetos de Pesquisa vinculados a | AW82: 12/2026 | AX82: Chamada CNPq/MCTI/FNDCT Nº 12/2026 - Faixa 3: Projetos de Pesquisa vinculados a UPs Grandes (acima de 200 servidores) | AY82: 27/04/2026 | AZ82: 27/06/2026 | BA82: berredo@museu-goeldi.br | BB82: 401966/2026-7 | BC82: José Francisco Berrêdo Reis da Silva | BD82: Museu Paraense Emílio Goeldi | BE82: MPEG | BF82: =IF(AND(BG82,BI82,BL82,BM82),TRUE,FALSE) -> TRUE | BG82: TRUE | BH82: 2006 | BI82: TRUE | BJ82: Faixa 3 | BK82: Faixa 3 (24 propostas) | BL82: TRUE | BM82: TRUE | BN82: TRUE | BO82: - Museu Paraense Emílio Goeldi: (Servidor público - Pesquisador Associado I (B IV)) - Universidade Federal Rural da Amazônia: (em branco) - Universide Federal do Pará: (em branco) | BP82: =IF(IFERROR(VLOOKUP(A82,[1]Planilha1!$A:$A,1,0),FALSE)=FALSE,FALSE,TRUE) -> TRUE
A83: 402322/2026-6 | B83: APQ | D83: 46204 | E83: 47664 | F83: 14181231453 | G83: José Luiz Alves | H83: http://lattes.cnpq.br/7078869287819893 | I83: José Luiz Alves | K83: José Luiz Alves, Marcella Grangeiro Lima, Geysa Karla Alves Galvão, Charlis Alberto Cabral de Moraes Júnior | L83: 5116820 | M83: Consultoria conectada a Agenda 2030: jogos digitais com ênfase na sustentabilidade das empresas públicas e privadas. | N83: PROGRAMA BASICO DE ADMINISTRACAO | O83: AE | P83: Ciências Sociais Aplicadas | Q83: Administração de Empresas | R83: Universidade de Pernambuco | S83: UPE | T83: PE | U83: NE | V83: Brasil | W83: Universidade de Pernambuco | X83: UPE | Y83: PE | Z83: NE | AA83: Brasil | AB83: DCTI | AC83: COSAE | AD83: 27/06/2026 | AE83: 11:45:29 | AF83: 27/06/2026 | AG83: 11:45:38 | AH83: 4 | AI83: 686400 | AJ83: 396768 | AK83: 0 | AL83: 1083168 | AM83: Universidade de Pernambuco | AN83: UPE | AO83: PE | AP83: NE | AQ83: Brasil | AR83: 7078869287819893 | AS83: 46202.465 | AT83: PCI2026 | AU83: Chamada CNPq/MCTI/FNDCT Nº 12/2026 - Programa PCI | AV83: Chamada: Chamada CNPq/MCTI/FNDCT Nº 12/2026 - Faixa 3: Projetos de Pesquisa vinculados a | AW83: 12/2026 | AX83: Chamada CNPq/MCTI/FNDCT Nº 12/2026 - Faixa 3: Projetos de Pesquisa vinculados a UPs Grandes (acima de 200 servidores) | AY83: 27/04/2026 | AZ83: 27/06/2026 | BA83: luiz.alves@upe.br | BB83: 402322/2026-6 | BC83: José Luiz Alves | BD83: Universidade de Pernambuco | BE83: UPE | BF83: =IF(AND(BG83,BI83,BL83,BM83),TRUE,FALSE) -> FALSE | BG83: FALSE | BH83: 2011 | BI83: FALSE | BJ83: Faixa 3 | BK83: Faixa 3 (1 propostas) | BL83: TRUE | BM83: TRUE | BN83: TRUE | BO83: - Universidade de Pernambuco: (Servidor público - Estatutário) - Instituto Nacional de Estudos e Pesquisas Educacionais Anísio Teixeira: (Membro de comitê assessor) - Universidade de Pernambuco: (em branco) | BP83: =IF(IFERROR(VLOOKUP(A83,[1]Planilha1!$A:$A,1,0),FALSE)=FALSE,FALSE,TRUE) -> FALSE
A84: 402190/2026-2 | B84: APQ | D84: 46204 | E84: 47664 | F84: 90041640659 | G84: Jose Ricardo Cezar Salgado | H84: http://lattes.cnpq.br/3914867445646676 | I84: Jose Ricardo Cezar Salgado | K84: Jose Ricardo Cezar Salgado, Diogo Miguel Franco dos Santos, Josimar Ribeiro, Leonardo Alexandre Veltrone, Adalberto Teógenes Tavares Júnior, Henrique Chien Hua Nascimento, Jorge Luis de Oliveira Gomes, Márcio de | L84: 5116684 | M84: Desenvolvimento de Eletrocatalisadores Ternários CoNiCu Obtidos por Eletrodeposição para Aplicação na Reação de Desprendimento de Hidrogênio e Oxigênio visando Produção Sustentável de Hidrogênio Verde | N84: PROGRAMA BASICO DE QUIMICA | O84: QU | P84: Ciências Exatas e da Terra | Q84: Eletroquímica | R84: Universidade Federal da Integração Latino-Americana | S84: UNILA | T84: PR | U84: SU | V84: Brasil | W84: Universidade Federal da Integração Latino-Americana | X84: UNILA | Y84: PR | Z84: SU | AA84: Brasil | AB84: DCTI | AC84: COCQG | AD84: 26/06/2026 | AE84: 17:55:07 | AF84: 27/06/2026 | AG84: 09:58:08 | AH84: 12 | AI84: 1049820 | AJ84: 104982 | AK84: 0 | AL84: 1154802 | AM84: Universidade Federal da Integração Latino-Americana | AN84: UNILA | AO84: PR | AP84: SU | AQ84: Brasil | AR84: 3914867445646676 | AS84: 46202.465 | AT84: PCI2026 | AU84: Chamada CNPq/MCTI/FNDCT Nº 12/2026 - Programa PCI | AV84: Chamada: Chamada CNPq/MCTI/FNDCT Nº 12/2026 - Faixa 3: Projetos de Pesquisa vinculados a | AW84: 12/2026 | AX84: Chamada CNPq/MCTI/FNDCT Nº 12/2026 - Faixa 3: Projetos de Pesquisa vinculados a UPs Grandes (acima de 200 servidores) | AY84: 27/04/2026 | AZ84: 27/06/2026 | BA84: jrc_salgado@yahoo.com.br | BB84: 402190/2026-2 | BC84: Jose Ricardo Cezar Salgado | BD84: Universidade Federal da Integração Latino-Americana | BE84: UNILA | BF84: =IF(AND(BG84,BI84,BL84,BM84),TRUE,FALSE) -> FALSE | BG84: FALSE | BH84: 2005 | BI84: FALSE | BJ84: Faixa 3 | BK84: Faixa 3 (4 propostas) | BL84: TRUE | BM84: TRUE | BN84: TRUE | BO84: - Universidade Federal da Integração Latino-Americana: (Servidor público - Professor Adjunto A1) - Fundação Araucária de Apoio ao Desenvolvimento Científico e Tecnológico: (Membro de comitê assessor) - Universidade Federal da Fronteira Sul - Campus Realeza: (Membro de comitê assessor) - Universidade Federal de Pelotas: (Membro de comitê assessor) - Universidade Estadual do Rio Grande do Sul: (Membro de comitê assessor) | BP84: =IF(IFERROR(VLOOKUP(A84,[1]Planilha1!$A:$A,1,0),FALSE)=FALSE,FALSE,TRUE) -> FALSE
A85: 401045/2026-9 | B85: APQ | D85: 46204 | E85: 47664 | F85: 33954487896 | G85: Joyce Rodrigues de Araújo | H85: http://lattes.cnpq.br/8715885877497181 | I85: Joyce Rodrigues de Araújo | K85: Joyce Rodrigues de Araújo, Maria de Fátima Vieira Marques, Michelle Gonçalves Mothé, Thenner Silva Rodrigues, Rogerio Valaski, Fabiele Collovini Tavares, Alan de Araujo Dias, Marcello Pojucan Magaldi Santos | L85: 5111639 | M85: Plataforma Nacional de Filmes Finos Semicondutores para Energia e Optoeletrônica | N85: PROGRAMA BASICO DE ENGENHARIA DE MATERIAIS E METALURGIA | O85: MM | P85: Engenharias | Q85: Polímeros, Aplicações | R85: Instituto Nacional de Metrologia, Qualidade e Tecnologia | S85: INMETRO | T85: DF | U85: CO | V85: Brasil | W85: Instituto Nacional de Metrologia, Qualidade e Tecnologia | X85: INMETRO | Y85: DF | Z85: CO | AA85: Brasil | AB85: DCTI | AC85: COBEN | AD85: 25/05/2026 | AE85: 14:02:52 | AF85: 25/05/2026 | AG85: 14:02:59 | AH85: 12 | AI85: 1439620 | AJ85: 60000 | AK85: 0 | AL85: 1499620 | AM85: Instituto Nacional de Metrologia, Qualidade e Tecnologia | AN85: INMETRO | AO85: DF | AP85: CO | AQ85: Brasil | AR85: 8715885877497181 | AS85: 46202.465 | AT85: PCI2026 | AU85: Chamada CNPq/MCTI/FNDCT Nº 12/2026 - Programa PCI | AV85: Chamada: Chamada CNPq/MCTI/FNDCT Nº 12/2026 - Faixa 3: Projetos de Pesquisa vinculados a | AW85: 12/2026 | AX85: Chamada CNPq/MCTI/FNDCT Nº 12/2026 - Faixa 3: Projetos de Pesquisa vinculados a UPs Grandes (acima de 200 servidores) | AY85: 27/04/2026 | AZ85: 27/06/2026 | BA85: joyce.2003@gmail.com | BB85: 401045/2026-9 | BC85: Joyce Rodrigues de Araújo | BD85: Instituto Nacional de Metrologia, Qualidade e Tecnologia | BE85: INMETRO | BF85: =IF(AND(BG85,BI85,BL85,BM85),TRUE,FALSE) -> FALSE | BG85: FALSE | BH85: 2012 | BI85: FALSE | BJ85: Faixa 3 | BK85: Faixa 3 (1 propostas) | BL85: TRUE | BM85: TRUE | BN85: FALSE | BO85: - Instituto Nacional de Metrologia, Qualidade e Tecnologia: (Pesquisador Tecnologista) - Instituto Nacional de Metrologia, Qualidade e Tecnologia: (em branco) | BP85: =IF(IFERROR(VLOOKUP(A85,[1]Planilha1!$A:$A,1,0),FALSE)=FALSE,FALSE,TRUE) -> FALSE
A86: 402180/2026-7 | B86: APQ | D86: 46204 | E86: 47664 | F86: 07695340740 | G86: Katia Carneiro de Paula | H86: http://lattes.cnpq.br/8188475000675337 | I86: Katia Carneiro de Paula | K86: Katia Carneiro de Paula, Adriana de Oliveira e Silva, Luiza Carneiro Chrysóstomo, Renata Milhomem Sá, Maria Fernanda Lima Oliveira, Nathália Pentagna Maciello Drummond Pires, Rafael Carlini Ruzzi | L86: 5116674 | M86: Caracterização multi-ômica de uma terapia epigenética para promover a regeneração tecidual em modelo pré-clínico saudável e diabético | N86: PROGRAMA BASICO DE MORFOLOGIA | O86: MF | P86: Ciências Biológicas | Q86: Citologia e Biologia Celular | R86: Universidade Federal do Rio de Janeiro | S86: UFRJ | T86: RJ | U86: SE | V86: Brasil | W86: Universidade Federal do Rio de Janeiro | X86: UFRJ | Y86: RJ | Z86: SE | AA86: Brasil | AB86: DCTI | AC86: COBIO | AD86: 26/06/2026 | AE86: 23:31:52 | AF86: 27/06/2026 | AG86: 09:57:32 | AH86: 2 | AI86: 399360 | AJ86: 45000 | AK86: 0 | AL86: 444360 | AM86: Universidade Federal do Rio de Janeiro | AN86: UFRJ | AO86: RJ | AP86: SE | AQ86: Brasil | AR86: 8188475000675337 | AS86: 46202.465 | AT86: PCI2026 | AU86: Chamada CNPq/MCTI/FNDCT Nº 12/2026 - Programa PCI | AV86: Chamada: Chamada CNPq/MCTI/FNDCT Nº 12/2026 - Faixa 3: Projetos de Pesquisa vinculados a | AW86: 12/2026 | AX86: Chamada CNPq/MCTI/FNDCT Nº 12/2026 - Faixa 3: Projetos de Pesquisa vinculados a UPs Grandes (acima de 200 servidores) | AY86: 27/04/2026 | AZ86: 27/06/2026 | BA86: kcarneiro@histo.ufrj.br | BB86: 402180/2026-7 | BC86: Katia Carneiro de Paula | BD86: Universidade Federal do Rio de Janeiro | BE86: UFRJ | BF86: =IF(AND(BG86,BI86,BL86,BM86),TRUE,FALSE) -> FALSE | BG86: FALSE | BH86: 2007 | BI86: FALSE | BJ86: Faixa 3 | BK86: Faixa 3 (6 propostas) | BL86: TRUE | BM86: TRUE | BN86: TRUE | BO86: - Universidade Federal do Rio de Janeiro: (Coordenadora Pós-graduação) - Universidade Federal do Rio de Janeiro: (Servidor público - Professora Associada) - Universidade Federal do Rio de Janeiro: (Servidor público - Coordenadora de Programa de Pesquisa) - Fundação de Amparo à Pesquisa do Estado de São Paulo: (Membro de comitê assessor) - UFRJ: (Membro de comitê assessor) - Ministério da Saúde: (Membro de comitê assessor) - Université de Haute-Alsace: (PROFESSOR_VISITANTE - Researcher) | BP86: =IF(IFERROR(VLOOKUP(A86,[1]Planilha1!$A:$A,1,0),FALSE)=FALSE,FALSE,TRUE) -> FALSE
A87: 401990/2026-5 | B87: APQ | D87: 46204 | E87: 47664 | F87: 19041906851 | G87: Kleber Pinheiro Naccarato | H87: http://lattes.cnpq.br/6324293045209180 | I87: Kleber Pinheiro Naccarato | K87: Kleber Pinheiro Naccarato, Ernani de Lima Nascimento, Aurelienne Aparecida Souza Jorge, Izabelly Carvalho da Costa, Thiago Souza Biscaro, Diego Pereira Enoré, Caio Átila Pereira Sena, Diego Rodrigo Moitinho de Souza, | L87: 5116473 | M87: Geração e Disseminação de Produtos Derivados de Dados de Sensoriamento Remoto para Aprimoramento da Infraestrutura Institucional de Modelagem Numérica de Tempo e Sistema Integrado de Bases de Dados | N87: Programa Basico de Ciências Ambientais | O87: CA | P87: Ciências Exatas e da Terra | Q87: Meteorologia | R87: Instituto Nacional de Pesquisas Espaciais | S87: INPE | T87: SP | U87: SE | V87: Brasil | W87: Instituto Nacional de Pesquisas Espaciais | X87: INPE | Y87: SP | Z87: SE | AA87: Brasil | AB87: DCTI | AC87: COCAM | AD87: 25/06/2026 | AE87: 16:31:45 | AF87: 25/06/2026 | AG87: 16:50:25 | AH87: 9 | AI87: 1460160 | AJ87: 39000 | AK87: 0 | AL87: 1499160 | AM87: Instituto Nacional de Pesquisas Espaciais | AN87: INPE | AO87: SP | AP87: SE | AQ87: Brasil | AR87: 6324293045209180 | AS87: 46202.465 | AT87: PCI2026 | AU87: Chamada CNPq/MCTI/FNDCT Nº 12/2026 - Programa PCI | AV87: Chamada: Chamada CNPq/MCTI/FNDCT Nº 12/2026 - Faixa 3: Projetos de Pesquisa vinculados a | AW87: 12/2026 | AX87: Chamada CNPq/MCTI/FNDCT Nº 12/2026 - Faixa 3: Projetos de Pesquisa vinculados a UPs Grandes (acima de 200 servidores) | AY87: 27/04/2026 | AZ87: 27/06/2026 | BA87: kleber.naccarato@inpe.br | BB87: 401990/2026-5 | BC87: Kleber Pinheiro Naccarato | BD87: Instituto Nacional de Pesquisas Espaciais | BE87: INPE | BF87: =IF(AND(BG87,BI87,BL87,BM87),TRUE,FALSE) -> TRUE | BG87: TRUE | BH87: 2005 | BI87: TRUE | BJ87: Faixa 3 | BK87: Faixa 3 (20 propostas) | BL87: TRUE | BM87: TRUE | BN87: FALSE | BO87: - Instituto Nacional de Pesquisas Espaciais: (Pesquisador Associado I) - Instituto Tecnológico de Aeronáutica: (Pesquisador Colaborador - Docente de Pós-Graduação) | BP87: =IF(IFERROR(VLOOKUP(A87,[1]Planilha1!$A:$A,1,0),FALSE)=FALSE,FALSE,TRUE) -> TRUE
A88: 402191/2026-9 | B88: APQ | D88: 46204 | E88: 47664 | F88: 78771919287 | G88: Larissa Ramos Chevreuil | H88: http://lattes.cnpq.br/8899452024207330 | I88: Larissa Ramos Chevreuil | K88: Larissa Ramos Chevreuil, Ceci Sales-Campos, Simone de Nazaré Melo Ramos, Raimundo Sousa Lima Júnior, Márcia Queiroz Latorraca, Maressa Caldeira Morzelle, Julia Ines Fariña, Edson Pablo da Silva, Larissa Batista do Nascimento | L88: 5116685 | M88: FUNGIbioActive: Rede Integrada de Capacitação Científica e Desenvolvimento Tecnológico de Macrofungos Amazônicos para Saúde e Bioeconomia | N88: PROGRAMA BASICO DE MICROBIOLOGIA | O88: MP | P88: Ciências Biológicas | Q88: Microbiologia Aplicada | R88: Instituto Nacional de Pesquisas da Amazônia | S88: INPA | T88: AM | U88: NO | V88: Brasil | W88: Instituto Nacional de Pesquisas da Amazônia | X88: INPA | Y88: AM | Z88: NO | AA88: Brasil | AB88: DCTI | AC88: COBIO | AD88: 26/06/2026 | AE88: 17:50:02 | AF88: 27/06/2026 | AG88: 09:58:11 | AH88: 5 | AI88: 839280 | AJ88: 121229.33 | AK88: 0 | AL88: 960509.33 | AM88: Instituto Nacional de Pesquisas da Amazônia | AN88: INPA | AO88: AM | AP88: NO | AQ88: Brasil | AR88: 8899452024207330 | AS88: 46202.465 | AT88: PCI2026 | AU88: Chamada CNPq/MCTI/FNDCT Nº 12/2026 - Programa PCI | AV88: Chamada: Chamada CNPq/MCTI/FNDCT Nº 12/2026 - Faixa 3: Projetos de Pesquisa vinculados a | AW88: 12/2026 | AX88: Chamada CNPq/MCTI/FNDCT Nº 12/2026 - Faixa 3: Projetos de Pesquisa vinculados a UPs Grandes (acima de 200 servidores) | AY88: 27/04/2026 | AZ88: 27/06/2026 | BA88: lchevreuil@inpa.gov.br | BB88: 402191/2026-9 | BC88: Larissa Ramos Chevreuil | BD88: Instituto Nacional de Pesquisas da Amazônia | BE88: INPA | BF88: =IF(AND(BG88,BI88,BL88,BM88),TRUE,FALSE) -> TRUE | BG88: TRUE | BH88: 2013 | BI88: TRUE | BJ88: Faixa 3 | BK88: Faixa 3 (15 propostas) | BL88: TRUE | BM88: TRUE | BN88: TRUE | BO88: - Instituto Nacional de Pesquisas da Amazônia: (Servidor público - Pesquisador) - Universidade Estadual de Campinas: (COLABORADOR - integrante de projeto de pesquisa) - Universidade de Caxias do Sul: (COLABORADOR - integrante de projeto de pesquisa) - Universidade Federal do Amazonas: (Professora Colaboradora - Professora colaboradora) - Universidade do Estado do Amazonas: (Professora Colaboradora - Professora colaboradora) | BP88: =IF(IFERROR(VLOOKUP(A88,[1]Planilha1!$A:$A,1,0),FALSE)=FALSE,FALSE,TRUE) -> TRUE
A89: 402384/2026-1 | B89: APQ | D89: 46204 | E89: 47664 | F89: 32588088805 | G89: Lina Bufalino | H89: http://lattes.cnpq.br/1775021506836485 | I89: Lina Bufalino | K89: Lina Bufalino, Lays Camila Matos, Ingryd Aranda Maciel da Silva, Valéria De Jesus Pereira, Paulo Roberto Santos Josino, Dhimitrius Neves Paraguassu Smith de Oliveira, Luiza Helena da Silva Martins, Nathália Santos Serrão de | L89: 5116882 | M89: PRODUTOS CELULÓSICOS DE FIBRAS DO RESÍDUO DE AÇAÍ FUNCIONALIZADOS COM BIOATIVOS AMAZÔNICOS PARA ECOEMBALAGENS | N89: PROGRAMA BASICO DE RECURSOS FLORESTAIS E ENGENHARIA FLORESTAL | O89: RF | P89: Ciências Agrárias | Q89: Tecnologia e Utilização de Produtos Florestais | R89: Universidade Federal Rural da Amazônia | S89: UFRA | T89: PA | U89: NO | V89: Brasil | W89: Universidade Federal Rural da Amazônia | X89: UFRA | Y89: PA | Z89: NO | AA89: Brasil | AB89: DCTI | AC89: COAGR | AD89: 27/06/2026 | AE89: 19:37:45 | AF89: 27/06/2026 | AG89: 19:37:52 | AH89: 7 | AI89: 823680 | AJ89: 94848 | AK89: 0 | AL89: 918528 | AM89: Universidade Federal Rural da Amazônia | AN89: UFRA | AO89: PA | AP89: NO | AQ89: Brasil | AR89: 1775021506836485 | AS89: 46202.465 | AT89: PCI2026 | AU89: Chamada CNPq/MCTI/FNDCT Nº 12/2026 - Programa PCI | AV89: Chamada: Chamada CNPq/MCTI/FNDCT Nº 12/2026 - Faixa 3: Projetos de Pesquisa vinculados a | AW89: 12/2026 | AX89: Chamada CNPq/MCTI/FNDCT Nº 12/2026 - Faixa 3: Projetos de Pesquisa vinculados a UPs Grandes (acima de 200 servidores) | AY89: 27/04/2026 | AZ89: 27/06/2026 | BA89: linabufalino1@gmail.com | BB89: 402384/2026-1 | BC89: Lina Bufalino | BD89: Universidade Federal Rural da Amazônia | BE89: UFRA | BF89: =IF(AND(BG89,BI89,BL89,BM89),TRUE,FALSE) -> FALSE | BG89: FALSE | BH89: 2014 | BI89: FALSE | BJ89: Faixa 3 | BK89: Faixa 3 (2 propostas) | BL89: TRUE | BM89: TRUE | BN89: TRUE | BO89: - Universidade Federal do Amapá: (Pós-graduação - Professor Efetivo) - Universidade Federal Rural da Amazônia: (Servidor público - Professora) - The Biodiversity Research Consortium Brazil-Norway: (Membro de comitê assessor) - Universidade Estadual do Maranhão: (Pós Graduação - Professora permanente de pós-graduação) | BP89: =IF(IFERROR(VLOOKUP(A89,[1]Planilha1!$A:$A,1,0),FALSE)=FALSE,FALSE,TRUE) -> FALSE
A90: 402009/2026-6 | B90: APQ | D90: 46204 | E90: 47664 | F90: 06501970466 | G90: Lis Fernandes Stegmann | H90: http://lattes.cnpq.br/9454867287897965 | I90: Lis Fernandes Stegmann | K90: Lis Fernandes Stegmann, Sâmia Batista e Silva, Sue Anne Regina Ferreira da Costa, Vanja Joice Bispo Santos, Fernando Elias da Silva, Tarcízio Macedo, Mayara Larrys Gomes de Assis Nogueira, Carla Patrícia Serqueira Lima, | L90: 5116499 | M90: OCCA - Observatório da Ciência Cidadã na Amazônia | N90: Programa Basico de Ciências Ambientais | O90: CA | P90: Outra | Q90: Ciências Ambientais | R90: Museu Paraense Emílio Goeldi | S90: MPEG | T90: PA | U90: NO | V90: Brasil | W90: Museu Paraense Emílio Goeldi | X90: MPEG | Y90: PA | Z90: NO | AA90: Brasil | AB90: DCTI | AC90: COCAM | AD90: 25/06/2026 | AE90: 22:38:47 | AF90: 25/06/2026 | AG90: 22:39:01 | AH90: 11 | AI90: 1320300 | AJ90: 122000 | AK90: 0 | AL90: 1442300 | AM90: Museu Paraense Emílio Goeldi | AN90: MPEG | AO90: PA | AP90: NO | AQ90: Brasil | AR90: 9454867287897965 | AS90: 46202.465 | AT90: PCI2026 | AU90: Chamada CNPq/MCTI/FNDCT Nº 12/2026 - Programa PCI | AV90: Chamada: Chamada CNPq/MCTI/FNDCT Nº 12/2026 - Faixa 3: Projetos de Pesquisa vinculados a | AW90: 12/2026 | AX90: Chamada CNPq/MCTI/FNDCT Nº 12/2026 - Faixa 3: Projetos de Pesquisa vinculados a UPs Grandes (acima de 200 servidores) | AY90: 27/04/2026 | AZ90: 27/06/2026 | BA90: lis.stegmann@gmail.com | BB90: 402009/2026-6 | BC90: Lis Fernandes Stegmann | BD90: Museu Paraense Emílio Goeldi | BE90: MPEG | BF90: =IF(AND(BG90,BI90,BL90,BM90),TRUE,FALSE) -> TRUE | BG90: TRUE | BH90: 2019 | BI90: TRUE | BJ90: Faixa 3 | BK90: Faixa 3 (24 propostas) | BL90: TRUE | BM90: TRUE | BN90: TRUE | BO90: - Museu Paraense Emílio Goeldi: (Servidor público - Pesquisadora) | BP90: =IF(IFERROR(VLOOKUP(A90,[1]Planilha1!$A:$A,1,0),FALSE)=FALSE,FALSE,TRUE) -> TRUE
